Workbook

Sheet Data Sources
B2: Sheet Name | C2: Data Sources
B3: Ticker List | C3: https://www.idx.co.id/id/data-pasar/data-saham/daftar-saham/ Sector & Industry : Probe YFInance
B4: Index & IHSG (IDX-IC) | C4: https://www.idx.co.id/id/data-pasar/data-saham/indeks-saham/
B5: Ownership 1% & Classification | C5: https://www.idx.co.id/id/perusahaan-tercatat/data-kepemilikan-saham/
B6: Konglo Index | C6: https://www.perplexity.ai/computer/a/1ec049c8-dfbf-4ae1-8034-45ddd8f97f91

Sheet TICKER LIST
A1: No. | B1: Ticker | C1: Company Name | D1: Listing Date | E1: Shares | F1: Listing Board | G1: Sector Index | H1: Sector | I1: Industry
A2: 1 | B2: MGLV | C2: NexAI Digital Infrastruktur Tb | D2: 08 Jun 2021 | E2: 1.904.883.411 | F2: Akselerasi | H2: Consumer Cyclical | I2: Furnishings, Fixtures & Appliances
A3: 2 | B3: TRUE | C3: Triniti Dinamik Tbk. | D3: 10 Jun 2021 | E3: 7.571.107.860 | F3: Pengembangan | G3: IDXPROPERT | H3: Real Estate | I3: Real Estate - Development
A4: 3 | B4: LABA | C4: Green Power Group Tbk. | D4: 10 Jun 2021 | E4: 1.103.402.553 | F4: Pengembangan | G4: IDXINDUST | H4: Basic Materials | I4: Steel
A5: 4 | B5: ARCI | C5: Archi Indonesia Tbk. | D5: 28 Jun 2021 | E5: 25.235.000.000 | F5: Pengembangan | G5: IDXBASIC | H5: Basic Materials | I5: Gold
A6: 5 | B6: IPAC | C6: Era Graharealty Tbk. | D6: 30 Jun 2021 | E6: 949.868.500 | F6: Akselerasi | H6: Real Estate | I6: Real Estate Services
A7: 6 | B7: MASB | C7: Bank Multiarta Sentosa Tbk. | D7: 30 Jun 2021 | E7: 1.387.737.233 | F7: Utama | G7: IDXFINANCE | H7: Financial Services | I7: Banks - Regional
A8: 7 | B8: BMHS | C8: Bundamedik Tbk. | D8: 06 Jul 2021 | E8: 8.603.416.176 | F8: Utama | G8: IDXHEALTH | H8: Healthcare | I8: Medical Care Facilities
A9: 8 | B9: FLMC | C9: Falmaco Nonwoven Industri Tbk. | D9: 08 Jul 2021 | E9: 781.250.000 | F9: Akselerasi | H9: Consumer Defensive | I9: Household & Personal Products
A10: 9 | B10: NICL | C10: PAM Mineral Tbk. | D10: 09 Jul 2021 | E10: 10.635.644.907 | F10: Pengembangan | G10: IDXBASIC | H10: Basic Materials | I10: Other Industrial Metals & Mining
A11: 10 | B11: UVCR | C11: Trimegah Karya Pratama Tbk. | D11: 27 Jul 2021 | E11: 2.000.144.838 | F11: Pengembangan | G11: IDXTECHNO | H11: Technology | I11: Software - Application
A12: 11 | B12: BUKA | C12: Bukalapak.com Tbk. | D12: 06 Agt 2021 | E12: 103.167.090.767 | F12: Ekonomi Baru | G12: IDXTECHNO | H12: Consumer Cyclical | I12: Internet Retail
A13: 12 | B13: HAIS | C13: Hasnur Internasional Shipping | D13: 01 Sep 2021 | E13: 2.626.250.000 | F13: Pengembangan | G13: IDXTRANS | H13: Industrials | I13: Marine Shipping
A14: 13 | B14: OILS | C14: Indo Oil Perkasa Tbk. | D14: 06 Sep 2021 | E14: 454.056.563 | F14: Pengembangan | G14: IDXNONCYC | H14: Consumer Defensive | I14: Packaged Foods
A15: 14 | B15: GPSO | C15: Geoprima Solusi Tbk. | D15: 06 Sep 2021 | E15: 733.415.103 | F15: Pengembangan | G15: IDXINDUST | H15: Technology | I15: Scientific & Technical Instruments
A16: 15 | B16: MCOL | C16: Prima Andalan Mandiri Tbk. | D16: 07 Sep 2021 | E16: 3.555.560.000 | F16: Utama | G16: IDXENERGY | H16: Energy | I16: Thermal Coal
A17: 16 | B17: RSGK | C17: Kedoya Adyaraya Tbk. | D17: 08 Sep 2021 | E17: 929.675.000 | F17: Pengembangan | G17: IDXHEALTH | H17: Healthcare | I17: Medical Care Facilities
A18: 17 | B18: RUNS | C18: Global Sukses Solusi Tbk. | D18: 08 Sep 2021 | E18: 983.557.875 | F18: Akselerasi | H18: Technology | I18: Software - Application
A19: 18 | B19: SBMA | C19: Surya Biru Murni Acetylene Tbk | D19: 08 Sep 2021 | E19: 929.926.282 | F19: Pengembangan | G19: IDXBASIC | H19: Basic Materials | I19: Chemicals
A20: 19 | B20: CMNT | C20: Cemindo Gemilang Tbk. | D20: 08 Sep 2021 | E20: 17.125.504.000 | F20: Pengembangan | G20: IDXBASIC | H20: Basic Materials | I20: Building Materials
A21: 20 | B21: GTSI | C21: GTS Internasional Tbk. | D21: 08 Sep 2021 | E21: 15.819.142.767 | F21: Pengembangan | G21: IDXENERGY | H21: Industrials | I21: Marine Shipping
A22: 21 | B22: IDEA | C22: Idea Indonesia Akademi Tbk. | D22: 09 Sep 2021 | E22: 1.062.437.500 | F22: Akselerasi | H22: Consumer Defensive | I22: Education & Training Services
A23: 22 | B23: KUAS | C23: Ace Oldfields Tbk. | D23: 25 Okt 2021 | E23: 1.292.808.150 | F23: Pengembangan | G23: IDXINDUST | H23: Industrials | I23: Building Products & Equipment
A24: 23 | B24: BOBA | C24: Formosa Ingredient Factory Tbk | D24: 01 Nov 2021 | E24: 1.155.750.000 | F24: Pengembangan | G24: IDXNONCYC | H24: Consumer Defensive | I24: Packaged Foods
A25: 24 | B25: MTEL | C25: Dayamitra Telekomunikasi Tbk. | D25: 22 Nov 2021 | E25: 83.559.677.444 | F25: Utama | G25: IDXINFRA | H25: Communication Services | I25: Telecom Services
A26: 25 | B26: DEPO | C26: Caturkarda Depo Bangunan Tbk. | D26: 25 Nov 2021 | E26: 6.790.000.000 | F26: Pengembangan | G26: IDXCYCLIC | H26: Consumer Cyclical | I26: Home Improvement Retail
A27: 26 | B27: BINO | C27: Perma Plasindo Tbk. | D27: 25 Nov 2021 | E27: 2.275.316.111 | F27: Pengembangan | G27: IDXINDUST | H27: Industrials | I27: Business Equipment & Supplies
A28: 27 | B28: CMRY | C28: Cisarua Mountain Dairy Tbk. | D28: 06 Des 2021 | E28: 7.934.683.000 | F28: Utama | G28: IDXNONCYC | H28: Consumer Defensive | I28: Packaged Foods
A29: 28 | B29: WGSH | C29: Wira Global Solusi Tbk. | D29: 06 Des 2021 | E29: 2.085.000.000 | F29: Akselerasi | H29: Technology | I29: Software - Infrastructure
A30: 29 | B30: TAYS | C30: Jaya Swarasa Agung Tbk. | D30: 06 Des 2021 | E30: 1.098.920.000 | F30: Pengembangan | G30: IDXNONCYC | H30: Consumer Defensive | I30: Packaged Foods
A31: 30 | B31: WMPP | C31: Widodo Makmur Perkasa Tbk. | D31: 06 Des 2021 | E31: 29.419.000.000 | F31: Pemantauan Khusus | G31: IDXNONCYC | H31: Industrials | I31: Conglomerates
A32: 31 | B32: RMKE | C32: RMK Energy Tbk. | D32: 07 Des 2021 | E32: 21.875.000.000 | F32: Utama | G32: IDXENERGY | H32: Energy | I32: Thermal Coal
A33: 32 | B33: OBMD | C33: OBM Drilchem Tbk. | D33: 08 Des 2021 | E33: 805.992.931 | F33: Pengembangan | G33: IDXBASIC | H33: Basic Materials | I33: Specialty Chemicals
A34: 33 | B34: AVIA | C34: Avia Avian Tbk. | D34: 09 Mar 2026 | E34: 61.953.555.600 | G34: IDXBASIC | H34: Basic Materials | I34: Specialty Chemicals
A35: 34 | B35: IPPE | C35: Indo Pureco Pratama Tbk. | D35: 09 Des 2021 | E35: 4.600.000.000 | F35: Pemantauan Khusus | G35: IDXNONCYC | H35: Consumer Defensive | I35: Packaged Foods
A36: 35 | B36: NASI | C36: Wahana Inti Makmur Tbk. | D36: 13 Des 2021 | E36: 807.400.000 | F36: Pengembangan | G36: IDXNONCYC | H36: Consumer Defensive | I36: Farm Products
A37: 36 | B37: BSML | C37: Bintang Samudera Mandiri Lines | D37: 16 Des 2021 | E37: 1.850.225.000 | F37: Pengembangan | G37: IDXENERGY | H37: Industrials | I37: Marine Shipping
A38: 37 | B38: DRMA | C38: Dharma Polimetal Tbk. | D38: 20 Des 2021 | E38: 4.705.882.300 | F38: Utama | G38: IDXCYCLIC | H38: Consumer Cyclical | I38: Auto Parts
A39: 38 | B39: ADMR | C39: Alamtri Minerals Indonesia Tbk | D39: 03 Jan 2022 | E39: 40.882.331.500 | F39: Utama | G39: IDXENERGY | H39: Basic Materials | I39: Coking Coal
A40: 39 | B40: SEMA | C40: Semacom Integrated Tbk. | D40: 10 Jan 2022 | E40: 1.347.258.842 | F40: Pengembangan | G40: IDXENERGY | H40: Industrials | I40: Specialty Industrial Machinery
A41: 40 | B41: ASLC | C41: Autopedia Sukses Lestari Tbk. | D41: 25 Jan 2022 | E41: 12.746.354.780 | F41: Pengembangan | G41: IDXCYCLIC | H41: Consumer Cyclical | I41: Auto & Truck Dealerships
A42: 41 | B42: NETV | C42: MDTV Media Technologies Tbk. | D42: 26 Jan 2022 | E42: 41.360.517.722 | F42: Pengembangan | G42: IDXCYCLIC | H42: Communication Services | I42: Broadcasting
A43: 42 | B43: BAUT | C43: Mitra Angkasa Sejahtera Tbk. | D43: 28 Jan 2022 | E43: 4.800.182.969 | F43: Pemantauan Khusus | G43: IDXCYCLIC | H43: Industrials | I43: Tools & Accessories
A44: 43 | B44: ENAK | C44: Champ Resto Indonesia Tbk. | D44: 08 Feb 2022 | E44: 2.166.666.800 | F44: Pengembangan | G44: IDXCYCLIC | H44: Consumer Cyclical | I44: Restaurants
A45: 44 | B45: NTBK | C45: Nusatama Berkah Tbk. | D45: 09 Feb 2022 | E45: 2.700.064.877 | F45: Pengembangan | G45: IDXINDUST | H45: Industrials | I45: Farm & Heavy Construction Machinery
A46: 45 | B46: SMKM | C46: Sumber Mas Konstruksi Tbk. | D46: 09 Mar 2022 | E46: 1.253.000.000 | F46: Akselerasi | H46: Industrials | I46: Engineering & Construction
A47: 46 | B47: STAA | C47: Sumber Tani Agung Resources Tb | D47: 10 Mar 2022 | E47: 10.903.372.600 | F47: Utama | G47: IDXNONCYC | H47: Consumer Defensive | I47: Farm Products
A48: 47 | B48: NANO | C48: Nanotech Indonesia Global Tbk. | D48: 10 Mar 2022 | E48: 4.285.440.269 | F48: Akselerasi | H48: Healthcare | I48: Medical Devices
A49: 48 | B49: BIKE | C49: Bhineka Inovasi Ketahanan Ener | D49: 21 Mar 2022 | E49: 1.293.916.404 | F49: Pemantauan Khusus | G49: IDXCYCLIC | H49: Consumer Cyclical | I49: Leisure
A50: 49 | B50: WIRG | C50: WIR ASIA Tbk. | D50: 04 Apr 2022 | E50: 11.938.622.394 | F50: Pengembangan | G50: IDXTECHNO | H50: Technology | I50: Information Technology Services
A51: 50 | B51: SICO | C51: Sigma Energy Compressindo Tbk. | D51: 08 Apr 2022 | E51: 910.077.764 | F51: Pengembangan | G51: IDXENERGY | H51: Energy | I51: Oil & Gas Equipment & Services
A52: 51 | B52: GOTO | C52: GoTo Gojek Tokopedia Tbk. | D52: 11 Apr 2022 | E52: 1.140.573.267.220 | F52: Pengembangan | G52: IDXTECHNO | H52: Technology | I52: Software - Infrastructure
A53: 52 | B53: TLDN | C53: Teladan Prima Agro Tbk. | D53: 12 Apr 2022 | E53: 12.946.530.200 | F53: Utama | G53: IDXNONCYC | H53: Consumer Defensive | I53: Farm Products
A54: 53 | B54: MTMH | C54: Murni Sadar Tbk. | D54: 20 Apr 2022 | E54: 2.068.526.950 | F54: Utama | G54: IDXHEALTH | H54: Healthcare | I54: Medical Care Facilities
A55: 54 | B55: WINR | C55: Winner Nusantara Jaya Tbk. | D55: 25 Apr 2022 | E55: 5.235.316.030 | F55: Pemantauan Khusus | G55: IDXPROPERT | H55: Real Estate | I55: Real Estate - Development
A56: 55 | B56: IBOS | C56: Indo Boga Sukses Tbk. | D56: 25 Apr 2022 | E56: 8.065.789.529 | F56: Akselerasi | H56: Consumer Cyclical | I56: Restaurants
A57: 56 | B57: OLIV | C57: Atlas Nexus Group Tbk. | D57: 17 Mei 2022 | E57: 1.900.073.314 | F57: Akselerasi | H57: Consumer Cyclical | I57: Furnishings, Fixtures & Appliances
A58: 57 | B58: ASHA | C58: Cilacap Samudera Fishing Indus | D58: 27 Mei 2022 | E58: 5.000.000.000 | F58: Pengembangan | G58: IDXNONCYC | H58: Consumer Defensive | I58: Farm Products
A59: 58 | B59: SWID | C59: Saraswanti Indoland Developmen | D59: 07 Jul 2022 | E59: 5.385.019.201 | F59: Pengembangan | G59: IDXCYCLIC | H59: Real Estate | I59: Real Estate - Development
A60: 59 | B60: TRGU | C60: Cerestar Indonesia Tbk. | D60: 08 Jul 2022 | E60: 7.945.412.700 | F60: Utama | G60: IDXNONCYC | H60: Consumer Defensive | I60: Packaged Foods
A61: 60 | B61: ARKO | C61: Arkora Hydro Tbk. | D61: 08 Jul 2022 | E61: 2.928.495.000 | F61: Pengembangan | G61: IDXINFRA | H61: Utilities | I61: Utilities - Renewable
A62: 61 | B62: CHEM | C62: Chemstar Indonesia Tbk. | D62: 08 Jul 2022 | E62: 1.700.014.594 | F62: Pengembangan | G62: IDXBASIC | H62: Basic Materials | I62: Specialty Chemicals
A63: 62 | B63: DEWI | C63: Dewi Shri Farmindo Tbk. | D63: 18 Jul 2022 | E63: 2.000.000.000 | F63: Pengembangan | G63: IDXNONCYC | H63: Consumer Defensive | I63: Farm Products
A64: 63 | B64: AXIO | C64: Tera Data Indonusa Tbk. | D64: 20 Jul 2022 | E64: 5.840.126.500 | F64: Pengembangan | G64: IDXTECHNO | H64: Technology | I64: Computer Hardware
A65: 64 | B65: KRYA | C65: Bangun Karya Perkasa Jaya Tbk. | D65: 25 Jul 2022 | E65: 1.663.943.474 | F65: Pengembangan | G65: IDXINFRA | H65: Industrials | I65: Engineering & Construction
A66: 65 | B66: HATM | C66: Habco Trans Maritima Tbk. | D66: 26 Jul 2022 | E66: 8.680.000.000 | F66: Utama | G66: IDXTRANS | H66: Industrials | I66: Marine Shipping
A67: 66 | B67: RCCC | C67: Utama Radar Cahaya Tbk. | D67: 02 Agt 2022 | E67: 787.500.000 | F67: Akselerasi | H67: Industrials | I67: Trucking
A68: 67 | B68: GULA | C68: Aman Agrindo Tbk. | D68: 03 Agt 2022 | E68: 1.070.362.500 | F68: Pengembangan | G68: IDXNONCYC | H68: Consumer Defensive | I68: Farm Products
A69: 68 | B69: JARR | C69: Jhonlin Agro Raya Tbk. | D69: 04 Agt 2022 | E69: 9.230.665.050 | F69: Utama | G69: IDXNONCYC | H69: Consumer Defensive | I69: Farm Products
A70: 69 | B70: AMMS | C70: Agung Menjangan Mas Tbk. | D70: 04 Agt 2022 | E70: 1.235.296.802 | F70: Akselerasi | H70: Consumer Defensive | I70: Farm Products
A71: 70 | B71: RAFI | C71: Sari Kreasi Boga Tbk. | D71: 05 Agt 2022 | E71: 3.128.140.475 | F71: Pemantauan Khusus | G71: IDXCYCLIC | H71: Consumer Cyclical | I71: Restaurants
A72: 71 | B72: KKES | C72: Kusuma Kemindo Sentosa Tbk. | D72: 08 Agt 2022 | E72: 1.500.000.000 | F72: Pengembangan | G72: IDXBASIC | H72: Basic Materials | I72: Specialty Chemicals
A73: 72 | B73: ELPI | C73: Pelayaran Nasional Ekalya Purn | D73: 08 Agt 2022 | E73: 9.524.420.000 | F73: Utama | G73: IDXTRANS | H73: Industrials | I73: Marine Shipping
A74: 73 | B74: EURO | C74: Estee Gold Feet Tbk. | D74: 08 Agt 2022 | E74: 2.548.826.428 | F74: Akselerasi | H74: Consumer Defensive | I74: Household & Personal Products
A75: 74 | B75: KLIN | C75: Klinko Karya Imaji Tbk. | D75: 09 Agt 2022 | E75: 1.307.530.330 | F75: Akselerasi | H75: Consumer Cyclical | I75: Home Improvement Retail
A76: 75 | B76: TOOL | C76: Rohartindo Nusantara Luas Tbk. | D76: 09 Agt 2022 | E76: 2.050.020.320 | F76: Pengembangan | G76: IDXCYCLIC | H76: Consumer Cyclical | I76: Furnishings, Fixtures & Appliances
A77: 76 | B77: BUAH | C77: Segar Kumala Indonesia Tbk. | D77: 09 Agt 2022 | E77: 2.000.000.000 | F77: Pengembangan | G77: IDXNONCYC | H77: Consumer Defensive | I77: Food Distribution
A78: 77 | B78: CRAB | C78: Toba Surimi Industries Tbk. | D78: 10 Agt 2022 | E78: 1.950.000.000 | F78: Pengembangan | G78: IDXNONCYC | H78: Consumer Defensive | I78: Packaged Foods
A79: 78 | B79: MEDS | C79: Hetzer Medical Indonesia Tbk. | D79: 10 Agt 2022 | E79: 1.562.500.000 | F79: Pengembangan | G79: IDXHEALTH | H79: Healthcare | I79: Medical Instruments & Supplies
A80: 79 | B80: COAL | C80: Black Diamond Resources Tbk. | D80: 07 Sep 2022 | E80: 6.250.000.000 | F80: Pengembangan | G80: IDXENERGY | H80: Energy | I80: Thermal Coal
A81: 80 | B81: PRAY | C81: Famon Awal Bros Sedaya Tbk. | D81: 08 Nov 2022 | E81: 13.959.422.300 | F81: Utama | G81: IDXHEALTH | H81: Healthcare | I81: Medical Care Facilities
A82: 81 | B82: CBUT | C82: Citra Borneo Utama Tbk. | D82: 08 Nov 2022 | E82: 3.125.000.000 | F82: Utama | G82: IDXNONCYC | H82: Consumer Defensive | I82: Packaged Foods
A83: 82 | B83: BELI | C83: Global Digital Niaga Tbk. | D83: 08 Nov 2022 | E83: 137.218.985.689 | F83: Pengembangan | G83: IDXTECHNO | H83: Consumer Cyclical | I83: Internet Retail
A84: 83 | B84: MKTR | C84: Menthobi Karyatama Raya Tbk. | D84: 08 Nov 2022 | E84: 12.060.428.584 | F84: Utama | G84: IDXNONCYC | H84: Consumer Defensive | I84: Farm Products
A85: 84 | B85: OMED | C85: Jayamas Medica Industri Tbk. | D85: 08 Nov 2022 | E85: 27.058.850.000 | F85: Utama | G85: IDXHEALTH | H85: Healthcare | I85: Medical Instruments & Supplies
A86: 85 | B86: BSBK | C86: Wulandari Bangun Laksana Tbk. | D86: 08 Nov 2022 | E86: 25.091.882.375 | F86: Pengembangan | G86: IDXPROPERT | H86: Real Estate | I86: Real Estate - Development
A87: 86 | B87: PDPP | C87: Primadaya Plastisindo Tbk. | D87: 09 Nov 2022 | E87: 3.061.341.438 | F87: Pengembangan | G87: IDXBASIC | H87: Consumer Cyclical | I87: Packaging & Containers
... A89: 88 | B89: ZATA | C89: Bersama Zatta Jaya Tbk. | D89: 10 Nov 2022 | E89: 8.496.000.000 | F89: Pengembangan | G89: IDXCYCLIC | H89: Consumer Cyclical | I89: Apparel Retail
A90: 89 | B90: NINE | C90: Techno9 Indonesia Tbk. | D90: 05 Des 2022 | E90: 2.157.000.000 | F90: Akselerasi | H90: Technology | I90: Information Technology Services
A91: 90 | B91: MMIX | C91: Multi Medika Internasional Tbk | D91: 06 Des 2022 | E91: 4.800.425.380 | F91: Pengembangan | G91: IDXHEALTH | H91: Healthcare | I91: Pharmaceutical Retailers
A92: 91 | B92: PADA | C92: Personel Alih Daya Tbk. | D92: 08 Des 2022 | E92: 3.150.000.000 | F92: Pengembangan | G92: IDXINDUST | H92: Industrials | I92: Staffing & Employment Services
A93: 92 | B93: ISAP | C93: Isra Presisi Indonesia Tbk. | D93: 09 Des 2022 | E93: 4.020.356.426 | F93: Akselerasi | H93: Industrials | I93: Metal Fabrication
A94: 93 | B94: VTNY | C94: Venteny Fortuna International | D94: 15 Des 2022 | E94: 6.265.193.445 | F94: Pengembangan | G94: IDXFINANCE | H94: Industrials | I94: Staffing & Employment Services
A95: 94 | B95: SOUL | C95: Mitra Tirta Buwana Tbk. | D95: 06 Jan 2023 | E95: 1.082.526.223 | F95: Akselerasi | H95: Industrials | I95: Specialty Business Services
A96: 95 | B96: ELIT | C96: Data Sinergitama Jaya Tbk. | D96: 06 Jan 2023 | E96: 2.031.643.057 | F96: Pengembangan | G96: IDXTECHNO | H96: Technology | I96: Information Technology Services
A97: 96 | B97: BEER | C97: Jobubu Jarum Minahasa Tbk. | D97: 06 Jan 2023 | E97: 4.000.000.000 | F97: Pengembangan | G97: IDXNONCYC | H97: Consumer Defensive | I97: Beverages - Wineries & Distilleries
A98: 97 | B98: CBPE | C98: Citra Buana Prasida Tbk. | D98: 06 Jan 2023 | E98: 1.356.250.000 | F98: Pengembangan | G98: IDXPROPERT | H98: Real Estate | I98: Real Estate - Development
A99: 98 | B99: SUNI | C99: Sunindo Pratama Tbk. | D99: 09 Jan 2023 | E99: 2.500.000.000 | F99: Utama | G99: IDXENERGY | H99: Energy | I99: Oil & Gas Equipment & Services
A100: 99 | B100: CBRE | C100: Cakra Buana Resources Energi T | D100: 09 Jan 2023 | E100: 4.538.067.441 | F100: Pengembangan | G100: IDXENERGY | H100: Industrials | I100: Marine Shipping
A101: 100 | B101: WINE | C101: Hatten Bali Tbk. | D101: 10 Jan 2023 | E101: 2.710.000.000 | F101: Pengembangan | G101: IDXNONCYC | H101: Consumer Defensive | I101: Beverages - Wineries & Distilleries
...

Sheet OWNERSHIP 1%
A1: Date | B1: Ticker | C1: Company Name | D1: Investor Name | E1: Investor Classification | F1: Local / Foreign | G1: Nationality | H1: Domicile | I1: Holdings (Scripless) | J1: Holdings (Scrip) | K1: Total Holding Shares | L1: Percentage (%) | M1: Free Float (%) | N1: Classic HHI | O1: Concentration Ratio Top 1 (CR1) | P1: Concentration Ratio Top 3 (CR3) | Q1: Holder | R1: CCS | S1: Ownership Type | T1: CCS Category | U1: Dedup Flag (helper) | V1: Deduped % (helper) | W1: Rank in Code (helper) | X1: Tie-Broken % (helper)
A2: 46265 | B2: AADI | C2: ADARO ANDALAN INDONESIA Tbk | D2: PT PERSADA CAPITAL INVESTAMA | E2: Corporate | F2: L | H2: INDONESIA | I2: 119887170 | J2: 0 | K2: 119887170 | L2: 1.54 | M2: =IFERROR(_xlfn.XLOOKUP($B2,'Ownership Metrics'!$A:$A,'Ownership Metrics'!$B:$B),"") -> 20.3 | N2: =IFERROR(_xlfn.XLOOKUP($B2,'Ownership Metrics'!$A:$A,'Ownership Metrics'!$C:$C),"") -> 2013 | O2: =IFERROR(_xlfn.XLOOKUP($B2,'Ownership Metrics'!$A:$A,'Ownership Metrics'!$D:$D),"") -> 41.1 | P2: =IFERROR(_xlfn.XLOOKUP($B2,'Ownership Metrics'!$A:$A,'Ownership Metrics'!$E:$E),"") -> 62.3 | Q2: =IFERROR(_xlfn.XLOOKUP($B2,'Ownership Metrics'!$A:$A,'Ownership Metrics'!$F:$F),"") -> 10 | R2: =IFERROR(_xlfn.XLOOKUP($B2,'Ownership Metrics'!$A:$A,'Ownership Metrics'!$G:$G),"") -> 41 | S2: =IFERROR(_xlfn.XLOOKUP($B2,'Ownership Metrics'!$A:$A,'Ownership Metrics'!$H:$H),"") -> Oligopoli | T2: =IFERROR(_xlfn.XLOOKUP($B2,'Ownership Metrics'!$A:$A,'Ownership Metrics'!$I:$I),"") -> Sedang | U2: =IF(COUNTIFS($B$2:$B2,$B2,$D$2:$D2,$D2)=1,1,0) -> 1 | V2: =SUMIFS($L$2:$L$10000,$B$2:$B$10000,$B2,$D$2:$D$10000,$D2) -> 1.54 | W2: =COUNTIFS($B$2:$B$10000,$B2,$U$2:$U$10000,1,$X$2:$X$10000,">"&$X2)+1 -> 8 | X2: =$V2-(ROW()*0.0000000001) -> 1.54
A3: 46265 | B3: AADI | C3: ADARO ANDALAN INDONESIA Tbk | D3: SARATOGA INVESTAMA SEDAYA TBK | E3: Private Bank | F3: L | H3: INDONESIA | I3: 340897429 | J3: 0 | K3: 340897429 | L3: 4.38 | M3: =IFERROR(_xlfn.XLOOKUP($B3,'Ownership Metrics'!$A:$A,'Ownership Metrics'!$B:$B),"") -> 20.3 | N3: =IFERROR(_xlfn.XLOOKUP($B3,'Ownership Metrics'!$A:$A,'Ownership Metrics'!$C:$C),"") -> 2013 | O3: =IFERROR(_xlfn.XLOOKUP($B3,'Ownership Metrics'!$A:$A,'Ownership Metrics'!$D:$D),"") -> 41.1 | P3: =IFERROR(_xlfn.XLOOKUP($B3,'Ownership Metrics'!$A:$A,'Ownership Metrics'!$E:$E),"") -> 62.3 | Q3: =IFERROR(_xlfn.XLOOKUP($B3,'Ownership Metrics'!$A:$A,'Ownership Metrics'!$F:$F),"") -> 10 | R3: =IFERROR(_xlfn.XLOOKUP($B3,'Ownership Metrics'!$A:$A,'Ownership Metrics'!$G:$G),"") -> 41 | S3: =IFERROR(_xlfn.XLOOKUP($B3,'Ownership Metrics'!$A:$A,'Ownership Metrics'!$H:$H),"") -> Oligopoli | T3: =IFERROR(_xlfn.XLOOKUP($B3,'Ownership Metrics'!$A:$A,'Ownership Metrics'!$I:$I),"") -> Sedang | U3: =IF(COUNTIFS($B$2:$B3,$B3,$D$2:$D3,$D3)=1,1,0) -> 1 | V3: =SUMIFS($L$2:$L$10000,$B$2:$B$10000,$B3,$D$2:$D$10000,$D3) -> 4.38 | W3: =COUNTIFS($B$2:$B$10000,$B3,$U$2:$U$10000,1,$X$2:$X$10000,">"&$X3)+1 -> 4 | X3: =$V3-(ROW()*0.0000000001) -> 4.38
A4: 46265 | B4: AADI | C4: ADARO ANDALAN INDONESIA Tbk | D4: PT TRINUGRAHA THOHIR | E4: Corporate | F4: L | H4: INDONESIA | I4: 89926520 | J4: 0 | K4: 89926520 | L4: 1.15 | M4: =IFERROR(_xlfn.XLOOKUP($B4,'Ownership Metrics'!$A:$A,'Ownership Metrics'!$B:$B),"") -> 20.3 | N4: =IFERROR(_xlfn.XLOOKUP($B4,'Ownership Metrics'!$A:$A,'Ownership Metrics'!$C:$C),"") -> 2013 | O4: =IFERROR(_xlfn.XLOOKUP($B4,'Ownership Metrics'!$A:$A,'Ownership Metrics'!$D:$D),"") -> 41.1 | P4: =IFERROR(_xlfn.XLOOKUP($B4,'Ownership Metrics'!$A:$A,'Ownership Metrics'!$E:$E),"") -> 62.3 | Q4: =IFERROR(_xlfn.XLOOKUP($B4,'Ownership Metrics'!$A:$A,'Ownership Metrics'!$F:$F),"") -> 10 | R4: =IFERROR(_xlfn.XLOOKUP($B4,'Ownership Metrics'!$A:$A,'Ownership Metrics'!$G:$G),"") -> 41 | S4: =IFERROR(_xlfn.XLOOKUP($B4,'Ownership Metrics'!$A:$A,'Ownership Metrics'!$H:$H),"") -> Oligopoli | T4: =IFERROR(_xlfn.XLOOKUP($B4,'Ownership Metrics'!$A:$A,'Ownership Metrics'!$I:$I),"") -> Sedang | U4: =IF(COUNTIFS($B$2:$B4,$B4,$D$2:$D4,$D4)=1,1,0) -> 1 | V4: =SUMIFS($L$2:$L$10000,$B$2:$B$10000,$B4,$D$2:$D$10000,$D4) -> 1.15 | W4: =COUNTIFS($B$2:$B$10000,$B4,$U$2:$U$10000,1,$X$2:$X$10000,">"&$X4)+1 -> 10 | X4: =$V4-(ROW()*0.0000000001) -> 1.15
A5: 46265 | B5: AADI | C5: ADARO ANDALAN INDONESIA Tbk | D5: ADARO STRATEGIC INVESTMENTS | E5: Corporate | F5: L | H5: INDONESIA | I5: 3200142830 | J5: 0 | K5: 3200142830 | L5: 41.1 | M5: =IFERROR(_xlfn.XLOOKUP($B5,'Ownership Metrics'!$A:$A,'Ownership Metrics'!$B:$B),"") -> 20.3 | N5: =IFERROR(_xlfn.XLOOKUP($B5,'Ownership Metrics'!$A:$A,'Ownership Metrics'!$C:$C),"") -> 2013 | O5: =IFERROR(_xlfn.XLOOKUP($B5,'Ownership Metrics'!$A:$A,'Ownership Metrics'!$D:$D),"") -> 41.1 | P5: =IFERROR(_xlfn.XLOOKUP($B5,'Ownership Metrics'!$A:$A,'Ownership Metrics'!$E:$E),"") -> 62.3 | Q5: =IFERROR(_xlfn.XLOOKUP($B5,'Ownership Metrics'!$A:$A,'Ownership Metrics'!$F:$F),"") -> 10 | R5: =IFERROR(_xlfn.XLOOKUP($B5,'Ownership Metrics'!$A:$A,'Ownership Metrics'!$G:$G),"") -> 41 | S5: =IFERROR(_xlfn.XLOOKUP($B5,'Ownership Metrics'!$A:$A,'Ownership Metrics'!$H:$H),"") -> Oligopoli | T5: =IFERROR(_xlfn.XLOOKUP($B5,'Ownership Metrics'!$A:$A,'Ownership Metrics'!$I:$I),"") -> Sedang | U5: =IF(COUNTIFS($B$2:$B5,$B5,$D$2:$D5,$D5)=1,1,0) -> 1 | V5: =SUMIFS($L$2:$L$10000,$B$2:$B$10000,$B5,$D$2:$D$10000,$D5) -> 41.1 | W5: =COUNTIFS($B$2:$B$10000,$B5,$U$2:$U$10000,1,$X$2:$X$10000,">"&$X5)+1 -> 1 | X5: =$V5-(ROW()*0.0000000001) -> 41.1
A6: 46265 | B6: AADI | C6: ADARO ANDALAN INDONESIA Tbk | D6: ALAMTRI RESOURCES INDONESIA TBK PT | E6: Corporate | F6: L | H6: INDONESIA | I6: 1197023942 | J6: 0 | K6: 1197023942 | L6: 15.37 | M6: =IFERROR(_xlfn.XLOOKUP($B6,'Ownership Metrics'!$A:$A,'Ownership Metrics'!$B:$B),"") -> 20.3 | N6: =IFERROR(_xlfn.XLOOKUP($B6,'Ownership Metrics'!$A:$A,'Ownership Metrics'!$C:$C),"") -> 2013 | O6: =IFERROR(_xlfn.XLOOKUP($B6,'Ownership Metrics'!$A:$A,'Ownership Metrics'!$D:$D),"") -> 41.1 | P6: =IFERROR(_xlfn.XLOOKUP($B6,'Ownership Metrics'!$A:$A,'Ownership Metrics'!$E:$E),"") -> 62.3 | Q6: =IFERROR(_xlfn.XLOOKUP($B6,'Ownership Metrics'!$A:$A,'Ownership Metrics'!$F:$F),"") -> 10 | R6: =IFERROR(_xlfn.XLOOKUP($B6,'Ownership Metrics'!$A:$A,'Ownership Metrics'!$G:$G),"") -> 41 | S6: =IFERROR(_xlfn.XLOOKUP($B6,'Ownership Metrics'!$A:$A,'Ownership Metrics'!$H:$H),"") -> Oligopoli | T6: =IFERROR(_xlfn.XLOOKUP($B6,'Ownership Metrics'!$A:$A,'Ownership Metrics'!$I:$I),"") -> Sedang | U6: =IF(COUNTIFS($B$2:$B6,$B6,$D$2:$D6,$D6)=1,1,0) -> 1 | V6: =SUMIFS($L$2:$L$10000,$B$2:$B$10000,$B6,$D$2:$D$10000,$D6) -> 15.37 | W6: =COUNTIFS($B$2:$B$10000,$B6,$U$2:$U$10000,1,$X$2:$X$10000,">"&$X6)+1 -> 2 | X6: =$V6-(ROW()*0.0000000001) -> 15.37
A7: 46265 | B7: AADI | C7: ADARO ANDALAN INDONESIA Tbk | D7: FTAG INVESTMENT BANK LTD | E7: Financial Institutional | F7: F | H7: MALAYSIA | I7: 100722000 | J7: 0 | K7: 100722000 | L7: 1.29 | M7: =IFERROR(_xlfn.XLOOKUP($B7,'Ownership Metrics'!$A:$A,'Ownership Metrics'!$B:$B),"") -> 20.3 | N7: =IFERROR(_xlfn.XLOOKUP($B7,'Ownership Metrics'!$A:$A,'Ownership Metrics'!$C:$C),"") -> 2013 | O7: =IFERROR(_xlfn.XLOOKUP($B7,'Ownership Metrics'!$A:$A,'Ownership Metrics'!$D:$D),"") -> 41.1 | P7: =IFERROR(_xlfn.XLOOKUP($B7,'Ownership Metrics'!$A:$A,'Ownership Metrics'!$E:$E),"") -> 62.3 | Q7: =IFERROR(_xlfn.XLOOKUP($B7,'Ownership Metrics'!$A:$A,'Ownership Metrics'!$F:$F),"") -> 10 | R7: =IFERROR(_xlfn.XLOOKUP($B7,'Ownership Metrics'!$A:$A,'Ownership Metrics'!$G:$G),"") -> 41 | S7: =IFERROR(_xlfn.XLOOKUP($B7,'Ownership Metrics'!$A:$A,'Ownership Metrics'!$H:$H),"") -> Oligopoli | T7: =IFERROR(_xlfn.XLOOKUP($B7,'Ownership Metrics'!$A:$A,'Ownership Metrics'!$I:$I),"") -> Sedang | U7: =IF(COUNTIFS($B$2:$B7,$B7,$D$2:$D7,$D7)=1,1,0) -> 1 | V7: =SUMIFS($L$2:$L$10000,$B$2:$B$10000,$B7,$D$2:$D$10000,$D7) -> 1.29 | W7: =COUNTIFS($B$2:$B$10000,$B7,$U$2:$U$10000,1,$X$2:$X$10000,">"&$X7)+1 -> 9 | X7: =$V7-(ROW()*0.0000000001) -> 1.29
A8: 46265 | B8: AADI | C8: ADARO ANDALAN INDONESIA Tbk | D8: GARIBALDI THOHIR | E8: Individual | F8: L | G8: INDONESIAN | H8: INDONESIA | I8: 454011607 | J8: 0 | K8: 454011607 | L8: 5.83 | M8: =IFERROR(_xlfn.XLOOKUP($B8,'Ownership Metrics'!$A:$A,'Ownership Metrics'!$B:$B),"") -> 20.3 | N8: =IFERROR(_xlfn.XLOOKUP($B8,'Ownership Metrics'!$A:$A,'Ownership Metrics'!$C:$C),"") -> 2013 | O8: =IFERROR(_xlfn.XLOOKUP($B8,'Ownership Metrics'!$A:$A,'Ownership Metrics'!$D:$D),"") -> 41.1 | P8: =IFERROR(_xlfn.XLOOKUP($B8,'Ownership Metrics'!$A:$A,'Ownership Metrics'!$E:$E),"") -> 62.3 | Q8: =IFERROR(_xlfn.XLOOKUP($B8,'Ownership Metrics'!$A:$A,'Ownership Metrics'!$F:$F),"") -> 10 | R8: =IFERROR(_xlfn.XLOOKUP($B8,'Ownership Metrics'!$A:$A,'Ownership Metrics'!$G:$G),"") -> 41 | S8: =IFERROR(_xlfn.XLOOKUP($B8,'Ownership Metrics'!$A:$A,'Ownership Metrics'!$H:$H),"") -> Oligopoli | T8: =IFERROR(_xlfn.XLOOKUP($B8,'Ownership Metrics'!$A:$A,'Ownership Metrics'!$I:$I),"") -> Sedang | U8: =IF(COUNTIFS($B$2:$B8,$B8,$D$2:$D8,$D8)=1,1,0) -> 1 | V8: =SUMIFS($L$2:$L$10000,$B$2:$B$10000,$B8,$D$2:$D$10000,$D8) -> 5.83 | W8: =COUNTIFS($B$2:$B$10000,$B8,$U$2:$U$10000,1,$X$2:$X$10000,">"&$X8)+1 -> 3 | X8: =$V8-(ROW()*0.0000000001) -> 5.83
A9: 46265 | B9: AADI | C9: ADARO ANDALAN INDONESIA Tbk | D9: IR. T. PERMADI RACHMAT | E9: Individual | F9: L | G9: INDONESIAN | H9: INDONESIA | I9: 271164118 | J9: 0 | K9: 271164118 | L9: 3.48 | M9: =IFERROR(_xlfn.XLOOKUP($B9,'Ownership Metrics'!$A:$A,'Ownership Metrics'!$B:$B),"") -> 20.3 | N9: =IFERROR(_xlfn.XLOOKUP($B9,'Ownership Metrics'!$A:$A,'Ownership Metrics'!$C:$C),"") -> 2013 | O9: =IFERROR(_xlfn.XLOOKUP($B9,'Ownership Metrics'!$A:$A,'Ownership Metrics'!$D:$D),"") -> 41.1 | P9: =IFERROR(_xlfn.XLOOKUP($B9,'Ownership Metrics'!$A:$A,'Ownership Metrics'!$E:$E),"") -> 62.3 | Q9: =IFERROR(_xlfn.XLOOKUP($B9,'Ownership Metrics'!$A:$A,'Ownership Metrics'!$F:$F),"") -> 10 | R9: =IFERROR(_xlfn.XLOOKUP($B9,'Ownership Metrics'!$A:$A,'Ownership Metrics'!$G:$G),"") -> 41 | S9: =IFERROR(_xlfn.XLOOKUP($B9,'Ownership Metrics'!$A:$A,'Ownership Metrics'!$H:$H),"") -> Oligopoli | T9: =IFERROR(_xlfn.XLOOKUP($B9,'Ownership Metrics'!$A:$A,'Ownership Metrics'!$I:$I),"") -> Sedang | U9: =IF(COUNTIFS($B$2:$B9,$B9,$D$2:$D9,$D9)=1,1,0) -> 1 | V9: =SUMIFS($L$2:$L$10000,$B$2:$B$10000,$B9,$D$2:$D$10000,$D9) -> 3.48 | W9: =COUNTIFS($B$2:$B$10000,$B9,$U$2:$U$10000,1,$X$2:$X$10000,">"&$X9)+1 -> 6 | X9: =$V9-(ROW()*0.0000000001) -> 3.48
A10: 46265 | B10: AADI | C10: ADARO ANDALAN INDONESIA Tbk | D10: EDWIN SOERYADJAYA | E10: Individual | F10: L | G10: INDONESIAN | H10: INDONESIA | I10: 273955636 | J10: 0 | K10: 273955636 | L10: 3.52 | M10: =IFERROR(_xlfn.XLOOKUP($B10,'Ownership Metrics'!$A:$A,'Ownership Metrics'!$B:$B),"") -> 20.3 | N10: =IFERROR(_xlfn.XLOOKUP($B10,'Ownership Metrics'!$A:$A,'Ownership Metrics'!$C:$C),"") -> 2013 | O10: =IFERROR(_xlfn.XLOOKUP($B10,'Ownership Metrics'!$A:$A,'Ownership Metrics'!$D:$D),"") -> 41.1 | P10: =IFERROR(_xlfn.XLOOKUP($B10,'Ownership Metrics'!$A:$A,'Ownership Metrics'!$E:$E),"") -> 62.3 | Q10: =IFERROR(_xlfn.XLOOKUP($B10,'Ownership Metrics'!$A:$A,'Ownership Metrics'!$F:$F),"") -> 10 | R10: =IFERROR(_xlfn.XLOOKUP($B10,'Ownership Metrics'!$A:$A,'Ownership Metrics'!$G:$G),"") -> 41 | S10: =IFERROR(_xlfn.XLOOKUP($B10,'Ownership Metrics'!$A:$A,'Ownership Metrics'!$H:$H),"") -> Oligopoli | T10: =IFERROR(_xlfn.XLOOKUP($B10,'Ownership Metrics'!$A:$A,'Ownership Metrics'!$I:$I),"") -> Sedang | U10: =IF(COUNTIFS($B$2:$B10,$B10,$D$2:$D10,$D10)=1,1,0) -> 1 | V10: =SUMIFS($L$2:$L$10000,$B$2:$B$10000,$B10,$D$2:$D$10000,$D10) -> 3.52 | W10: =COUNTIFS($B$2:$B$10000,$B10,$U$2:$U$10000,1,$X$2:$X$10000,">"&$X10)+1 -> 5 | X10: =$V10-(ROW()*0.0000000001) -> 3.52
A11: 46265 | B11: AADI | C11: ADARO ANDALAN INDONESIA Tbk | D11: SANDIAGA SALAHUDDIN UNO | E11: Individual | F11: L | G11: INDONESIAN | H11: INDONESIA | I11: 159027175 | J11: 0 | K11: 159027175 | L11: 2.04 | M11: =IFERROR(_xlfn.XLOOKUP($B11,'Ownership Metrics'!$A:$A,'Ownership Metrics'!$B:$B),"") -> 20.3 | N11: =IFERROR(_xlfn.XLOOKUP($B11,'Ownership Metrics'!$A:$A,'Ownership Metrics'!$C:$C),"") -> 2013 | O11: =IFERROR(_xlfn.XLOOKUP($B11,'Ownership Metrics'!$A:$A,'Ownership Metrics'!$D:$D),"") -> 41.1 | P11: =IFERROR(_xlfn.XLOOKUP($B11,'Ownership Metrics'!$A:$A,'Ownership Metrics'!$E:$E),"") -> 62.3 | Q11: =IFERROR(_xlfn.XLOOKUP($B11,'Ownership Metrics'!$A:$A,'Ownership Metrics'!$F:$F),"") -> 10 | R11: =IFERROR(_xlfn.XLOOKUP($B11,'Ownership Metrics'!$A:$A,'Ownership Metrics'!$G:$G),"") -> 41 | S11: =IFERROR(_xlfn.XLOOKUP($B11,'Ownership Metrics'!$A:$A,'Ownership Metrics'!$H:$H),"") -> Oligopoli | T11: =IFERROR(_xlfn.XLOOKUP($B11,'Ownership Metrics'!$A:$A,'Ownership Metrics'!$I:$I),"") -> Sedang | U11: =IF(COUNTIFS($B$2:$B11,$B11,$D$2:$D11,$D11)=1,1,0) -> 1 | V11: =SUMIFS($L$2:$L$10000,$B$2:$B$10000,$B11,$D$2:$D$10000,$D11) -> 2.04 | W11: =COUNTIFS($B$2:$B$10000,$B11,$U$2:$U$10000,1,$X$2:$X$10000,">"&$X11)+1 -> 7 | X11: =$V11-(ROW()*0.0000000001) -> 2.04
A12: 46265 | B12: AALI | C12: ASTRA AGRO LESTARI Tbk | D12: PT ASTRA INTERNATIONAL TBK | E12: Corporate | F12: L | H12: INDONESIA | I12: 0 | J12: 1533682440 | K12: 1533682440 | L12: 79.68 | M12: =IFERROR(_xlfn.XLOOKUP($B12,'Ownership Metrics'!$A:$A,'Ownership Metrics'!$B:$B),"") -> 18.14 | N12: =IFERROR(_xlfn.XLOOKUP($B12,'Ownership Metrics'!$A:$A,'Ownership Metrics'!$C:$C),"") -> 6354 | O12: =IFERROR(_xlfn.XLOOKUP($B12,'Ownership Metrics'!$A:$A,'Ownership Metrics'!$D:$D),"") -> 79.68 | P12: =IFERROR(_xlfn.XLOOKUP($B12,'Ownership Metrics'!$A:$A,'Ownership Metrics'!$E:$E),"") -> 81.86 | Q12: =IFERROR(_xlfn.XLOOKUP($B12,'Ownership Metrics'!$A:$A,'Ownership Metrics'!$F:$F),"") -> 2 | R12: =IFERROR(_xlfn.XLOOKUP($B12,'Ownership Metrics'!$A:$A,'Ownership Metrics'!$G:$G),"") -> 76 | S12: =IFERROR(_xlfn.XLOOKUP($B12,'Ownership Metrics'!$A:$A,'Ownership Metrics'!$H:$H),"") -> Mayoritas | T12: =IFERROR(_xlfn.XLOOKUP($B12,'Ownership Metrics'!$A:$A,'Ownership Metrics'!$I:$I),"") -> Tinggi | U12: =IF(COUNTIFS($B$2:$B12,$B12,$D$2:$D12,$D12)=1,1,0) -> 1 | V12: =SUMIFS($L$2:$L$10000,$B$2:$B$10000,$B12,$D$2:$D$10000,$D12) -> 79.68 | W12: =COUNTIFS($B$2:$B$10000,$B12,$U$2:$U$10000,1,$X$2:$X$10000,">"&$X12)+1 -> 1 | X12: =$V12-(ROW()*0.0000000001) -> 79.68
A13: 46265 | B13: AALI | C13: ASTRA AGRO LESTARI Tbk | D13: DJS KETENAGAKERJAAN PROGRAM JAMINAN HARI TUA | E13: Insurance | F13: L | H13: INDONESIA | I13: 41979300 | J13: 0 | K13: 41979300 | L13: 2.18 | M13: =IFERROR(_xlfn.XLOOKUP($B13,'Ownership Metrics'!$A:$A,'Ownership Metrics'!$B:$B),"") -> 18.14 | N13: =IFERROR(_xlfn.XLOOKUP($B13,'Ownership Metrics'!$A:$A,'Ownership Metrics'!$C:$C),"") -> 6354 | O13: =IFERROR(_xlfn.XLOOKUP($B13,'Ownership Metrics'!$A:$A,'Ownership Metrics'!$D:$D),"") -> 79.68 | P13: =IFERROR(_xlfn.XLOOKUP($B13,'Ownership Metrics'!$A:$A,'Ownership Metrics'!$E:$E),"") -> 81.86 | Q13: =IFERROR(_xlfn.XLOOKUP($B13,'Ownership Metrics'!$A:$A,'Ownership Metrics'!$F:$F),"") -> 2 | R13: =IFERROR(_xlfn.XLOOKUP($B13,'Ownership Metrics'!$A:$A,'Ownership Metrics'!$G:$G),"") -> 76 | S13: =IFERROR(_xlfn.XLOOKUP($B13,'Ownership Metrics'!$A:$A,'Ownership Metrics'!$H:$H),"") -> Mayoritas | T13: =IFERROR(_xlfn.XLOOKUP($B13,'Ownership Metrics'!$A:$A,'Ownership Metrics'!$I:$I),"") -> Tinggi | U13: =IF(COUNTIFS($B$2:$B13,$B13,$D$2:$D13,$D13)=1,1,0) -> 1 | V13: =SUMIFS($L$2:$L$10000,$B$2:$B$10000,$B13,$D$2:$D$10000,$D13) -> 2.18 | W13: =COUNTIFS($B$2:$B$10000,$B13,$U$2:$U$10000,1,$X$2:$X$10000,">"&$X13)+1 -> 2 | X13: =$V13-(ROW()*0.0000000001) -> 2.18
A14: 46265 | B14: ABBA | C14: MAHAKA MEDIA Tbk | D14: YAYASAN BINA SEJAHTERA WARGA BULOG | I14: 0 | J14: 52975286 | K14: 52975286 | L14: 1.35 | M14: =IFERROR(_xlfn.XLOOKUP($B14,'Ownership Metrics'!$A:$A,'Ownership Metrics'!$B:$B),"") -> 25.33 | N14: =IFERROR(_xlfn.XLOOKUP($B14,'Ownership Metrics'!$A:$A,'Ownership Metrics'!$C:$C),"") -> 1915 | O14: =IFERROR(_xlfn.XLOOKUP($B14,'Ownership Metrics'!$A:$A,'Ownership Metrics'!$D:$D),"") -> 40.47 | P14: =IFERROR(_xlfn.XLOOKUP($B14,'Ownership Metrics'!$A:$A,'Ownership Metrics'!$E:$E),"") -> 61.43 | Q14: =IFERROR(_xlfn.XLOOKUP($B14,'Ownership Metrics'!$A:$A,'Ownership Metrics'!$F:$F),"") -> 10 | R14: =IFERROR(_xlfn.XLOOKUP($B14,'Ownership Metrics'!$A:$A,'Ownership Metrics'!$G:$G),"") -> 41 | S14: =IFERROR(_xlfn.XLOOKUP($B14,'Ownership Metrics'!$A:$A,'Ownership Metrics'!$H:$H),"") -> Oligopoli | T14: =IFERROR(_xlfn.XLOOKUP($B14,'Ownership Metrics'!$A:$A,'Ownership Metrics'!$I:$I),"") -> Sedang | U14: =IF(COUNTIFS($B$2:$B14,$B14,$D$2:$D14,$D14)=1,1,0) -> 1 | V14: =SUMIFS($L$2:$L$10000,$B$2:$B$10000,$B14,$D$2:$D$10000,$D14) -> 1.35 | W14: =COUNTIFS($B$2:$B$10000,$B14,$U$2:$U$10000,1,$X$2:$X$10000,">"&$X14)+1 -> 6 | X14: =$V14-(ROW()*0.0000000001) -> 1.35
A15: 46265 | B15: ABBA | C15: MAHAKA MEDIA Tbk | D15: YAYASAN ABDI BANGSA | I15: 0 | J15: 111372886 | K15: 111372886 | L15: 2.83 | M15: =IFERROR(_xlfn.XLOOKUP($B15,'Ownership Metrics'!$A:$A,'Ownership Metrics'!$B:$B),"") -> 25.33 | N15: =IFERROR(_xlfn.XLOOKUP($B15,'Ownership Metrics'!$A:$A,'Ownership Metrics'!$C:$C),"") -> 1915 | O15: =IFERROR(_xlfn.XLOOKUP($B15,'Ownership Metrics'!$A:$A,'Ownership Metrics'!$D:$D),"") -> 40.47 | P15: =IFERROR(_xlfn.XLOOKUP($B15,'Ownership Metrics'!$A:$A,'Ownership Metrics'!$E:$E),"") -> 61.43 | Q15: =IFERROR(_xlfn.XLOOKUP($B15,'Ownership Metrics'!$A:$A,'Ownership Metrics'!$F:$F),"") -> 10 | R15: =IFERROR(_xlfn.XLOOKUP($B15,'Ownership Metrics'!$A:$A,'Ownership Metrics'!$G:$G),"") -> 41 | S15: =IFERROR(_xlfn.XLOOKUP($B15,'Ownership Metrics'!$A:$A,'Ownership Metrics'!$H:$H),"") -> Oligopoli | T15: =IFERROR(_xlfn.XLOOKUP($B15,'Ownership Metrics'!$A:$A,'Ownership Metrics'!$I:$I),"") -> Sedang | U15: =IF(COUNTIFS($B$2:$B15,$B15,$D$2:$D15,$D15)=1,1,0) -> 1 | V15: =SUMIFS($L$2:$L$10000,$B$2:$B$10000,$B15,$D$2:$D$10000,$D15) -> 2.83 | W15: =COUNTIFS($B$2:$B$10000,$B15,$U$2:$U$10000,1,$X$2:$X$10000,">"&$X15)+1 -> 5 | X15: =$V15-(ROW()*0.0000000001) -> 2.83
A16: 46265 | B16: ABBA | C16: MAHAKA MEDIA Tbk | D16: MEDIAHUIS IRELAND LIMITED | I16: 0 | J16: 282886300 | K16: 282886300 | L16: 7.19 | M16: =IFERROR(_xlfn.XLOOKUP($B16,'Ownership Metrics'!$A:$A,'Ownership Metrics'!$B:$B),"") -> 25.33 | N16: =IFERROR(_xlfn.XLOOKUP($B16,'Ownership Metrics'!$A:$A,'Ownership Metrics'!$C:$C),"") -> 1915 | O16: =IFERROR(_xlfn.XLOOKUP($B16,'Ownership Metrics'!$A:$A,'Ownership Metrics'!$D:$D),"") -> 40.47 | P16: =IFERROR(_xlfn.XLOOKUP($B16,'Ownership Metrics'!$A:$A,'Ownership Metrics'!$E:$E),"") -> 61.43 | Q16: =IFERROR(_xlfn.XLOOKUP($B16,'Ownership Metrics'!$A:$A,'Ownership Metrics'!$F:$F),"") -> 10 | R16: =IFERROR(_xlfn.XLOOKUP($B16,'Ownership Metrics'!$A:$A,'Ownership Metrics'!$G:$G),"") -> 41 | S16: =IFERROR(_xlfn.XLOOKUP($B16,'Ownership Metrics'!$A:$A,'Ownership Metrics'!$H:$H),"") -> Oligopoli | T16: =IFERROR(_xlfn.XLOOKUP($B16,'Ownership Metrics'!$A:$A,'Ownership Metrics'!$I:$I),"") -> Sedang | U16: =IF(COUNTIFS($B$2:$B16,$B16,$D$2:$D16,$D16)=1,1,0) -> 1 | V16: =SUMIFS($L$2:$L$10000,$B$2:$B$10000,$B16,$D$2:$D$10000,$D16) -> 7.19 | W16: =COUNTIFS($B$2:$B$10000,$B16,$U$2:$U$10000,1,$X$2:$X$10000,">"&$X16)+1 -> 3 | X16: =$V16-(ROW()*0.0000000001) -> 7.19
A17: 46265 | B17: ABBA | C17: MAHAKA MEDIA Tbk | D17: PT BEYOND MEDIA | E17: Private Equity | F17: L | H17: INDONESIA | I17: 1592831618 | J17: 0 | K17: 1592831618 | L17: 40.47 | M17: =IFERROR(_xlfn.XLOOKUP($B17,'Ownership Metrics'!$A:$A,'Ownership Metrics'!$B:$B),"") -> 25.33 | N17: =IFERROR(_xlfn.XLOOKUP($B17,'Ownership Metrics'!$A:$A,'Ownership Metrics'!$C:$C),"") -> 1915 | O17: =IFERROR(_xlfn.XLOOKUP($B17,'Ownership Metrics'!$A:$A,'Ownership Metrics'!$D:$D),"") -> 40.47 | P17: =IFERROR(_xlfn.XLOOKUP($B17,'Ownership Metrics'!$A:$A,'Ownership Metrics'!$E:$E),"") -> 61.43 | Q17: =IFERROR(_xlfn.XLOOKUP($B17,'Ownership Metrics'!$A:$A,'Ownership Metrics'!$F:$F),"") -> 10 | R17: =IFERROR(_xlfn.XLOOKUP($B17,'Ownership Metrics'!$A:$A,'Ownership Metrics'!$G:$G),"") -> 41 | S17: =IFERROR(_xlfn.XLOOKUP($B17,'Ownership Metrics'!$A:$A,'Ownership Metrics'!$H:$H),"") -> Oligopoli | T17: =IFERROR(_xlfn.XLOOKUP($B17,'Ownership Metrics'!$A:$A,'Ownership Metrics'!$I:$I),"") -> Sedang | U17: =IF(COUNTIFS($B$2:$B17,$B17,$D$2:$D17,$D17)=1,1,0) -> 1 | V17: =SUMIFS($L$2:$L$10000,$B$2:$B$10000,$B17,$D$2:$D$10000,$D17) -> 40.47 | W17: =COUNTIFS($B$2:$B$10000,$B17,$U$2:$U$10000,1,$X$2:$X$10000,">"&$X17)+1 -> 1 | X17: =$V17-(ROW()*0.0000000001) -> 40.47
A18: 46265 | B18: ABBA | C18: MAHAKA MEDIA Tbk | D18: PT.Grid One Media | E18: Corporate | F18: L | H18: INDONESIA | I18: 43791628 | J18: 0 | K18: 43791628 | L18: 1.11 | M18: =IFERROR(_xlfn.XLOOKUP($B18,'Ownership Metrics'!$A:$A,'Ownership Metrics'!$B:$B),"") -> 25.33 | N18: =IFERROR(_xlfn.XLOOKUP($B18,'Ownership Metrics'!$A:$A,'Ownership Metrics'!$C:$C),"") -> 1915 | O18: =IFERROR(_xlfn.XLOOKUP($B18,'Ownership Metrics'!$A:$A,'Ownership Metrics'!$D:$D),"") -> 40.47 | P18: =IFERROR(_xlfn.XLOOKUP($B18,'Ownership Metrics'!$A:$A,'Ownership Metrics'!$E:$E),"") -> 61.43 | Q18: =IFERROR(_xlfn.XLOOKUP($B18,'Ownership Metrics'!$A:$A,'Ownership Metrics'!$F:$F),"") -> 10 | R18: =IFERROR(_xlfn.XLOOKUP($B18,'Ownership Metrics'!$A:$A,'Ownership Metrics'!$G:$G),"") -> 41 | S18: =IFERROR(_xlfn.XLOOKUP($B18,'Ownership Metrics'!$A:$A,'Ownership Metrics'!$H:$H),"") -> Oligopoli | T18: =IFERROR(_xlfn.XLOOKUP($B18,'Ownership Metrics'!$A:$A,'Ownership Metrics'!$I:$I),"") -> Sedang | U18: =IF(COUNTIFS($B$2:$B18,$B18,$D$2:$D18,$D18)=1,1,0) -> 1 | V18: =SUMIFS($L$2:$L$10000,$B$2:$B$10000,$B18,$D$2:$D$10000,$D18) -> 1.11 | W18: =COUNTIFS($B$2:$B$10000,$B18,$U$2:$U$10000,1,$X$2:$X$10000,">"&$X18)+1 -> 8 | X18: =$V18-(ROW()*0.0000000001) -> 1.11
A19: 46265 | B19: ABBA | C19: MAHAKA MEDIA Tbk | D19: SOLIC KREASI BARU PT | E19: Corporate | F19: L | H19: INDONESIA | I19: 542042122 | J19: 0 | K19: 542042122 | L19: 13.77 | M19: =IFERROR(_xlfn.XLOOKUP($B19,'Ownership Metrics'!$A:$A,'Ownership Metrics'!$B:$B),"") -> 25.33 | N19: =IFERROR(_xlfn.XLOOKUP($B19,'Ownership Metrics'!$A:$A,'Ownership Metrics'!$C:$C),"") -> 1915 | O19: =IFERROR(_xlfn.XLOOKUP($B19,'Ownership Metrics'!$A:$A,'Ownership Metrics'!$D:$D),"") -> 40.47 | P19: =IFERROR(_xlfn.XLOOKUP($B19,'Ownership Metrics'!$A:$A,'Ownership Metrics'!$E:$E),"") -> 61.43 | Q19: =IFERROR(_xlfn.XLOOKUP($B19,'Ownership Metrics'!$A:$A,'Ownership Metrics'!$F:$F),"") -> 10 | R19: =IFERROR(_xlfn.XLOOKUP($B19,'Ownership Metrics'!$A:$A,'Ownership Metrics'!$G:$G),"") -> 41 | S19: =IFERROR(_xlfn.XLOOKUP($B19,'Ownership Metrics'!$A:$A,'Ownership Metrics'!$H:$H),"") -> Oligopoli | T19: =IFERROR(_xlfn.XLOOKUP($B19,'Ownership Metrics'!$A:$A,'Ownership Metrics'!$I:$I),"") -> Sedang | U19: =IF(COUNTIFS($B$2:$B19,$B19,$D$2:$D19,$D19)=1,1,0) -> 1 | V19: =SUMIFS($L$2:$L$10000,$B$2:$B$10000,$B19,$D$2:$D$10000,$D19) -> 13.77 | W19: =COUNTIFS($B$2:$B$10000,$B19,$U$2:$U$10000,1,$X$2:$X$10000,">"&$X19)+1 -> 2 | X19: =$V19-(ROW()*0.0000000001) -> 13.77
A20: 46265 | B20: ABBA | C20: MAHAKA MEDIA Tbk | D20: KAIROS EKSPRES INTERNASIONAL PT | E20: Corporate | F20: L | H20: INDONESIA | I20: 52362500 | J20: 0 | K20: 52362500 | L20: 1.33 | M20: =IFERROR(_xlfn.XLOOKUP($B20,'Ownership Metrics'!$A:$A,'Ownership Metrics'!$B:$B),"") -> 25.33 | N20: =IFERROR(_xlfn.XLOOKUP($B20,'Ownership Metrics'!$A:$A,'Ownership Metrics'!$C:$C),"") -> 1915 | O20: =IFERROR(_xlfn.XLOOKUP($B20,'Ownership Metrics'!$A:$A,'Ownership Metrics'!$D:$D),"") -> 40.47 | P20: =IFERROR(_xlfn.XLOOKUP($B20,'Ownership Metrics'!$A:$A,'Ownership Metrics'!$E:$E),"") -> 61.43 | Q20: =IFERROR(_xlfn.XLOOKUP($B20,'Ownership Metrics'!$A:$A,'Ownership Metrics'!$F:$F),"") -> 10 | R20: =IFERROR(_xlfn.XLOOKUP($B20,'Ownership Metrics'!$A:$A,'Ownership Metrics'!$G:$G),"") -> 41 | S20: =IFERROR(_xlfn.XLOOKUP($B20,'Ownership Metrics'!$A:$A,'Ownership Metrics'!$H:$H),"") -> Oligopoli | T20: =IFERROR(_xlfn.XLOOKUP($B20,'Ownership Metrics'!$A:$A,'Ownership Metrics'!$I:$I),"") -> Sedang | U20: =IF(COUNTIFS($B$2:$B20,$B20,$D$2:$D20,$D20)=1,1,0) -> 1 | V20: =SUMIFS($L$2:$L$10000,$B$2:$B$10000,$B20,$D$2:$D$10000,$D20) -> 1.33 | W20: =COUNTIFS($B$2:$B$10000,$B20,$U$2:$U$10000,1,$X$2:$X$10000,">"&$X20)+1 -> 7 | X20: =$V20-(ROW()*0.0000000001) -> 1.33
A21: 46265 | B21: ABBA | C21: MAHAKA MEDIA Tbk | D21: PEARL HILL INVESTMENTS LTD | E21: Financial Institutional | F21: F | H21: VIRGIN ISLANDS, BRITISH | I21: 39999999 | J21: 0 | K21: 39999999 | L21: 1.02 | M21: =IFERROR(_xlfn.XLOOKUP($B21,'Ownership Metrics'!$A:$A,'Ownership Metrics'!$B:$B),"") -> 25.33 | N21: =IFERROR(_xlfn.XLOOKUP($B21,'Ownership Metrics'!$A:$A,'Ownership Metrics'!$C:$C),"") -> 1915 | O21: =IFERROR(_xlfn.XLOOKUP($B21,'Ownership Metrics'!$A:$A,'Ownership Metrics'!$D:$D),"") -> 40.47 | P21: =IFERROR(_xlfn.XLOOKUP($B21,'Ownership Metrics'!$A:$A,'Ownership Metrics'!$E:$E),"") -> 61.43 | Q21: =IFERROR(_xlfn.XLOOKUP($B21,'Ownership Metrics'!$A:$A,'Ownership Metrics'!$F:$F),"") -> 10 | R21: =IFERROR(_xlfn.XLOOKUP($B21,'Ownership Metrics'!$A:$A,'Ownership Metrics'!$G:$G),"") -> 41 | S21: =IFERROR(_xlfn.XLOOKUP($B21,'Ownership Metrics'!$A:$A,'Ownership Metrics'!$H:$H),"") -> Oligopoli | T21: =IFERROR(_xlfn.XLOOKUP($B21,'Ownership Metrics'!$A:$A,'Ownership Metrics'!$I:$I),"") -> Sedang | U21: =IF(COUNTIFS($B$2:$B21,$B21,$D$2:$D21,$D21)=1,1,0) -> 1 | V21: =SUMIFS($L$2:$L$10000,$B$2:$B$10000,$B21,$D$2:$D$10000,$D21) -> 1.02 | W21: =COUNTIFS($B$2:$B$10000,$B21,$U$2:$U$10000,1,$X$2:$X$10000,">"&$X21)+1 -> 10 | X21: =$V21-(ROW()*0.0000000001) -> 1.02
A22: 46265 | B22: ABBA | C22: MAHAKA MEDIA Tbk | D22: TJEN FOENG FA | E22: Individual | F22: L | G22: INDONESIAN | H22: INDONESIA | I22: 41856300 | J22: 0 | K22: 41856300 | L22: 1.06 | M22: =IFERROR(_xlfn.XLOOKUP($B22,'Ownership Metrics'!$A:$A,'Ownership Metrics'!$B:$B),"") -> 25.33 | N22: =IFERROR(_xlfn.XLOOKUP($B22,'Ownership Metrics'!$A:$A,'Ownership Metrics'!$C:$C),"") -> 1915 | O22: =IFERROR(_xlfn.XLOOKUP($B22,'Ownership Metrics'!$A:$A,'Ownership Metrics'!$D:$D),"") -> 40.47 | P22: =IFERROR(_xlfn.XLOOKUP($B22,'Ownership Metrics'!$A:$A,'Ownership Metrics'!$E:$E),"") -> 61.43 | Q22: =IFERROR(_xlfn.XLOOKUP($B22,'Ownership Metrics'!$A:$A,'Ownership Metrics'!$F:$F),"") -> 10 | R22: =IFERROR(_xlfn.XLOOKUP($B22,'Ownership Metrics'!$A:$A,'Ownership Metrics'!$G:$G),"") -> 41 | S22: =IFERROR(_xlfn.XLOOKUP($B22,'Ownership Metrics'!$A:$A,'Ownership Metrics'!$H:$H),"") -> Oligopoli | T22: =IFERROR(_xlfn.XLOOKUP($B22,'Ownership Metrics'!$A:$A,'Ownership Metrics'!$I:$I),"") -> Sedang | U22: =IF(COUNTIFS($B$2:$B22,$B22,$D$2:$D22,$D22)=1,1,0) -> 1 | V22: =SUMIFS($L$2:$L$10000,$B$2:$B$10000,$B22,$D$2:$D$10000,$D22) -> 1.06 | W22: =COUNTIFS($B$2:$B$10000,$B22,$U$2:$U$10000,1,$X$2:$X$10000,">"&$X22)+1 -> 9 | X22: =$V22-(ROW()*0.0000000001) -> 1.06
A23: 46265 | B23: ABBA | C23: MAHAKA MEDIA Tbk | D23: DRS. WINARTO | E23: Individual | F23: L | G23: INDONESIAN | I23: 178745400 | J23: 0 | K23: 178745400 | L23: 4.54 | M23: =IFERROR(_xlfn.XLOOKUP($B23,'Ownership Metrics'!$A:$A,'Ownership Metrics'!$B:$B),"") -> 25.33 | N23: =IFERROR(_xlfn.XLOOKUP($B23,'Ownership Metrics'!$A:$A,'Ownership Metrics'!$C:$C),"") -> 1915 | O23: =IFERROR(_xlfn.XLOOKUP($B23,'Ownership Metrics'!$A:$A,'Ownership Metrics'!$D:$D),"") -> 40.47 | P23: =IFERROR(_xlfn.XLOOKUP($B23,'Ownership Metrics'!$A:$A,'Ownership Metrics'!$E:$E),"") -> 61.43 | Q23: =IFERROR(_xlfn.XLOOKUP($B23,'Ownership Metrics'!$A:$A,'Ownership Metrics'!$F:$F),"") -> 10 | R23: =IFERROR(_xlfn.XLOOKUP($B23,'Ownership Metrics'!$A:$A,'Ownership Metrics'!$G:$G),"") -> 41 | S23: =IFERROR(_xlfn.XLOOKUP($B23,'Ownership Metrics'!$A:$A,'Ownership Metrics'!$H:$H),"") -> Oligopoli | T23: =IFERROR(_xlfn.XLOOKUP($B23,'Ownership Metrics'!$A:$A,'Ownership Metrics'!$I:$I),"") -> Sedang | U23: =IF(COUNTIFS($B$2:$B23,$B23,$D$2:$D23,$D23)=1,1,0) -> 1 | V23: =SUMIFS($L$2:$L$10000,$B$2:$B$10000,$B23,$D$2:$D$10000,$D23) -> 4.54 | W23: =COUNTIFS($B$2:$B$10000,$B23,$U$2:$U$10000,1,$X$2:$X$10000,">"&$X23)+1 -> 4 | X23: =$V23-(ROW()*0.0000000001) -> 4.54
A24: 46265 | B24: ABDA | C24: ASURANSI BINA DANA ARTA Tbk | D24: SKYLIGHT INVESTMENT LTD | E24: Private Equity | F24: F | H24: CAYMAN ISLANDS | I24: 21728234 | J24: 0 | K24: 21728234 | L24: 3.5 | M24: =IFERROR(_xlfn.XLOOKUP($B24,'Ownership Metrics'!$A:$A,'Ownership Metrics'!$B:$B),"") -> 0.32 | N24: =IFERROR(_xlfn.XLOOKUP($B24,'Ownership Metrics'!$A:$A,'Ownership Metrics'!$C:$C),"") -> 7584 | O24: =IFERROR(_xlfn.XLOOKUP($B24,'Ownership Metrics'!$A:$A,'Ownership Metrics'!$D:$D),"") -> 86.76 | P24: =IFERROR(_xlfn.XLOOKUP($B24,'Ownership Metrics'!$A:$A,'Ownership Metrics'!$E:$E),"") -> 96.18 | Q24: =IFERROR(_xlfn.XLOOKUP($B24,'Ownership Metrics'!$A:$A,'Ownership Metrics'!$F:$F),"") -> 4 | R24: =IFERROR(_xlfn.XLOOKUP($B24,'Ownership Metrics'!$A:$A,'Ownership Metrics'!$G:$G),"") -> 85 | S24: =IFERROR(_xlfn.XLOOKUP($B24,'Ownership Metrics'!$A:$A,'Ownership Metrics'!$H:$H),"") -> Mayoritas | T24: =IFERROR(_xlfn.XLOOKUP($B24,'Ownership Metrics'!$A:$A,'Ownership Metrics'!$I:$I),"") -> Tinggi | U24: =IF(COUNTIFS($B$2:$B24,$B24,$D$2:$D24,$D24)=1,1,0) -> 1 | V24: =SUMIFS($L$2:$L$10000,$B$2:$B$10000,$B24,$D$2:$D$10000,$D24) -> 3.5 | W24: =COUNTIFS($B$2:$B$10000,$B24,$U$2:$U$10000,1,$X$2:$X$10000,">"&$X24)+1 -> 4 | X24: =$V24-(ROW()*0.0000000001) -> 3.5
A25: 46265 | B25: ABDA | C25: ASURANSI BINA DANA ARTA Tbk | D25: DBS BANK LTD. | E25: Private Bank | F25: F | H25: SINGAPORE | I25: 28000000 | J25: 0 | K25: 28000000 | L25: 4.51 | M25: =IFERROR(_xlfn.XLOOKUP($B25,'Ownership Metrics'!$A:$A,'Ownership Metrics'!$B:$B),"") -> 0.32 | N25: =IFERROR(_xlfn.XLOOKUP($B25,'Ownership Metrics'!$A:$A,'Ownership Metrics'!$C:$C),"") -> 7584 | O25: =IFERROR(_xlfn.XLOOKUP($B25,'Ownership Metrics'!$A:$A,'Ownership Metrics'!$D:$D),"") -> 86.76 | P25: =IFERROR(_xlfn.XLOOKUP($B25,'Ownership Metrics'!$A:$A,'Ownership Metrics'!$E:$E),"") -> 96.18 | Q25: =IFERROR(_xlfn.XLOOKUP($B25,'Ownership Metrics'!$A:$A,'Ownership Metrics'!$F:$F),"") -> 4 | R25: =IFERROR(_xlfn.XLOOKUP($B25,'Ownership Metrics'!$A:$A,'Ownership Metrics'!$G:$G),"") -> 85 | S25: =IFERROR(_xlfn.XLOOKUP($B25,'Ownership Metrics'!$A:$A,'Ownership Metrics'!$H:$H),"") -> Mayoritas | T25: =IFERROR(_xlfn.XLOOKUP($B25,'Ownership Metrics'!$A:$A,'Ownership Metrics'!$I:$I),"") -> Tinggi | U25: =IF(COUNTIFS($B$2:$B25,$B25,$D$2:$D25,$D25)=1,1,0) -> 1 | V25: =SUMIFS($L$2:$L$10000,$B$2:$B$10000,$B25,$D$2:$D$10000,$D25) -> 4.51 | W25: =COUNTIFS($B$2:$B$10000,$B25,$U$2:$U$10000,1,$X$2:$X$10000,">"&$X25)+1 -> 3 | X25: =$V25-(ROW()*0.0000000001) -> 4.51
A26: 46265 | B26: ABDA | C26: ASURANSI BINA DANA ARTA Tbk | D26: OONA INDONESIA PTE LTD | E26: Insurance | F26: F | H26: SINGAPORE | I26: 538604204 | J26: 0 | K26: 538604204 | L26: 86.76 | M26: =IFERROR(_xlfn.XLOOKUP($B26,'Ownership Metrics'!$A:$A,'Ownership Metrics'!$B:$B),"") -> 0.32 | N26: =IFERROR(_xlfn.XLOOKUP($B26,'Ownership Metrics'!$A:$A,'Ownership Metrics'!$C:$C),"") -> 7584 | O26: =IFERROR(_xlfn.XLOOKUP($B26,'Ownership Metrics'!$A:$A,'Ownership Metrics'!$D:$D),"") -> 86.76 | P26: =IFERROR(_xlfn.XLOOKUP($B26,'Ownership Metrics'!$A:$A,'Ownership Metrics'!$E:$E),"") -> 96.18 | Q26: =IFERROR(_xlfn.XLOOKUP($B26,'Ownership Metrics'!$A:$A,'Ownership Metrics'!$F:$F),"") -> 4 | R26: =IFERROR(_xlfn.XLOOKUP($B26,'Ownership Metrics'!$A:$A,'Ownership Metrics'!$G:$G),"") -> 85 | S26: =IFERROR(_xlfn.XLOOKUP($B26,'Ownership Metrics'!$A:$A,'Ownership Metrics'!$H:$H),"") -> Mayoritas | T26: =IFERROR(_xlfn.XLOOKUP($B26,'Ownership Metrics'!$A:$A,'Ownership Metrics'!$I:$I),"") -> Tinggi | U26: =IF(COUNTIFS($B$2:$B26,$B26,$D$2:$D26,$D26)=1,1,0) -> 1 | V26: =SUMIFS($L$2:$L$10000,$B$2:$B$10000,$B26,$D$2:$D$10000,$D26) -> 86.76 | W26: =COUNTIFS($B$2:$B$10000,$B26,$U$2:$U$10000,1,$X$2:$X$10000,">"&$X26)+1 -> 1 | X26: =$V26-(ROW()*0.0000000001) -> 86.76
A27: 46265 | B27: ABDA | C27: ASURANSI BINA DANA ARTA Tbk | D27: MAYBANK SECURITIES PTE. LTD. | E27: Securities Company | F27: F | H27: SINGAPORE | I27: 30499400 | J27: 0 | K27: 30499400 | L27: 4.91 | M27: =IFERROR(_xlfn.XLOOKUP($B27,'Ownership Metrics'!$A:$A,'Ownership Metrics'!$B:$B),"") -> 0.32 | N27: =IFERROR(_xlfn.XLOOKUP($B27,'Ownership Metrics'!$A:$A,'Ownership Metrics'!$C:$C),"") -> 7584 | O27: =IFERROR(_xlfn.XLOOKUP($B27,'Ownership Metrics'!$A:$A,'Ownership Metrics'!$D:$D),"") -> 86.76 | P27: =IFERROR(_xlfn.XLOOKUP($B27,'Ownership Metrics'!$A:$A,'Ownership Metrics'!$E:$E),"") -> 96.18 | Q27: =IFERROR(_xlfn.XLOOKUP($B27,'Ownership Metrics'!$A:$A,'Ownership Metrics'!$F:$F),"") -> 4 | R27: =IFERROR(_xlfn.XLOOKUP($B27,'Ownership Metrics'!$A:$A,'Ownership Metrics'!$G:$G),"") -> 85 | S27: =IFERROR(_xlfn.XLOOKUP($B27,'Ownership Metrics'!$A:$A,'Ownership Metrics'!$H:$H),"") -> Mayoritas | T27: =IFERROR(_xlfn.XLOOKUP($B27,'Ownership Metrics'!$A:$A,'Ownership Metrics'!$I:$I),"") -> Tinggi | U27: =IF(COUNTIFS($B$2:$B27,$B27,$D$2:$D27,$D27)=1,1,0) -> 1 | V27: =SUMIFS($L$2:$L$10000,$B$2:$B$10000,$B27,$D$2:$D$10000,$D27) -> 4.91 | W27: =COUNTIFS($B$2:$B$10000,$B27,$U$2:$U$10000,1,$X$2:$X$10000,">"&$X27)+1 -> 2 | X27: =$V27-(ROW()*0.0000000001) -> 4.91
A28: 46265 | B28: ABMM | C28: ABM INVESTAMA Tbk | D28: PT TIARA MARGA TRAKINDO | E28: Corporate | F28: L | H28: INDONESIA | I28: 1474573133 | J28: 0 | K28: 1474573133 | L28: 53.56 | M28: =IFERROR(_xlfn.XLOOKUP($B28,'Ownership Metrics'!$A:$A,'Ownership Metrics'!$B:$B),"") -> 11.77 | N28: =IFERROR(_xlfn.XLOOKUP($B28,'Ownership Metrics'!$A:$A,'Ownership Metrics'!$C:$C),"") -> 3564 | O28: =IFERROR(_xlfn.XLOOKUP($B28,'Ownership Metrics'!$A:$A,'Ownership Metrics'!$D:$D),"") -> 53.56 | P28: =IFERROR(_xlfn.XLOOKUP($B28,'Ownership Metrics'!$A:$A,'Ownership Metrics'!$E:$E),"") -> 84.73 | Q28: =IFERROR(_xlfn.XLOOKUP($B28,'Ownership Metrics'!$A:$A,'Ownership Metrics'!$F:$F),"") -> 4 | R28: =IFERROR(_xlfn.XLOOKUP($B28,'Ownership Metrics'!$A:$A,'Ownership Metrics'!$G:$G),"") -> 63 | S28: =IFERROR(_xlfn.XLOOKUP($B28,'Ownership Metrics'!$A:$A,'Ownership Metrics'!$H:$H),"") -> Mayoritas | T28: =IFERROR(_xlfn.XLOOKUP($B28,'Ownership Metrics'!$A:$A,'Ownership Metrics'!$I:$I),"") -> Tinggi | U28: =IF(COUNTIFS($B$2:$B28,$B28,$D$2:$D28,$D28)=1,1,0) -> 1 | V28: =SUMIFS($L$2:$L$10000,$B$2:$B$10000,$B28,$D$2:$D$10000,$D28) -> 53.56 | W28: =COUNTIFS($B$2:$B$10000,$B28,$U$2:$U$10000,1,$X$2:$X$10000,">"&$X28)+1 -> 1 | X28: =$V28-(ROW()*0.0000000001) -> 53.56
A29: 46265 | B29: ABMM | C29: ABM INVESTAMA Tbk | D29: NOBLE INVESTMENT CORPORATION (SPC) LTD. | E29: Mutual Funds | F29: F | H29: CAYMAN ISLANDS | I29: 96446100 | J29: 0 | K29: 96446100 | L29: 3.5 | M29: =IFERROR(_xlfn.XLOOKUP($B29,'Ownership Metrics'!$A:$A,'Ownership Metrics'!$B:$B),"") -> 11.77 | N29: =IFERROR(_xlfn.XLOOKUP($B29,'Ownership Metrics'!$A:$A,'Ownership Metrics'!$C:$C),"") -> 3564 | O29: =IFERROR(_xlfn.XLOOKUP($B29,'Ownership Metrics'!$A:$A,'Ownership Metrics'!$D:$D),"") -> 53.56 | P29: =IFERROR(_xlfn.XLOOKUP($B29,'Ownership Metrics'!$A:$A,'Ownership Metrics'!$E:$E),"") -> 84.73 | Q29: =IFERROR(_xlfn.XLOOKUP($B29,'Ownership Metrics'!$A:$A,'Ownership Metrics'!$F:$F),"") -> 4 | R29: =IFERROR(_xlfn.XLOOKUP($B29,'Ownership Metrics'!$A:$A,'Ownership Metrics'!$G:$G),"") -> 63 | S29: =IFERROR(_xlfn.XLOOKUP($B29,'Ownership Metrics'!$A:$A,'Ownership Metrics'!$H:$H),"") -> Mayoritas | T29: =IFERROR(_xlfn.XLOOKUP($B29,'Ownership Metrics'!$A:$A,'Ownership Metrics'!$I:$I),"") -> Tinggi | U29: =IF(COUNTIFS($B$2:$B29,$B29,$D$2:$D29,$D29)=1,1,0) -> 1 | V29: =SUMIFS($L$2:$L$10000,$B$2:$B$10000,$B29,$D$2:$D$10000,$D29) -> 3.5 | W29: =COUNTIFS($B$2:$B$10000,$B29,$U$2:$U$10000,1,$X$2:$X$10000,">"&$X29)+1 -> 4 | X29: =$V29-(ROW()*0.0000000001) -> 3.5
A30: 46265 | B30: ABMM | C30: ABM INVESTAMA Tbk | D30: VALLE VERDE PTE LTD | E30: Firm | F30: F | H30: SINGAPORE | I30: 702349867 | J30: 0 | K30: 702349867 | L30: 25.51 | M30: =IFERROR(_xlfn.XLOOKUP($B30,'Ownership Metrics'!$A:$A,'Ownership Metrics'!$B:$B),"") -> 11.77 | N30: =IFERROR(_xlfn.XLOOKUP($B30,'Ownership Metrics'!$A:$A,'Ownership Metrics'!$C:$C),"") -> 3564 | O30: =IFERROR(_xlfn.XLOOKUP($B30,'Ownership Metrics'!$A:$A,'Ownership Metrics'!$D:$D),"") -> 53.56 | P30: =IFERROR(_xlfn.XLOOKUP($B30,'Ownership Metrics'!$A:$A,'Ownership Metrics'!$E:$E),"") -> 84.73 | Q30: =IFERROR(_xlfn.XLOOKUP($B30,'Ownership Metrics'!$A:$A,'Ownership Metrics'!$F:$F),"") -> 4 | R30: =IFERROR(_xlfn.XLOOKUP($B30,'Ownership Metrics'!$A:$A,'Ownership Metrics'!$G:$G),"") -> 63 | S30: =IFERROR(_xlfn.XLOOKUP($B30,'Ownership Metrics'!$A:$A,'Ownership Metrics'!$H:$H),"") -> Mayoritas | T30: =IFERROR(_xlfn.XLOOKUP($B30,'Ownership Metrics'!$A:$A,'Ownership Metrics'!$I:$I),"") -> Tinggi | U30: =IF(COUNTIFS($B$2:$B30,$B30,$D$2:$D30,$D30)=1,1,0) -> 1 | V30: =SUMIFS($L$2:$L$10000,$B$2:$B$10000,$B30,$D$2:$D$10000,$D30) -> 25.51 | W30: =COUNTIFS($B$2:$B$10000,$B30,$U$2:$U$10000,1,$X$2:$X$10000,">"&$X30)+1 -> 2 | X30: =$V30-(ROW()*0.0000000001) -> 25.51
A31: 46265 | B31: ABMM | C31: ABM INVESTAMA Tbk | D31: DRS LO KHENG HONG | E31: Individual | F31: L | G31: INDONESIAN | H31: INDONESIA | I31: 155929500 | J31: 0 | K31: 155929500 | L31: 5.66 | M31: =IFERROR(_xlfn.XLOOKUP($B31,'Ownership Metrics'!$A:$A,'Ownership Metrics'!$B:$B),"") -> 11.77 | N31: =IFERROR(_xlfn.XLOOKUP($B31,'Ownership Metrics'!$A:$A,'Ownership Metrics'!$C:$C),"") -> 3564 | O31: =IFERROR(_xlfn.XLOOKUP($B31,'Ownership Metrics'!$A:$A,'Ownership Metrics'!$D:$D),"") -> 53.56 | P31: =IFERROR(_xlfn.XLOOKUP($B31,'Ownership Metrics'!$A:$A,'Ownership Metrics'!$E:$E),"") -> 84.73 | Q31: =IFERROR(_xlfn.XLOOKUP($B31,'Ownership Metrics'!$A:$A,'Ownership Metrics'!$F:$F),"") -> 4 | R31: =IFERROR(_xlfn.XLOOKUP($B31,'Ownership Metrics'!$A:$A,'Ownership Metrics'!$G:$G),"") -> 63 | S31: =IFERROR(_xlfn.XLOOKUP($B31,'Ownership Metrics'!$A:$A,'Ownership Metrics'!$H:$H),"") -> Mayoritas | T31: =IFERROR(_xlfn.XLOOKUP($B31,'Ownership Metrics'!$A:$A,'Ownership Metrics'!$I:$I),"") -> Tinggi | U31: =IF(COUNTIFS($B$2:$B31,$B31,$D$2:$D31,$D31)=1,1,0) -> 1 | V31: =SUMIFS($L$2:$L$10000,$B$2:$B$10000,$B31,$D$2:$D$10000,$D31) -> 5.66 | W31: =COUNTIFS($B$2:$B$10000,$B31,$U$2:$U$10000,1,$X$2:$X$10000,">"&$X31)+1 -> 3 | X31: =$V31-(ROW()*0.0000000001) -> 5.66
A32: 46265 | B32: ACES | C32: ASPIRASI HIDUP INDONESIA Tbk | D32: PT KAWAN LAMA SEJAHTERA | E32: Corporate | F32: L | H32: INDONESIA | I32: 10272189700 | J32: 0 | K32: 10272189700 | L32: 60 | M32: =IFERROR(_xlfn.XLOOKUP($B32,'Ownership Metrics'!$A:$A,'Ownership Metrics'!$B:$B),"") -> 34.69 | N32: =IFERROR(_xlfn.XLOOKUP($B32,'Ownership Metrics'!$A:$A,'Ownership Metrics'!$C:$C),"") -> 3611 | O32: =IFERROR(_xlfn.XLOOKUP($B32,'Ownership Metrics'!$A:$A,'Ownership Metrics'!$D:$D),"") -> 60 | P32: =IFERROR(_xlfn.XLOOKUP($B32,'Ownership Metrics'!$A:$A,'Ownership Metrics'!$E:$E),"") -> 64.16 | Q32: =IFERROR(_xlfn.XLOOKUP($B32,'Ownership Metrics'!$A:$A,'Ownership Metrics'!$F:$F),"") -> 4 | R32: =IFERROR(_xlfn.XLOOKUP($B32,'Ownership Metrics'!$A:$A,'Ownership Metrics'!$G:$G),"") -> 56 | S32: =IFERROR(_xlfn.XLOOKUP($B32,'Ownership Metrics'!$A:$A,'Ownership Metrics'!$H:$H),"") -> Mayoritas | T32: =IFERROR(_xlfn.XLOOKUP($B32,'Ownership Metrics'!$A:$A,'Ownership Metrics'!$I:$I),"") -> Tinggi | U32: =IF(COUNTIFS($B$2:$B32,$B32,$D$2:$D32,$D32)=1,1,0) -> 1 | V32: =SUMIFS($L$2:$L$10000,$B$2:$B$10000,$B32,$D$2:$D$10000,$D32) -> 60 | W32: =COUNTIFS($B$2:$B$10000,$B32,$U$2:$U$10000,1,$X$2:$X$10000,">"&$X32)+1 -> 1 | X32: =$V32-(ROW()*0.0000000001) -> 60
A33: 46265 | B33: ACES | C33: ASPIRASI HIDUP INDONESIA Tbk | D33: MERCER QIF FUND PLC | E33: Mutual Funds | F33: F | H33: IRELAND | I33: 196536000 | J33: 0 | K33: 196536000 | L33: 1.15 | M33: =IFERROR(_xlfn.XLOOKUP($B33,'Ownership Metrics'!$A:$A,'Ownership Metrics'!$B:$B),"") -> 34.69 | N33: =IFERROR(_xlfn.XLOOKUP($B33,'Ownership Metrics'!$A:$A,'Ownership Metrics'!$C:$C),"") -> 3611 | O33: =IFERROR(_xlfn.XLOOKUP($B33,'Ownership Metrics'!$A:$A,'Ownership Metrics'!$D:$D),"") -> 60 | P33: =IFERROR(_xlfn.XLOOKUP($B33,'Ownership Metrics'!$A:$A,'Ownership Metrics'!$E:$E),"") -> 64.16 | Q33: =IFERROR(_xlfn.XLOOKUP($B33,'Ownership Metrics'!$A:$A,'Ownership Metrics'!$F:$F),"") -> 4 | R33: =IFERROR(_xlfn.XLOOKUP($B33,'Ownership Metrics'!$A:$A,'Ownership Metrics'!$G:$G),"") -> 56 | S33: =IFERROR(_xlfn.XLOOKUP($B33,'Ownership Metrics'!$A:$A,'Ownership Metrics'!$H:$H),"") -> Mayoritas | T33: =IFERROR(_xlfn.XLOOKUP($B33,'Ownership Metrics'!$A:$A,'Ownership Metrics'!$I:$I),"") -> Tinggi | U33: =IF(COUNTIFS($B$2:$B33,$B33,$D$2:$D33,$D33)=1,1,0) -> 1 | V33: =SUMIFS($L$2:$L$10000,$B$2:$B$10000,$B33,$D$2:$D$10000,$D33) -> 1.15 | W33: =COUNTIFS($B$2:$B$10000,$B33,$U$2:$U$10000,1,$X$2:$X$10000,">"&$X33)+1 -> 4 | X33: =$V33-(ROW()*0.0000000001) -> 1.15
A34: 46265 | B34: ACES | C34: ASPIRASI HIDUP INDONESIA Tbk | D34: ALBIZIA ASEAN OPPORTUNITIES FUND | E34: Mutual Funds | F34: F | H34: CAYMAN ISLANDS | I34: 488996500 | J34: 0 | K34: 488996500 | L34: 2.86 | M34: =IFERROR(_xlfn.XLOOKUP($B34,'Ownership Metrics'!$A:$A,'Ownership Metrics'!$B:$B),"") -> 34.69 | N34: =IFERROR(_xlfn.XLOOKUP($B34,'Ownership Metrics'!$A:$A,'Ownership Metrics'!$C:$C),"") -> 3611 | O34: =IFERROR(_xlfn.XLOOKUP($B34,'Ownership Metrics'!$A:$A,'Ownership Metrics'!$D:$D),"") -> 60 | P34: =IFERROR(_xlfn.XLOOKUP($B34,'Ownership Metrics'!$A:$A,'Ownership Metrics'!$E:$E),"") -> 64.16 | Q34: =IFERROR(_xlfn.XLOOKUP($B34,'Ownership Metrics'!$A:$A,'Ownership Metrics'!$F:$F),"") -> 4 | R34: =IFERROR(_xlfn.XLOOKUP($B34,'Ownership Metrics'!$A:$A,'Ownership Metrics'!$G:$G),"") -> 56 | S34: =IFERROR(_xlfn.XLOOKUP($B34,'Ownership Metrics'!$A:$A,'Ownership Metrics'!$H:$H),"") -> Mayoritas | T34: =IFERROR(_xlfn.XLOOKUP($B34,'Ownership Metrics'!$A:$A,'Ownership Metrics'!$I:$I),"") -> Tinggi | U34: =IF(COUNTIFS($B$2:$B34,$B34,$D$2:$D34,$D34)=1,1,0) -> 1 | V34: =SUMIFS($L$2:$L$10000,$B$2:$B$10000,$B34,$D$2:$D$10000,$D34) -> 2.86 | W34: =COUNTIFS($B$2:$B$10000,$B34,$U$2:$U$10000,1,$X$2:$X$10000,">"&$X34)+1 -> 2 | X34: =$V34-(ROW()*0.0000000001) -> 2.86
A35: 46265 | B35: ACES | C35: ASPIRASI HIDUP INDONESIA Tbk | D35: NT TST CO S/A EDGBASTON ASIAN EQUITY (JERSEY) TRUST | E35: Investment Advisors | F35: F | H35: JERSEY | I35: 222955600 | J35: 0 | K35: 222955600 | L35: 1.3 | M35: =IFERROR(_xlfn.XLOOKUP($B35,'Ownership Metrics'!$A:$A,'Ownership Metrics'!$B:$B),"") -> 34.69 | N35: =IFERROR(_xlfn.XLOOKUP($B35,'Ownership Metrics'!$A:$A,'Ownership Metrics'!$C:$C),"") -> 3611 | O35: =IFERROR(_xlfn.XLOOKUP($B35,'Ownership Metrics'!$A:$A,'Ownership Metrics'!$D:$D),"") -> 60 | P35: =IFERROR(_xlfn.XLOOKUP($B35,'Ownership Metrics'!$A:$A,'Ownership Metrics'!$E:$E),"") -> 64.16 | Q35: =IFERROR(_xlfn.XLOOKUP($B35,'Ownership Metrics'!$A:$A,'Ownership Metrics'!$F:$F),"") -> 4 | R35: =IFERROR(_xlfn.XLOOKUP($B35,'Ownership Metrics'!$A:$A,'Ownership Metrics'!$G:$G),"") -> 56 | S35: =IFERROR(_xlfn.XLOOKUP($B35,'Ownership Metrics'!$A:$A,'Ownership Metrics'!$H:$H),"") -> Mayoritas | T35: =IFERROR(_xlfn.XLOOKUP($B35,'Ownership Metrics'!$A:$A,'Ownership Metrics'!$I:$I),"") -> Tinggi | U35: =IF(COUNTIFS($B$2:$B35,$B35,$D$2:$D35,$D35)=1,1,0) -> 1 | V35: =SUMIFS($L$2:$L$10000,$B$2:$B$10000,$B35,$D$2:$D$10000,$D35) -> 1.3 | W35: =COUNTIFS($B$2:$B$10000,$B35,$U$2:$U$10000,1,$X$2:$X$10000,">"&$X35)+1 -> 3 | X35: =$V35-(ROW()*0.0000000001) -> 1.3
A36: 46265 | B36: ACRO | C36: SAMCRO HYOSUNG ADILESTARI Tbk | D36: JOO HEE KO | E36: Individual | F36: F | G36: SOUTH KOREAN | H36: INDONESIA | I36: 155459000 | J36: 0 | K36: 155459000 | L36: 4.48 | M36: =IFERROR(_xlfn.XLOOKUP($B36,'Ownership Metrics'!$A:$A,'Ownership Metrics'!$B:$B),"") -> 10.23 | N36: =IFERROR(_xlfn.XLOOKUP($B36,'Ownership Metrics'!$A:$A,'Ownership Metrics'!$C:$C),"") -> 6191 | O36: =IFERROR(_xlfn.XLOOKUP($B36,'Ownership Metrics'!$A:$A,'Ownership Metrics'!$D:$D),"") -> 78.4 | P36: =IFERROR(_xlfn.XLOOKUP($B36,'Ownership Metrics'!$A:$A,'Ownership Metrics'!$E:$E),"") -> 86.67 | Q36: =IFERROR(_xlfn.XLOOKUP($B36,'Ownership Metrics'!$A:$A,'Ownership Metrics'!$F:$F),"") -> 4 | R36: =IFERROR(_xlfn.XLOOKUP($B36,'Ownership Metrics'!$A:$A,'Ownership Metrics'!$G:$G),"") -> 75 | S36: =IFERROR(_xlfn.XLOOKUP($B36,'Ownership Metrics'!$A:$A,'Ownership Metrics'!$H:$H),"") -> Mayoritas | T36: =IFERROR(_xlfn.XLOOKUP($B36,'Ownership Metrics'!$A:$A,'Ownership Metrics'!$I:$I),"") -> Tinggi | U36: =IF(COUNTIFS($B$2:$B36,$B36,$D$2:$D36,$D36)=1,1,0) -> 1 | V36: =SUMIFS($L$2:$L$10000,$B$2:$B$10000,$B36,$D$2:$D$10000,$D36) -> 4.48 | W36: =COUNTIFS($B$2:$B$10000,$B36,$U$2:$U$10000,1,$X$2:$X$10000,">"&$X36)+1 -> 2 | X36: =$V36-(ROW()*0.0000000001) -> 4.48
A37: 46265 | B37: ACRO | C37: SAMCRO HYOSUNG ADILESTARI Tbk | D37: SUMAN KIM | E37: Individual | F37: F | G37: SOUTH KOREAN | H37: INDONESIA | I37: 131628700 | J37: 0 | K37: 131628700 | L37: 3.79 | M37: =IFERROR(_xlfn.XLOOKUP($B37,'Ownership Metrics'!$A:$A,'Ownership Metrics'!$B:$B),"") -> 10.23 | N37: =IFERROR(_xlfn.XLOOKUP($B37,'Ownership Metrics'!$A:$A,'Ownership Metrics'!$C:$C),"") -> 6191 | O37: =IFERROR(_xlfn.XLOOKUP($B37,'Ownership Metrics'!$A:$A,'Ownership Metrics'!$D:$D),"") -> 78.4 | P37: =IFERROR(_xlfn.XLOOKUP($B37,'Ownership Metrics'!$A:$A,'Ownership Metrics'!$E:$E),"") -> 86.67 | Q37: =IFERROR(_xlfn.XLOOKUP($B37,'Ownership Metrics'!$A:$A,'Ownership Metrics'!$F:$F),"") -> 4 | R37: =IFERROR(_xlfn.XLOOKUP($B37,'Ownership Metrics'!$A:$A,'Ownership Metrics'!$G:$G),"") -> 75 | S37: =IFERROR(_xlfn.XLOOKUP($B37,'Ownership Metrics'!$A:$A,'Ownership Metrics'!$H:$H),"") -> Mayoritas | T37: =IFERROR(_xlfn.XLOOKUP($B37,'Ownership Metrics'!$A:$A,'Ownership Metrics'!$I:$I),"") -> Tinggi | U37: =IF(COUNTIFS($B$2:$B37,$B37,$D$2:$D37,$D37)=1,1,0) -> 1 | V37: =SUMIFS($L$2:$L$10000,$B$2:$B$10000,$B37,$D$2:$D$10000,$D37) -> 3.79 | W37: =COUNTIFS($B$2:$B$10000,$B37,$U$2:$U$10000,1,$X$2:$X$10000,">"&$X37)+1 -> 3 | X37: =$V37-(ROW()*0.0000000001) -> 3.79
A38: 46265 | B38: ACRO | C38: SAMCRO HYOSUNG ADILESTARI Tbk | D38: KYUNGHEE KO | E38: Individual | F38: F | G38: SOUTH KOREAN | H38: INDONESIA | I38: 107563300 | J38: 0 | K38: 107563300 | L38: 3.1 | M38: =IFERROR(_xlfn.XLOOKUP($B38,'Ownership Metrics'!$A:$A,'Ownership Metrics'!$B:$B),"") -> 10.23 | N38: =IFERROR(_xlfn.XLOOKUP($B38,'Ownership Metrics'!$A:$A,'Ownership Metrics'!$C:$C),"") -> 6191 | O38: =IFERROR(_xlfn.XLOOKUP($B38,'Ownership Metrics'!$A:$A,'Ownership Metrics'!$D:$D),"") -> 78.4 | P38: =IFERROR(_xlfn.XLOOKUP($B38,'Ownership Metrics'!$A:$A,'Ownership Metrics'!$E:$E),"") -> 86.67 | Q38: =IFERROR(_xlfn.XLOOKUP($B38,'Ownership Metrics'!$A:$A,'Ownership Metrics'!$F:$F),"") -> 4 | R38: =IFERROR(_xlfn.XLOOKUP($B38,'Ownership Metrics'!$A:$A,'Ownership Metrics'!$G:$G),"") -> 75 | S38: =IFERROR(_xlfn.XLOOKUP($B38,'Ownership Metrics'!$A:$A,'Ownership Metrics'!$H:$H),"") -> Mayoritas | T38: =IFERROR(_xlfn.XLOOKUP($B38,'Ownership Metrics'!$A:$A,'Ownership Metrics'!$I:$I),"") -> Tinggi | U38: =IF(COUNTIFS($B$2:$B38,$B38,$D$2:$D38,$D38)=1,1,0) -> 1 | V38: =SUMIFS($L$2:$L$10000,$B$2:$B$10000,$B38,$D$2:$D$10000,$D38) -> 3.1 | W38: =COUNTIFS($B$2:$B$10000,$B38,$U$2:$U$10000,1,$X$2:$X$10000,">"&$X38)+1 -> 4 | X38: =$V38-(ROW()*0.0000000001) -> 3.1
A39: 46265 | B39: ACRO | C39: SAMCRO HYOSUNG ADILESTARI Tbk | D39: TAE SUNG CHUNG | E39: Individual | F39: F | G39: SOUTH KOREAN | H39: INDONESIA | I39: 2720072495 | J39: 0 | K39: 2720072495 | L39: 78.4 | M39: =IFERROR(_xlfn.XLOOKUP($B39,'Ownership Metrics'!$A:$A,'Ownership Metrics'!$B:$B),"") -> 10.23 | N39: =IFERROR(_xlfn.XLOOKUP($B39,'Ownership Metrics'!$A:$A,'Ownership Metrics'!$C:$C),"") -> 6191 | O39: =IFERROR(_xlfn.XLOOKUP($B39,'Ownership Metrics'!$A:$A,'Ownership Metrics'!$D:$D),"") -> 78.4 | P39: =IFERROR(_xlfn.XLOOKUP($B39,'Ownership Metrics'!$A:$A,'Ownership Metrics'!$E:$E),"") -> 86.67 | Q39: =IFERROR(_xlfn.XLOOKUP($B39,'Ownership Metrics'!$A:$A,'Ownership Metrics'!$F:$F),"") -> 4 | R39: =IFERROR(_xlfn.XLOOKUP($B39,'Ownership Metrics'!$A:$A,'Ownership Metrics'!$G:$G),"") -> 75 | S39: =IFERROR(_xlfn.XLOOKUP($B39,'Ownership Metrics'!$A:$A,'Ownership Metrics'!$H:$H),"") -> Mayoritas | T39: =IFERROR(_xlfn.XLOOKUP($B39,'Ownership Metrics'!$A:$A,'Ownership Metrics'!$I:$I),"") -> Tinggi | U39: =IF(COUNTIFS($B$2:$B39,$B39,$D$2:$D39,$D39)=1,1,0) -> 1 | V39: =SUMIFS($L$2:$L$10000,$B$2:$B$10000,$B39,$D$2:$D$10000,$D39) -> 78.4 | W39: =COUNTIFS($B$2:$B$10000,$B39,$U$2:$U$10000,1,$X$2:$X$10000,">"&$X39)+1 -> 1 | X39: =$V39-(ROW()*0.0000000001) -> 78.4
A40: 46265 | B40: ACST | C40: ACSET INDONUSA Tbk | D40: PT. KARYA SUPRA PERKASA | E40: Corporate | F40: L | H40: INDONESIA | I40: 16115027968 | J40: 0 | K40: 16115027968 | L40: 91.17 | M40: =IFERROR(_xlfn.XLOOKUP($B40,'Ownership Metrics'!$A:$A,'Ownership Metrics'!$B:$B),"") -> 8.83 | N40: =IFERROR(_xlfn.XLOOKUP($B40,'Ownership Metrics'!$A:$A,'Ownership Metrics'!$C:$C),"") -> 8312 | O40: =IFERROR(_xlfn.XLOOKUP($B40,'Ownership Metrics'!$A:$A,'Ownership Metrics'!$D:$D),"") -> 91.17 | P40: =IFERROR(_xlfn.XLOOKUP($B40,'Ownership Metrics'!$A:$A,'Ownership Metrics'!$E:$E),"") -> 91.17 | Q40: =IFERROR(_xlfn.XLOOKUP($B40,'Ownership Metrics'!$A:$A,'Ownership Metrics'!$F:$F),"") -> 1 | R40: =IFERROR(_xlfn.XLOOKUP($B40,'Ownership Metrics'!$A:$A,'Ownership Metrics'!$G:$G),"") -> 89 | S40: =IFERROR(_xlfn.XLOOKUP($B40,'Ownership Metrics'!$A:$A,'Ownership Metrics'!$H:$H),"") -> Mayoritas | T40: =IFERROR(_xlfn.XLOOKUP($B40,'Ownership Metrics'!$A:$A,'Ownership Metrics'!$I:$I),"") -> Tinggi | U40: =IF(COUNTIFS($B$2:$B40,$B40,$D$2:$D40,$D40)=1,1,0) -> 1 | V40: =SUMIFS($L$2:$L$10000,$B$2:$B$10000,$B40,$D$2:$D$10000,$D40) -> 91.17 | W40: =COUNTIFS($B$2:$B$10000,$B40,$U$2:$U$10000,1,$X$2:$X$10000,">"&$X40)+1 -> 1 | X40: =$V40-(ROW()*0.0000000001) -> 91.17
A41: 46265 | B41: ADCP | C41: ADHI COMMUTER PROPERTI Tbk | D41: ADHI KARYA PERSERO TBK PT. | E41: State Owned Enterprises | F41: L | H41: INDONESIA | I41: 0 | J41: 19999900000 | K41: 19999900000 | L41: 90 | M41: =IFERROR(_xlfn.XLOOKUP($B41,'Ownership Metrics'!$A:$A,'Ownership Metrics'!$B:$B),"") -> 10 | N41: =IFERROR(_xlfn.XLOOKUP($B41,'Ownership Metrics'!$A:$A,'Ownership Metrics'!$C:$C),"") -> 8100 | O41: =IFERROR(_xlfn.XLOOKUP($B41,'Ownership Metrics'!$A:$A,'Ownership Metrics'!$D:$D),"") -> 90 | P41: =IFERROR(_xlfn.XLOOKUP($B41,'Ownership Metrics'!$A:$A,'Ownership Metrics'!$E:$E),"") -> 90 | Q41: =IFERROR(_xlfn.XLOOKUP($B41,'Ownership Metrics'!$A:$A,'Ownership Metrics'!$F:$F),"") -> 1 | R41: =IFERROR(_xlfn.XLOOKUP($B41,'Ownership Metrics'!$A:$A,'Ownership Metrics'!$G:$G),"") -> 88 | S41: =IFERROR(_xlfn.XLOOKUP($B41,'Ownership Metrics'!$A:$A,'Ownership Metrics'!$H:$H),"") -> Mayoritas | T41: =IFERROR(_xlfn.XLOOKUP($B41,'Ownership Metrics'!$A:$A,'Ownership Metrics'!$I:$I),"") -> Tinggi | U41: =IF(COUNTIFS($B$2:$B41,$B41,$D$2:$D41,$D41)=1,1,0) -> 1 | V41: =SUMIFS($L$2:$L$10000,$B$2:$B$10000,$B41,$D$2:$D$10000,$D41) -> 90 | W41: =COUNTIFS($B$2:$B$10000,$B41,$U$2:$U$10000,1,$X$2:$X$10000,">"&$X41)+1 -> 1 | X41: =$V41-(ROW()*0.0000000001) -> 90
A42: 46265 | B42: ADES | C42: AKASHA WIRA INTERNATIONAL Tbk | D42: WATER PARTNERS BOTTLING SA | E42: Corporate | F42: F | H42: SWITZERLAND | I42: 538896713 | J42: 0 | K42: 538896713 | L42: 91.35 | M42: =IFERROR(_xlfn.XLOOKUP($B42,'Ownership Metrics'!$A:$A,'Ownership Metrics'!$B:$B),"") -> 7.61 | N42: =IFERROR(_xlfn.XLOOKUP($B42,'Ownership Metrics'!$A:$A,'Ownership Metrics'!$C:$C),"") -> 8346 | O42: =IFERROR(_xlfn.XLOOKUP($B42,'Ownership Metrics'!$A:$A,'Ownership Metrics'!$D:$D),"") -> 91.35 | P42: =IFERROR(_xlfn.XLOOKUP($B42,'Ownership Metrics'!$A:$A,'Ownership Metrics'!$E:$E),"") -> 92.39 | Q42: =IFERROR(_xlfn.XLOOKUP($B42,'Ownership Metrics'!$A:$A,'Ownership Metrics'!$F:$F),"") -> 2 | R42: =IFERROR(_xlfn.XLOOKUP($B42,'Ownership Metrics'!$A:$A,'Ownership Metrics'!$G:$G),"") -> 89 | S42: =IFERROR(_xlfn.XLOOKUP($B42,'Ownership Metrics'!$A:$A,'Ownership Metrics'!$H:$H),"") -> Mayoritas | T42: =IFERROR(_xlfn.XLOOKUP($B42,'Ownership Metrics'!$A:$A,'Ownership Metrics'!$I:$I),"") -> Tinggi | U42: =IF(COUNTIFS($B$2:$B42,$B42,$D$2:$D42,$D42)=1,1,0) -> 1 | V42: =SUMIFS($L$2:$L$10000,$B$2:$B$10000,$B42,$D$2:$D$10000,$D42) -> 91.35 | W42: =COUNTIFS($B$2:$B$10000,$B42,$U$2:$U$10000,1,$X$2:$X$10000,">"&$X42)+1 -> 1 | X42: =$V42-(ROW()*0.0000000001) -> 91.35
A43: 46265 | B43: ADES | C43: AKASHA WIRA INTERNATIONAL Tbk | D43: SURONO SUBEKTI | E43: Individual | F43: L | G43: INDONESIAN | H43: INDONESIA | I43: 6106500 | J43: 0 | K43: 6106500 | L43: 1.04 | M43: =IFERROR(_xlfn.XLOOKUP($B43,'Ownership Metrics'!$A:$A,'Ownership Metrics'!$B:$B),"") -> 7.61 | N43: =IFERROR(_xlfn.XLOOKUP($B43,'Ownership Metrics'!$A:$A,'Ownership Metrics'!$C:$C),"") -> 8346 | O43: =IFERROR(_xlfn.XLOOKUP($B43,'Ownership Metrics'!$A:$A,'Ownership Metrics'!$D:$D),"") -> 91.35 | P43: =IFERROR(_xlfn.XLOOKUP($B43,'Ownership Metrics'!$A:$A,'Ownership Metrics'!$E:$E),"") -> 92.39 | Q43: =IFERROR(_xlfn.XLOOKUP($B43,'Ownership Metrics'!$A:$A,'Ownership Metrics'!$F:$F),"") -> 2 | R43: =IFERROR(_xlfn.XLOOKUP($B43,'Ownership Metrics'!$A:$A,'Ownership Metrics'!$G:$G),"") -> 89 | S43: =IFERROR(_xlfn.XLOOKUP($B43,'Ownership Metrics'!$A:$A,'Ownership Metrics'!$H:$H),"") -> Mayoritas | T43: =IFERROR(_xlfn.XLOOKUP($B43,'Ownership Metrics'!$A:$A,'Ownership Metrics'!$I:$I),"") -> Tinggi | U43: =IF(COUNTIFS($B$2:$B43,$B43,$D$2:$D43,$D43)=1,1,0) -> 1 | V43: =SUMIFS($L$2:$L$10000,$B$2:$B$10000,$B43,$D$2:$D$10000,$D43) -> 1.04 | W43: =COUNTIFS($B$2:$B$10000,$B43,$U$2:$U$10000,1,$X$2:$X$10000,">"&$X43)+1 -> 2 | X43: =$V43-(ROW()*0.0000000001) -> 1.04
A44: 46265 | B44: ADHI | C44: ADHI KARYA (PERSERO) Tbk | D44: PERUSAHAAN PERSEROAN (PERSERO) PT DANANTARA ASSET MANAGEMENT | E44: Corporate | F44: L | I44: 0 | J44: 5354686054 | K44: 5354686054 | L44: 63.69 | M44: =IFERROR(_xlfn.XLOOKUP($B44,'Ownership Metrics'!$A:$A,'Ownership Metrics'!$B:$B),"") -> 29.44 | N44: =IFERROR(_xlfn.XLOOKUP($B44,'Ownership Metrics'!$A:$A,'Ownership Metrics'!$C:$C),"") -> 4070 | O44: =IFERROR(_xlfn.XLOOKUP($B44,'Ownership Metrics'!$A:$A,'Ownership Metrics'!$D:$D),"") -> 63.69 | P44: =IFERROR(_xlfn.XLOOKUP($B44,'Ownership Metrics'!$A:$A,'Ownership Metrics'!$E:$E),"") -> 68.38 | Q44: =IFERROR(_xlfn.XLOOKUP($B44,'Ownership Metrics'!$A:$A,'Ownership Metrics'!$F:$F),"") -> 5 | R44: =IFERROR(_xlfn.XLOOKUP($B44,'Ownership Metrics'!$A:$A,'Ownership Metrics'!$G:$G),"") -> 58 | S44: =IFERROR(_xlfn.XLOOKUP($B44,'Ownership Metrics'!$A:$A,'Ownership Metrics'!$H:$H),"") -> Mayoritas | T44: =IFERROR(_xlfn.XLOOKUP($B44,'Ownership Metrics'!$A:$A,'Ownership Metrics'!$I:$I),"") -> Tinggi | U44: =IF(COUNTIFS($B$2:$B44,$B44,$D$2:$D44,$D44)=1,1,0) -> 1 | V44: =SUMIFS($L$2:$L$10000,$B$2:$B$10000,$B44,$D$2:$D$10000,$D44) -> 63.69 | W44: =COUNTIFS($B$2:$B$10000,$B44,$U$2:$U$10000,1,$X$2:$X$10000,">"&$X44)+1 -> 1 | X44: =$V44-(ROW()*0.0000000001) -> 63.69
A45: 46265 | B45: ADHI | C45: ADHI KARYA (PERSERO) Tbk | D45: PT WARUNA NUSASENTANA | E45: Firm | F45: L | H45: INDONESIA | I45: 96194100 | J45: 0 | K45: 96194100 | L45: 1.14 | M45: =IFERROR(_xlfn.XLOOKUP($B45,'Ownership Metrics'!$A:$A,'Ownership Metrics'!$B:$B),"") -> 29.44 | N45: =IFERROR(_xlfn.XLOOKUP($B45,'Ownership Metrics'!$A:$A,'Ownership Metrics'!$C:$C),"") -> 4070 | O45: =IFERROR(_xlfn.XLOOKUP($B45,'Ownership Metrics'!$A:$A,'Ownership Metrics'!$D:$D),"") -> 63.69 | P45: =IFERROR(_xlfn.XLOOKUP($B45,'Ownership Metrics'!$A:$A,'Ownership Metrics'!$E:$E),"") -> 68.38 | Q45: =IFERROR(_xlfn.XLOOKUP($B45,'Ownership Metrics'!$A:$A,'Ownership Metrics'!$F:$F),"") -> 5 | R45: =IFERROR(_xlfn.XLOOKUP($B45,'Ownership Metrics'!$A:$A,'Ownership Metrics'!$G:$G),"") -> 58 | S45: =IFERROR(_xlfn.XLOOKUP($B45,'Ownership Metrics'!$A:$A,'Ownership Metrics'!$H:$H),"") -> Mayoritas | T45: =IFERROR(_xlfn.XLOOKUP($B45,'Ownership Metrics'!$A:$A,'Ownership Metrics'!$I:$I),"") -> Tinggi | U45: =IF(COUNTIFS($B$2:$B45,$B45,$D$2:$D45,$D45)=1,1,0) -> 1 | V45: =SUMIFS($L$2:$L$10000,$B$2:$B$10000,$B45,$D$2:$D$10000,$D45) -> 1.14 | W45: =COUNTIFS($B$2:$B$10000,$B45,$U$2:$U$10000,1,$X$2:$X$10000,">"&$X45)+1 -> 4 | X45: =$V45-(ROW()*0.0000000001) -> 1.14
A46: 46265 | B46: ADHI | C46: ADHI KARYA (PERSERO) Tbk | D46: PT. MITRACOMM EKASARANA | E46: Corporate | F46: L | H46: INDONESIA | I46: 87662200 | J46: 0 | K46: 87662200 | L46: 1.04 | M46: =IFERROR(_xlfn.XLOOKUP($B46,'Ownership Metrics'!$A:$A,'Ownership Metrics'!$B:$B),"") -> 29.44 | N46: =IFERROR(_xlfn.XLOOKUP($B46,'Ownership Metrics'!$A:$A,'Ownership Metrics'!$C:$C),"") -> 4070 | O46: =IFERROR(_xlfn.XLOOKUP($B46,'Ownership Metrics'!$A:$A,'Ownership Metrics'!$D:$D),"") -> 63.69 | P46: =IFERROR(_xlfn.XLOOKUP($B46,'Ownership Metrics'!$A:$A,'Ownership Metrics'!$E:$E),"") -> 68.38 | Q46: =IFERROR(_xlfn.XLOOKUP($B46,'Ownership Metrics'!$A:$A,'Ownership Metrics'!$F:$F),"") -> 5 | R46: =IFERROR(_xlfn.XLOOKUP($B46,'Ownership Metrics'!$A:$A,'Ownership Metrics'!$G:$G),"") -> 58 | S46: =IFERROR(_xlfn.XLOOKUP($B46,'Ownership Metrics'!$A:$A,'Ownership Metrics'!$H:$H),"") -> Mayoritas | T46: =IFERROR(_xlfn.XLOOKUP($B46,'Ownership Metrics'!$A:$A,'Ownership Metrics'!$I:$I),"") -> Tinggi | U46: =IF(COUNTIFS($B$2:$B46,$B46,$D$2:$D46,$D46)=1,1,0) -> 1 | V46: =SUMIFS($L$2:$L$10000,$B$2:$B$10000,$B46,$D$2:$D$10000,$D46) -> 1.04 | W46: =COUNTIFS($B$2:$B$10000,$B46,$U$2:$U$10000,1,$X$2:$X$10000,">"&$X46)+1 -> 5 | X46: =$V46-(ROW()*0.0000000001) -> 1.04
A47: 46265 | B47: ADHI | C47: ADHI KARYA (PERSERO) Tbk | D47: SALIM LIM | E47: Individual | F47: L | G47: INDONESIAN | H47: INDONESIA | I47: 149273123 | J47: 0 | K47: 149273123 | L47: 1.78 | M47: =IFERROR(_xlfn.XLOOKUP($B47,'Ownership Metrics'!$A:$A,'Ownership Metrics'!$B:$B),"") -> 29.44 | N47: =IFERROR(_xlfn.XLOOKUP($B47,'Ownership Metrics'!$A:$A,'Ownership Metrics'!$C:$C),"") -> 4070 | O47: =IFERROR(_xlfn.XLOOKUP($B47,'Ownership Metrics'!$A:$A,'Ownership Metrics'!$D:$D),"") -> 63.69 | P47: =IFERROR(_xlfn.XLOOKUP($B47,'Ownership Metrics'!$A:$A,'Ownership Metrics'!$E:$E),"") -> 68.38 | Q47: =IFERROR(_xlfn.XLOOKUP($B47,'Ownership Metrics'!$A:$A,'Ownership Metrics'!$F:$F),"") -> 5 | R47: =IFERROR(_xlfn.XLOOKUP($B47,'Ownership Metrics'!$A:$A,'Ownership Metrics'!$G:$G),"") -> 58 | S47: =IFERROR(_xlfn.XLOOKUP($B47,'Ownership Metrics'!$A:$A,'Ownership Metrics'!$H:$H),"") -> Mayoritas | T47: =IFERROR(_xlfn.XLOOKUP($B47,'Ownership Metrics'!$A:$A,'Ownership Metrics'!$I:$I),"") -> Tinggi | U47: =IF(COUNTIFS($B$2:$B47,$B47,$D$2:$D47,$D47)=1,1,0) -> 1 | V47: =SUMIFS($L$2:$L$10000,$B$2:$B$10000,$B47,$D$2:$D$10000,$D47) -> 1.78 | W47: =COUNTIFS($B$2:$B$10000,$B47,$U$2:$U$10000,1,$X$2:$X$10000,">"&$X47)+1 -> 3 | X47: =$V47-(ROW()*0.0000000001) -> 1.78
A48: 46265 | B48: ADHI | C48: ADHI KARYA (PERSERO) Tbk | D48: PANIN SEKURITAS Tbk, PT | E48: Securities Company | F48: L | H48: INDONESIA | I48: 244716368 | J48: 0 | K48: 244716368 | L48: 2.91 | M48: =IFERROR(_xlfn.XLOOKUP($B48,'Ownership Metrics'!$A:$A,'Ownership Metrics'!$B:$B),"") -> 29.44 | N48: =IFERROR(_xlfn.XLOOKUP($B48,'Ownership Metrics'!$A:$A,'Ownership Metrics'!$C:$C),"") -> 4070 | O48: =IFERROR(_xlfn.XLOOKUP($B48,'Ownership Metrics'!$A:$A,'Ownership Metrics'!$D:$D),"") -> 63.69 | P48: =IFERROR(_xlfn.XLOOKUP($B48,'Ownership Metrics'!$A:$A,'Ownership Metrics'!$E:$E),"") -> 68.38 | Q48: =IFERROR(_xlfn.XLOOKUP($B48,'Ownership Metrics'!$A:$A,'Ownership Metrics'!$F:$F),"") -> 5 | R48: =IFERROR(_xlfn.XLOOKUP($B48,'Ownership Metrics'!$A:$A,'Ownership Metrics'!$G:$G),"") -> 58 | S48: =IFERROR(_xlfn.XLOOKUP($B48,'Ownership Metrics'!$A:$A,'Ownership Metrics'!$H:$H),"") -> Mayoritas | T48: =IFERROR(_xlfn.XLOOKUP($B48,'Ownership Metrics'!$A:$A,'Ownership Metrics'!$I:$I),"") -> Tinggi | U48: =IF(COUNTIFS($B$2:$B48,$B48,$D$2:$D48,$D48)=1,1,0) -> 1 | V48: =SUMIFS($L$2:$L$10000,$B$2:$B$10000,$B48,$D$2:$D$10000,$D48) -> 2.91 | W48: =COUNTIFS($B$2:$B$10000,$B48,$U$2:$U$10000,1,$X$2:$X$10000,">"&$X48)+1 -> 2 | X48: =$V48-(ROW()*0.0000000001) -> 2.91
A49: 46265 | B49: ADMF | C49: ADIRA DINAMIKA MULTI FINANCE Tbk | D49: BANK DANAMON INDONESIA Tbk, PT - REGISTRAR | E49: Bank | F49: L | H49: INDONESIA | I49: 920700000 | J49: 0 | K49: 920700000 | L49: 74.5 | M49: =IFERROR(_xlfn.XLOOKUP($B49,'Ownership Metrics'!$A:$A,'Ownership Metrics'!$B:$B),"") -> 6.6 | N49: =IFERROR(_xlfn.XLOOKUP($B49,'Ownership Metrics'!$A:$A,'Ownership Metrics'!$C:$C),"") -> 5907 | O49: =IFERROR(_xlfn.XLOOKUP($B49,'Ownership Metrics'!$A:$A,'Ownership Metrics'!$D:$D),"") -> 74.5 | P49: =IFERROR(_xlfn.XLOOKUP($B49,'Ownership Metrics'!$A:$A,'Ownership Metrics'!$E:$E),"") -> 93.4 | Q49: =IFERROR(_xlfn.XLOOKUP($B49,'Ownership Metrics'!$A:$A,'Ownership Metrics'!$F:$F),"") -> 2 | R49: =IFERROR(_xlfn.XLOOKUP($B49,'Ownership Metrics'!$A:$A,'Ownership Metrics'!$G:$G),"") -> 78 | S49: =IFERROR(_xlfn.XLOOKUP($B49,'Ownership Metrics'!$A:$A,'Ownership Metrics'!$H:$H),"") -> Mayoritas | T49: =IFERROR(_xlfn.XLOOKUP($B49,'Ownership Metrics'!$A:$A,'Ownership Metrics'!$I:$I),"") -> Tinggi | U49: =IF(COUNTIFS($B$2:$B49,$B49,$D$2:$D49,$D49)=1,1,0) -> 1 | V49: =SUMIFS($L$2:$L$10000,$B$2:$B$10000,$B49,$D$2:$D$10000,$D49) -> 74.5 | W49: =COUNTIFS($B$2:$B$10000,$B49,$U$2:$U$10000,1,$X$2:$X$10000,">"&$X49)+1 -> 1 | X49: =$V49-(ROW()*0.0000000001) -> 74.5
A50: 46265 | B50: ADMF | C50: ADIRA DINAMIKA MULTI FINANCE Tbk | D50: MUFG Bank Ltd | E50: Private Bank | F50: F | H50: JAPAN | I50: 233537759 | J50: 0 | K50: 233537759 | L50: 18.9 | M50: =IFERROR(_xlfn.XLOOKUP($B50,'Ownership Metrics'!$A:$A,'Ownership Metrics'!$B:$B),"") -> 6.6 | N50: =IFERROR(_xlfn.XLOOKUP($B50,'Ownership Metrics'!$A:$A,'Ownership Metrics'!$C:$C),"") -> 5907 | O50: =IFERROR(_xlfn.XLOOKUP($B50,'Ownership Metrics'!$A:$A,'Ownership Metrics'!$D:$D),"") -> 74.5 | P50: =IFERROR(_xlfn.XLOOKUP($B50,'Ownership Metrics'!$A:$A,'Ownership Metrics'!$E:$E),"") -> 93.4 | Q50: =IFERROR(_xlfn.XLOOKUP($B50,'Ownership Metrics'!$A:$A,'Ownership Metrics'!$F:$F),"") -> 2 | R50: =IFERROR(_xlfn.XLOOKUP($B50,'Ownership Metrics'!$A:$A,'Ownership Metrics'!$G:$G),"") -> 78 | S50: =IFERROR(_xlfn.XLOOKUP($B50,'Ownership Metrics'!$A:$A,'Ownership Metrics'!$H:$H),"") -> Mayoritas | T50: =IFERROR(_xlfn.XLOOKUP($B50,'Ownership Metrics'!$A:$A,'Ownership Metrics'!$I:$I),"") -> Tinggi | U50: =IF(COUNTIFS($B$2:$B50,$B50,$D$2:$D50,$D50)=1,1,0) -> 1 | V50: =SUMIFS($L$2:$L$10000,$B$2:$B$10000,$B50,$D$2:$D$10000,$D50) -> 18.9 | W50: =COUNTIFS($B$2:$B$10000,$B50,$U$2:$U$10000,1,$X$2:$X$10000,">"&$X50)+1 -> 2 | X50: =$V50-(ROW()*0.0000000001) -> 18.9
A51: 46265 | B51: ADMG | C51: POLYCHEM INDONESIA Tbk | D51: GAJAH TUNGGAL, TbK. PT. | E51: Corporate | F51: L | H51: INDONESIA | I51: 994150000 | J51: 0 | K51: 994150000 | L51: 25.56 | M51: =IFERROR(_xlfn.XLOOKUP($B51,'Ownership Metrics'!$A:$A,'Ownership Metrics'!$B:$B),"") -> 9.18 | N51: =IFERROR(_xlfn.XLOOKUP($B51,'Ownership Metrics'!$A:$A,'Ownership Metrics'!$C:$C),"") -> 3225 | O51: =IFERROR(_xlfn.XLOOKUP($B51,'Ownership Metrics'!$A:$A,'Ownership Metrics'!$D:$D),"") -> 49.51 | P51: =IFERROR(_xlfn.XLOOKUP($B51,'Ownership Metrics'!$A:$A,'Ownership Metrics'!$E:$E),"") -> 85.49 | Q51: =IFERROR(_xlfn.XLOOKUP($B51,'Ownership Metrics'!$A:$A,'Ownership Metrics'!$F:$F),"") -> 6 | R51: =IFERROR(_xlfn.XLOOKUP($B51,'Ownership Metrics'!$A:$A,'Ownership Metrics'!$G:$G),"") -> 59 | S51: =IFERROR(_xlfn.XLOOKUP($B51,'Ownership Metrics'!$A:$A,'Ownership Metrics'!$H:$H),"") -> Terkonsentrasi | T51: =IFERROR(_xlfn.XLOOKUP($B51,'Ownership Metrics'!$A:$A,'Ownership Metrics'!$I:$I),"") -> Tinggi | U51: =IF(COUNTIFS($B$2:$B51,$B51,$D$2:$D51,$D51)=1,1,0) -> 1 | V51: =SUMIFS($L$2:$L$10000,$B$2:$B$10000,$B51,$D$2:$D$10000,$D51) -> 25.56 | W51: =COUNTIFS($B$2:$B$10000,$B51,$U$2:$U$10000,1,$X$2:$X$10000,">"&$X51)+1 -> 2 | X51: =$V51-(ROW()*0.0000000001) -> 25.56
A52: 46265 | B52: ADMG | C52: POLYCHEM INDONESIA Tbk | D52: PT SATYA MULIA GEMA GEMILANG | E52: Corporate | F52: L | H52: INDONESIA | I52: 405356593 | J52: 0 | K52: 405356593 | L52: 10.42 | M52: =IFERROR(_xlfn.XLOOKUP($B52,'Ownership Metrics'!$A:$A,'Ownership Metrics'!$B:$B),"") -> 9.18 | N52: =IFERROR(_xlfn.XLOOKUP($B52,'Ownership Metrics'!$A:$A,'Ownership Metrics'!$C:$C),"") -> 3225 | O52: =IFERROR(_xlfn.XLOOKUP($B52,'Ownership Metrics'!$A:$A,'Ownership Metrics'!$D:$D),"") -> 49.51 | P52: =IFERROR(_xlfn.XLOOKUP($B52,'Ownership Metrics'!$A:$A,'Ownership Metrics'!$E:$E),"") -> 85.49 | Q52: =IFERROR(_xlfn.XLOOKUP($B52,'Ownership Metrics'!$A:$A,'Ownership Metrics'!$F:$F),"") -> 6 | R52: =IFERROR(_xlfn.XLOOKUP($B52,'Ownership Metrics'!$A:$A,'Ownership Metrics'!$G:$G),"") -> 59 | S52: =IFERROR(_xlfn.XLOOKUP($B52,'Ownership Metrics'!$A:$A,'Ownership Metrics'!$H:$H),"") -> Terkonsentrasi | T52: =IFERROR(_xlfn.XLOOKUP($B52,'Ownership Metrics'!$A:$A,'Ownership Metrics'!$I:$I),"") -> Tinggi | U52: =IF(COUNTIFS($B$2:$B52,$B52,$D$2:$D52,$D52)=1,1,0) -> 1 | V52: =SUMIFS($L$2:$L$10000,$B$2:$B$10000,$B52,$D$2:$D$10000,$D52) -> 10.42 | W52: =COUNTIFS($B$2:$B$10000,$B52,$U$2:$U$10000,1,$X$2:$X$10000,">"&$X52)+1 -> 3 | X52: =$V52-(ROW()*0.0000000001) -> 10.42
A53: 46265 | B53: ADMG | C53: POLYCHEM INDONESIA Tbk | D53: NEW WORLD GLOBAL LIMITED | E53: Corporate | F53: F | I53: 0 | J53: 39997466 | K53: 39997466 | L53: 1.03 | M53: =IFERROR(_xlfn.XLOOKUP($B53,'Ownership Metrics'!$A:$A,'Ownership Metrics'!$B:$B),"") -> 9.18 | N53: =IFERROR(_xlfn.XLOOKUP($B53,'Ownership Metrics'!$A:$A,'Ownership Metrics'!$C:$C),"") -> 3225 | O53: =IFERROR(_xlfn.XLOOKUP($B53,'Ownership Metrics'!$A:$A,'Ownership Metrics'!$D:$D),"") -> 49.51 | P53: =IFERROR(_xlfn.XLOOKUP($B53,'Ownership Metrics'!$A:$A,'Ownership Metrics'!$E:$E),"") -> 85.49 | Q53: =IFERROR(_xlfn.XLOOKUP($B53,'Ownership Metrics'!$A:$A,'Ownership Metrics'!$F:$F),"") -> 6 | R53: =IFERROR(_xlfn.XLOOKUP($B53,'Ownership Metrics'!$A:$A,'Ownership Metrics'!$G:$G),"") -> 59 | S53: =IFERROR(_xlfn.XLOOKUP($B53,'Ownership Metrics'!$A:$A,'Ownership Metrics'!$H:$H),"") -> Terkonsentrasi | T53: =IFERROR(_xlfn.XLOOKUP($B53,'Ownership Metrics'!$A:$A,'Ownership Metrics'!$I:$I),"") -> Tinggi | U53: =IF(COUNTIFS($B$2:$B53,$B53,$D$2:$D53,$D53)=1,1,0) -> 1 | V53: =SUMIFS($L$2:$L$10000,$B$2:$B$10000,$B53,$D$2:$D$10000,$D53) -> 1.03 | W53: =COUNTIFS($B$2:$B$10000,$B53,$U$2:$U$10000,1,$X$2:$X$10000,">"&$X53)+1 -> 6 | X53: =$V53-(ROW()*0.0000000001) -> 1.03
A54: 46265 | B54: ADMG | C54: POLYCHEM INDONESIA Tbk | D54: SOETIKNO HARTO SOEWITO | E54: Individual | F54: L | G54: INDONESIAN | I54: 117100500 | J54: 0 | K54: 117100500 | L54: 3.01 | M54: =IFERROR(_xlfn.XLOOKUP($B54,'Ownership Metrics'!$A:$A,'Ownership Metrics'!$B:$B),"") -> 9.18 | N54: =IFERROR(_xlfn.XLOOKUP($B54,'Ownership Metrics'!$A:$A,'Ownership Metrics'!$C:$C),"") -> 3225 | O54: =IFERROR(_xlfn.XLOOKUP($B54,'Ownership Metrics'!$A:$A,'Ownership Metrics'!$D:$D),"") -> 49.51 | P54: =IFERROR(_xlfn.XLOOKUP($B54,'Ownership Metrics'!$A:$A,'Ownership Metrics'!$E:$E),"") -> 85.49 | Q54: =IFERROR(_xlfn.XLOOKUP($B54,'Ownership Metrics'!$A:$A,'Ownership Metrics'!$F:$F),"") -> 6 | R54: =IFERROR(_xlfn.XLOOKUP($B54,'Ownership Metrics'!$A:$A,'Ownership Metrics'!$G:$G),"") -> 59 | S54: =IFERROR(_xlfn.XLOOKUP($B54,'Ownership Metrics'!$A:$A,'Ownership Metrics'!$H:$H),"") -> Terkonsentrasi | T54: =IFERROR(_xlfn.XLOOKUP($B54,'Ownership Metrics'!$A:$A,'Ownership Metrics'!$I:$I),"") -> Tinggi | U54: =IF(COUNTIFS($B$2:$B54,$B54,$D$2:$D54,$D54)=1,1,0) -> 1 | V54: =SUMIFS($L$2:$L$10000,$B$2:$B$10000,$B54,$D$2:$D$10000,$D54) -> 3.01 | W54: =COUNTIFS($B$2:$B$10000,$B54,$U$2:$U$10000,1,$X$2:$X$10000,">"&$X54)+1 -> 4 | X54: =$V54-(ROW()*0.0000000001) -> 3.01
A55: 46265 | B55: ADMG | C55: POLYCHEM INDONESIA Tbk | D55: DRS LO KHENG HONG | E55: Individual | F55: L | G55: INDONESIAN | H55: INDONESIA | I55: 50318100 | J55: 0 | K55: 50318100 | L55: 1.29 | M55: =IFERROR(_xlfn.XLOOKUP($B55,'Ownership Metrics'!$A:$A,'Ownership Metrics'!$B:$B),"") -> 9.18 | N55: =IFERROR(_xlfn.XLOOKUP($B55,'Ownership Metrics'!$A:$A,'Ownership Metrics'!$C:$C),"") -> 3225 | O55: =IFERROR(_xlfn.XLOOKUP($B55,'Ownership Metrics'!$A:$A,'Ownership Metrics'!$D:$D),"") -> 49.51 | P55: =IFERROR(_xlfn.XLOOKUP($B55,'Ownership Metrics'!$A:$A,'Ownership Metrics'!$E:$E),"") -> 85.49 | Q55: =IFERROR(_xlfn.XLOOKUP($B55,'Ownership Metrics'!$A:$A,'Ownership Metrics'!$F:$F),"") -> 6 | R55: =IFERROR(_xlfn.XLOOKUP($B55,'Ownership Metrics'!$A:$A,'Ownership Metrics'!$G:$G),"") -> 59 | S55: =IFERROR(_xlfn.XLOOKUP($B55,'Ownership Metrics'!$A:$A,'Ownership Metrics'!$H:$H),"") -> Terkonsentrasi | T55: =IFERROR(_xlfn.XLOOKUP($B55,'Ownership Metrics'!$A:$A,'Ownership Metrics'!$I:$I),"") -> Tinggi | U55: =IF(COUNTIFS($B$2:$B55,$B55,$D$2:$D55,$D55)=1,1,0) -> 1 | V55: =SUMIFS($L$2:$L$10000,$B$2:$B$10000,$B55,$D$2:$D$10000,$D55) -> 1.29 | W55: =COUNTIFS($B$2:$B$10000,$B55,$U$2:$U$10000,1,$X$2:$X$10000,">"&$X55)+1 -> 5 | X55: =$V55-(ROW()*0.0000000001) -> 1.29
A56: 46265 | B56: ADMG | C56: POLYCHEM INDONESIA Tbk | D56: PROVESTMENT LIMITED | E56: Partnership | F56: F | H56: VIRGIN ISLANDS, BRITISH | I56: 1925414417 | J56: 0 | K56: 1925414417 | L56: 49.51 | M56: =IFERROR(_xlfn.XLOOKUP($B56,'Ownership Metrics'!$A:$A,'Ownership Metrics'!$B:$B),"") -> 9.18 | N56: =IFERROR(_xlfn.XLOOKUP($B56,'Ownership Metrics'!$A:$A,'Ownership Metrics'!$C:$C),"") -> 3225 | O56: =IFERROR(_xlfn.XLOOKUP($B56,'Ownership Metrics'!$A:$A,'Ownership Metrics'!$D:$D),"") -> 49.51 | P56: =IFERROR(_xlfn.XLOOKUP($B56,'Ownership Metrics'!$A:$A,'Ownership Metrics'!$E:$E),"") -> 85.49 | Q56: =IFERROR(_xlfn.XLOOKUP($B56,'Ownership Metrics'!$A:$A,'Ownership Metrics'!$F:$F),"") -> 6 | R56: =IFERROR(_xlfn.XLOOKUP($B56,'Ownership Metrics'!$A:$A,'Ownership Metrics'!$G:$G),"") -> 59 | S56: =IFERROR(_xlfn.XLOOKUP($B56,'Ownership Metrics'!$A:$A,'Ownership Metrics'!$H:$H),"") -> Terkonsentrasi | T56: =IFERROR(_xlfn.XLOOKUP($B56,'Ownership Metrics'!$A:$A,'Ownership Metrics'!$I:$I),"") -> Tinggi | U56: =IF(COUNTIFS($B$2:$B56,$B56,$D$2:$D56,$D56)=1,1,0) -> 1 | V56: =SUMIFS($L$2:$L$10000,$B$2:$B$10000,$B56,$D$2:$D$10000,$D56) -> 49.51 | W56: =COUNTIFS($B$2:$B$10000,$B56,$U$2:$U$10000,1,$X$2:$X$10000,">"&$X56)+1 -> 1 | X56: =$V56-(ROW()*0.0000000001) -> 49.51
A57: 46265 | B57: ADMR | C57: ALAMTRI MINERALS INDONESIA Tbk | D57: ALAMTRI RESOURCES INDONESIA TBK PT | E57: Corporate | F57: L | H57: INDONESIA | I57: 34933166100 | J57: 0 | K57: 34933166100 | L57: 85.45 | M57: =IFERROR(_xlfn.XLOOKUP($B57,'Ownership Metrics'!$A:$A,'Ownership Metrics'!$B:$B),"") -> 12.18 | N57: =IFERROR(_xlfn.XLOOKUP($B57,'Ownership Metrics'!$A:$A,'Ownership Metrics'!$C:$C),"") -> 7305 | O57: =IFERROR(_xlfn.XLOOKUP($B57,'Ownership Metrics'!$A:$A,'Ownership Metrics'!$D:$D),"") -> 85.45 | P57: =IFERROR(_xlfn.XLOOKUP($B57,'Ownership Metrics'!$A:$A,'Ownership Metrics'!$E:$E),"") -> 87.82 | Q57: =IFERROR(_xlfn.XLOOKUP($B57,'Ownership Metrics'!$A:$A,'Ownership Metrics'!$F:$F),"") -> 3 | R57: =IFERROR(_xlfn.XLOOKUP($B57,'Ownership Metrics'!$A:$A,'Ownership Metrics'!$G:$G),"") -> 82 | S57: =IFERROR(_xlfn.XLOOKUP($B57,'Ownership Metrics'!$A:$A,'Ownership Metrics'!$H:$H),"") -> Mayoritas | T57: =IFERROR(_xlfn.XLOOKUP($B57,'Ownership Metrics'!$A:$A,'Ownership Metrics'!$I:$I),"") -> Tinggi | U57: =IF(COUNTIFS($B$2:$B57,$B57,$D$2:$D57,$D57)=1,1,0) -> 1 | V57: =SUMIFS($L$2:$L$10000,$B$2:$B$10000,$B57,$D$2:$D$10000,$D57) -> 85.45 | W57: =COUNTIFS($B$2:$B$10000,$B57,$U$2:$U$10000,1,$X$2:$X$10000,">"&$X57)+1 -> 1 | X57: =$V57-(ROW()*0.0000000001) -> 85.45
A58: 46265 | B58: ADMR | C58: ALAMTRI MINERALS INDONESIA Tbk | D58: SILVERCITY ENTERPRISE LIMITED | E58: Corporate | F58: F | H58: HONG KONG | I58: 436463680 | J58: 0 | K58: 436463680 | L58: 1.07 | M58: =IFERROR(_xlfn.XLOOKUP($B58,'Ownership Metrics'!$A:$A,'Ownership Metrics'!$B:$B),"") -> 12.18 | N58: =IFERROR(_xlfn.XLOOKUP($B58,'Ownership Metrics'!$A:$A,'Ownership Metrics'!$C:$C),"") -> 7305 | O58: =IFERROR(_xlfn.XLOOKUP($B58,'Ownership Metrics'!$A:$A,'Ownership Metrics'!$D:$D),"") -> 85.45 | P58: =IFERROR(_xlfn.XLOOKUP($B58,'Ownership Metrics'!$A:$A,'Ownership Metrics'!$E:$E),"") -> 87.82 | Q58: =IFERROR(_xlfn.XLOOKUP($B58,'Ownership Metrics'!$A:$A,'Ownership Metrics'!$F:$F),"") -> 3 | R58: =IFERROR(_xlfn.XLOOKUP($B58,'Ownership Metrics'!$A:$A,'Ownership Metrics'!$G:$G),"") -> 82 | S58: =IFERROR(_xlfn.XLOOKUP($B58,'Ownership Metrics'!$A:$A,'Ownership Metrics'!$H:$H),"") -> Mayoritas | T58: =IFERROR(_xlfn.XLOOKUP($B58,'Ownership Metrics'!$A:$A,'Ownership Metrics'!$I:$I),"") -> Tinggi | U58: =IF(COUNTIFS($B$2:$B58,$B58,$D$2:$D58,$D58)=1,1,0) -> 1 | V58: =SUMIFS($L$2:$L$10000,$B$2:$B$10000,$B58,$D$2:$D$10000,$D58) -> 1.07 | W58: =COUNTIFS($B$2:$B$10000,$B58,$U$2:$U$10000,1,$X$2:$X$10000,">"&$X58)+1 -> 3 | X58: =$V58-(ROW()*0.0000000001) -> 1.07
A59: 46265 | B59: ADMR | C59: ALAMTRI MINERALS INDONESIA Tbk | D59: VERANUS CAPITAL PTE. LTD. | E59: Investment Advisors | F59: F | H59: SINGAPORE | I59: 532762560 | J59: 0 | K59: 532762560 | L59: 1.3 | M59: =IFERROR(_xlfn.XLOOKUP($B59,'Ownership Metrics'!$A:$A,'Ownership Metrics'!$B:$B),"") -> 12.18 | N59: =IFERROR(_xlfn.XLOOKUP($B59,'Ownership Metrics'!$A:$A,'Ownership Metrics'!$C:$C),"") -> 7305 | O59: =IFERROR(_xlfn.XLOOKUP($B59,'Ownership Metrics'!$A:$A,'Ownership Metrics'!$D:$D),"") -> 85.45 | P59: =IFERROR(_xlfn.XLOOKUP($B59,'Ownership Metrics'!$A:$A,'Ownership Metrics'!$E:$E),"") -> 87.82 | Q59: =IFERROR(_xlfn.XLOOKUP($B59,'Ownership Metrics'!$A:$A,'Ownership Metrics'!$F:$F),"") -> 3 | R59: =IFERROR(_xlfn.XLOOKUP($B59,'Ownership Metrics'!$A:$A,'Ownership Metrics'!$G:$G),"") -> 82 | S59: =IFERROR(_xlfn.XLOOKUP($B59,'Ownership Metrics'!$A:$A,'Ownership Metrics'!$H:$H),"") -> Mayoritas | T59: =IFERROR(_xlfn.XLOOKUP($B59,'Ownership Metrics'!$A:$A,'Ownership Metrics'!$I:$I),"") -> Tinggi | U59: =IF(COUNTIFS($B$2:$B59,$B59,$D$2:$D59,$D59)=1,1,0) -> 1 | V59: =SUMIFS($L$2:$L$10000,$B$2:$B$10000,$B59,$D$2:$D$10000,$D59) -> 1.3 | W59: =COUNTIFS($B$2:$B$10000,$B59,$U$2:$U$10000,1,$X$2:$X$10000,">"&$X59)+1 -> 2 | X59: =$V59-(ROW()*0.0000000001) -> 1.3
A60: 46265 | B60: ADRO | C60: ALAMTRI RESOURCES INDONESIA Tbk | D60: SARATOGA INVESTAMA SEDAYA TBK | E60: Private Bank | F60: L | H60: INDONESIA | I60: 1174890670 | J60: 0 | K60: 1174890670 | L60: 4.08 | M60: =IFERROR(_xlfn.XLOOKUP($B60,'Ownership Metrics'!$A:$A,'Ownership Metrics'!$B:$B),"") -> 27.69 | N60: =IFERROR(_xlfn.XLOOKUP($B60,'Ownership Metrics'!$A:$A,'Ownership Metrics'!$C:$C),"") -> 2481 | O60: =IFERROR(_xlfn.XLOOKUP($B60,'Ownership Metrics'!$A:$A,'Ownership Metrics'!$D:$D),"") -> 48.77 | P60: =IFERROR(_xlfn.XLOOKUP($B60,'Ownership Metrics'!$A:$A,'Ownership Metrics'!$E:$E),"") -> 59.74 | Q60: =IFERROR(_xlfn.XLOOKUP($B60,'Ownership Metrics'!$A:$A,'Ownership Metrics'!$F:$F),"") -> 8 | R60: =IFERROR(_xlfn.XLOOKUP($B60,'Ownership Metrics'!$A:$A,'Ownership Metrics'!$G:$G),"") -> 45 | S60: =IFERROR(_xlfn.XLOOKUP($B60,'Ownership Metrics'!$A:$A,'Ownership Metrics'!$H:$H),"") -> Moderat | T60: =IFERROR(_xlfn.XLOOKUP($B60,'Ownership Metrics'!$A:$A,'Ownership Metrics'!$I:$I),"") -> Sedang | U60: =IF(COUNTIFS($B$2:$B60,$B60,$D$2:$D60,$D60)=1,1,0) -> 1 | V60: =SUMIFS($L$2:$L$10000,$B$2:$B$10000,$B60,$D$2:$D$10000,$D60) -> 4.08 | W60: =COUNTIFS($B$2:$B$10000,$B60,$U$2:$U$10000,1,$X$2:$X$10000,">"&$X60)+1 -> 4 | X60: =$V60-(ROW()*0.0000000001) -> 4.08
A61: 46265 | B61: ADRO | C61: ALAMTRI RESOURCES INDONESIA Tbk | D61: ADARO STRATEGIC INVESTMENTS | E61: Corporate | F61: L | H61: INDONESIA | I61: 14045425500 | J61: 0 | K61: 14045425500 | L61: 48.77 | M61: =IFERROR(_xlfn.XLOOKUP($B61,'Ownership Metrics'!$A:$A,'Ownership Metrics'!$B:$B),"") -> 27.69 | N61: =IFERROR(_xlfn.XLOOKUP($B61,'Ownership Metrics'!$A:$A,'Ownership Metrics'!$C:$C),"") -> 2481 | O61: =IFERROR(_xlfn.XLOOKUP($B61,'Ownership Metrics'!$A:$A,'Ownership Metrics'!$D:$D),"") -> 48.77 | P61: =IFERROR(_xlfn.XLOOKUP($B61,'Ownership Metrics'!$A:$A,'Ownership Metrics'!$E:$E),"") -> 59.74 | Q61: =IFERROR(_xlfn.XLOOKUP($B61,'Ownership Metrics'!$A:$A,'Ownership Metrics'!$F:$F),"") -> 8 | R61: =IFERROR(_xlfn.XLOOKUP($B61,'Ownership Metrics'!$A:$A,'Ownership Metrics'!$G:$G),"") -> 45 | S61: =IFERROR(_xlfn.XLOOKUP($B61,'Ownership Metrics'!$A:$A,'Ownership Metrics'!$H:$H),"") -> Moderat | T61: =IFERROR(_xlfn.XLOOKUP($B61,'Ownership Metrics'!$A:$A,'Ownership Metrics'!$I:$I),"") -> Sedang | U61: =IF(COUNTIFS($B$2:$B61,$B61,$D$2:$D61,$D61)=1,1,0) -> 1 | V61: =SUMIFS($L$2:$L$10000,$B$2:$B$10000,$B61,$D$2:$D$10000,$D61) -> 48.77 | W61: =COUNTIFS($B$2:$B$10000,$B61,$U$2:$U$10000,1,$X$2:$X$10000,">"&$X61)+1 -> 1 | X61: =$V61-(ROW()*0.0000000001) -> 48.77
A62: 46265 | B62: ADRO | C62: ALAMTRI RESOURCES INDONESIA Tbk | D62: KOREA SOUTH-EAST POWER CO.LTD | E62: Corporate | F62: F | H62: KOREA, REPUBLIC OF | I62: 480000000 | J62: 0 | K62: 480000000 | L62: 1.67 | M62: =IFERROR(_xlfn.XLOOKUP($B62,'Ownership Metrics'!$A:$A,'Ownership Metrics'!$B:$B),"") -> 27.69 | N62: =IFERROR(_xlfn.XLOOKUP($B62,'Ownership Metrics'!$A:$A,'Ownership Metrics'!$C:$C),"") -> 2481 | O62: =IFERROR(_xlfn.XLOOKUP($B62,'Ownership Metrics'!$A:$A,'Ownership Metrics'!$D:$D),"") -> 48.77 | P62: =IFERROR(_xlfn.XLOOKUP($B62,'Ownership Metrics'!$A:$A,'Ownership Metrics'!$E:$E),"") -> 59.74 | Q62: =IFERROR(_xlfn.XLOOKUP($B62,'Ownership Metrics'!$A:$A,'Ownership Metrics'!$F:$F),"") -> 8 | R62: =IFERROR(_xlfn.XLOOKUP($B62,'Ownership Metrics'!$A:$A,'Ownership Metrics'!$G:$G),"") -> 45 | S62: =IFERROR(_xlfn.XLOOKUP($B62,'Ownership Metrics'!$A:$A,'Ownership Metrics'!$H:$H),"") -> Moderat | T62: =IFERROR(_xlfn.XLOOKUP($B62,'Ownership Metrics'!$A:$A,'Ownership Metrics'!$I:$I),"") -> Sedang | U62: =IF(COUNTIFS($B$2:$B62,$B62,$D$2:$D62,$D62)=1,1,0) -> 1 | V62: =SUMIFS($L$2:$L$10000,$B$2:$B$10000,$B62,$D$2:$D$10000,$D62) -> 1.67 | W62: =COUNTIFS($B$2:$B$10000,$B62,$U$2:$U$10000,1,$X$2:$X$10000,">"&$X62)+1 -> 7 | X62: =$V62-(ROW()*0.0000000001) -> 1.67
A63: 46265 | B63: ADRO | C63: ALAMTRI RESOURCES INDONESIA Tbk | D63: GARIBALDI THOHIR | E63: Individual | F63: L | G63: INDONESIAN | H63: INDONESIA | I63: 1976632710 | J63: 0 | K63: 1976632710 | L63: 6.86 | M63: =IFERROR(_xlfn.XLOOKUP($B63,'Ownership Metrics'!$A:$A,'Ownership Metrics'!$B:$B),"") -> 27.69 | N63: =IFERROR(_xlfn.XLOOKUP($B63,'Ownership Metrics'!$A:$A,'Ownership Metrics'!$C:$C),"") -> 2481 | O63: =IFERROR(_xlfn.XLOOKUP($B63,'Ownership Metrics'!$A:$A,'Ownership Metrics'!$D:$D),"") -> 48.77 | P63: =IFERROR(_xlfn.XLOOKUP($B63,'Ownership Metrics'!$A:$A,'Ownership Metrics'!$E:$E),"") -> 59.74 | Q63: =IFERROR(_xlfn.XLOOKUP($B63,'Ownership Metrics'!$A:$A,'Ownership Metrics'!$F:$F),"") -> 8 | R63: =IFERROR(_xlfn.XLOOKUP($B63,'Ownership Metrics'!$A:$A,'Ownership Metrics'!$G:$G),"") -> 45 | S63: =IFERROR(_xlfn.XLOOKUP($B63,'Ownership Metrics'!$A:$A,'Ownership Metrics'!$H:$H),"") -> Moderat | T63: =IFERROR(_xlfn.XLOOKUP($B63,'Ownership Metrics'!$A:$A,'Ownership Metrics'!$I:$I),"") -> Sedang | U63: =IF(COUNTIFS($B$2:$B63,$B63,$D$2:$D63,$D63)=1,1,0) -> 1 | V63: =SUMIFS($L$2:$L$10000,$B$2:$B$10000,$B63,$D$2:$D$10000,$D63) -> 6.86 | W63: =COUNTIFS($B$2:$B$10000,$B63,$U$2:$U$10000,1,$X$2:$X$10000,">"&$X63)+1 -> 2 | X63: =$V63-(ROW()*0.0000000001) -> 6.86
A64: 46265 | B64: ADRO | C64: ALAMTRI RESOURCES INDONESIA Tbk | D64: IR. T. PERMADI RACHMAT | E64: Individual | F64: L | G64: INDONESIAN | H64: INDONESIA | I64: 1184879901 | J64: 0 | K64: 1184879901 | L64: 4.11 | M64: =IFERROR(_xlfn.XLOOKUP($B64,'Ownership Metrics'!$A:$A,'Ownership Metrics'!$B:$B),"") -> 27.69 | N64: =IFERROR(_xlfn.XLOOKUP($B64,'Ownership Metrics'!$A:$A,'Ownership Metrics'!$C:$C),"") -> 2481 | O64: =IFERROR(_xlfn.XLOOKUP($B64,'Ownership Metrics'!$A:$A,'Ownership Metrics'!$D:$D),"") -> 48.77 | P64: =IFERROR(_xlfn.XLOOKUP($B64,'Ownership Metrics'!$A:$A,'Ownership Metrics'!$E:$E),"") -> 59.74 | Q64: =IFERROR(_xlfn.XLOOKUP($B64,'Ownership Metrics'!$A:$A,'Ownership Metrics'!$F:$F),"") -> 8 | R64: =IFERROR(_xlfn.XLOOKUP($B64,'Ownership Metrics'!$A:$A,'Ownership Metrics'!$G:$G),"") -> 45 | S64: =IFERROR(_xlfn.XLOOKUP($B64,'Ownership Metrics'!$A:$A,'Ownership Metrics'!$H:$H),"") -> Moderat | T64: =IFERROR(_xlfn.XLOOKUP($B64,'Ownership Metrics'!$A:$A,'Ownership Metrics'!$I:$I),"") -> Sedang | U64: =IF(COUNTIFS($B$2:$B64,$B64,$D$2:$D64,$D64)=1,1,0) -> 1 | V64: =SUMIFS($L$2:$L$10000,$B$2:$B$10000,$B64,$D$2:$D$10000,$D64) -> 4.11 | W64: =COUNTIFS($B$2:$B$10000,$B64,$U$2:$U$10000,1,$X$2:$X$10000,">"&$X64)+1 -> 3 | X64: =$V64-(ROW()*0.0000000001) -> 4.11
A65: 46265 | B65: ADRO | C65: ALAMTRI RESOURCES INDONESIA Tbk | D65: EDWIN SOERYADJAYA | E65: Individual | F65: L | G65: INDONESIAN | H65: INDONESIA | I65: 1051738544 | J65: 0 | K65: 1051738544 | L65: 3.65 | M65: =IFERROR(_xlfn.XLOOKUP($B65,'Ownership Metrics'!$A:$A,'Ownership Metrics'!$B:$B),"") -> 27.69 | N65: =IFERROR(_xlfn.XLOOKUP($B65,'Ownership Metrics'!$A:$A,'Ownership Metrics'!$C:$C),"") -> 2481 | O65: =IFERROR(_xlfn.XLOOKUP($B65,'Ownership Metrics'!$A:$A,'Ownership Metrics'!$D:$D),"") -> 48.77 | P65: =IFERROR(_xlfn.XLOOKUP($B65,'Ownership Metrics'!$A:$A,'Ownership Metrics'!$E:$E),"") -> 59.74 | Q65: =IFERROR(_xlfn.XLOOKUP($B65,'Ownership Metrics'!$A:$A,'Ownership Metrics'!$F:$F),"") -> 8 | R65: =IFERROR(_xlfn.XLOOKUP($B65,'Ownership Metrics'!$A:$A,'Ownership Metrics'!$G:$G),"") -> 45 | S65: =IFERROR(_xlfn.XLOOKUP($B65,'Ownership Metrics'!$A:$A,'Ownership Metrics'!$H:$H),"") -> Moderat | T65: =IFERROR(_xlfn.XLOOKUP($B65,'Ownership Metrics'!$A:$A,'Ownership Metrics'!$I:$I),"") -> Sedang | U65: =IF(COUNTIFS($B$2:$B65,$B65,$D$2:$D65,$D65)=1,1,0) -> 1 | V65: =SUMIFS($L$2:$L$10000,$B$2:$B$10000,$B65,$D$2:$D$10000,$D65) -> 3.65 | W65: =COUNTIFS($B$2:$B$10000,$B65,$U$2:$U$10000,1,$X$2:$X$10000,">"&$X65)+1 -> 5 | X65: =$V65-(ROW()*0.0000000001) -> 3.65
A66: 46265 | B66: ADRO | C66: ALAMTRI RESOURCES INDONESIA Tbk | D66: SANDIAGA SALAHUDDIN UNO | E66: Individual | F66: L | G66: INDONESIAN | H66: INDONESIA | I66: 611849202 | J66: 0 | K66: 611849202 | L66: 2.12 | M66: =IFERROR(_xlfn.XLOOKUP($B66,'Ownership Metrics'!$A:$A,'Ownership Metrics'!$B:$B),"") -> 27.69 | N66: =IFERROR(_xlfn.XLOOKUP($B66,'Ownership Metrics'!$A:$A,'Ownership Metrics'!$C:$C),"") -> 2481 | O66: =IFERROR(_xlfn.XLOOKUP($B66,'Ownership Metrics'!$A:$A,'Ownership Metrics'!$D:$D),"") -> 48.77 | P66: =IFERROR(_xlfn.XLOOKUP($B66,'Ownership Metrics'!$A:$A,'Ownership Metrics'!$E:$E),"") -> 59.74 | Q66: =IFERROR(_xlfn.XLOOKUP($B66,'Ownership Metrics'!$A:$A,'Ownership Metrics'!$F:$F),"") -> 8 | R66: =IFERROR(_xlfn.XLOOKUP($B66,'Ownership Metrics'!$A:$A,'Ownership Metrics'!$G:$G),"") -> 45 | S66: =IFERROR(_xlfn.XLOOKUP($B66,'Ownership Metrics'!$A:$A,'Ownership Metrics'!$H:$H),"") -> Moderat | T66: =IFERROR(_xlfn.XLOOKUP($B66,'Ownership Metrics'!$A:$A,'Ownership Metrics'!$I:$I),"") -> Sedang | U66: =IF(COUNTIFS($B$2:$B66,$B66,$D$2:$D66,$D66)=1,1,0) -> 1 | V66: =SUMIFS($L$2:$L$10000,$B$2:$B$10000,$B66,$D$2:$D$10000,$D66) -> 2.12 | W66: =COUNTIFS($B$2:$B$10000,$B66,$U$2:$U$10000,1,$X$2:$X$10000,">"&$X66)+1 -> 6 | X66: =$V66-(ROW()*0.0000000001) -> 2.12
A67: 46265 | B67: ADRO | C67: ALAMTRI RESOURCES INDONESIA Tbk | D67: LAZARD EMERGING MARKETS EQUITY PORTFOLIO | E67: Mutual Funds | F67: F | H67: UNITED STATES | I67: 302334500 | J67: 0 | K67: 302334500 | L67: 1.05 | M67: =IFERROR(_xlfn.XLOOKUP($B67,'Ownership Metrics'!$A:$A,'Ownership Metrics'!$B:$B),"") -> 27.69 | N67: =IFERROR(_xlfn.XLOOKUP($B67,'Ownership Metrics'!$A:$A,'Ownership Metrics'!$C:$C),"") -> 2481 | O67: =IFERROR(_xlfn.XLOOKUP($B67,'Ownership Metrics'!$A:$A,'Ownership Metrics'!$D:$D),"") -> 48.77 | P67: =IFERROR(_xlfn.XLOOKUP($B67,'Ownership Metrics'!$A:$A,'Ownership Metrics'!$E:$E),"") -> 59.74 | Q67: =IFERROR(_xlfn.XLOOKUP($B67,'Ownership Metrics'!$A:$A,'Ownership Metrics'!$F:$F),"") -> 8 | R67: =IFERROR(_xlfn.XLOOKUP($B67,'Ownership Metrics'!$A:$A,'Ownership Metrics'!$G:$G),"") -> 45 | S67: =IFERROR(_xlfn.XLOOKUP($B67,'Ownership Metrics'!$A:$A,'Ownership Metrics'!$H:$H),"") -> Moderat | T67: =IFERROR(_xlfn.XLOOKUP($B67,'Ownership Metrics'!$A:$A,'Ownership Metrics'!$I:$I),"") -> Sedang | U67: =IF(COUNTIFS($B$2:$B67,$B67,$D$2:$D67,$D67)=1,1,0) -> 1 | V67: =SUMIFS($L$2:$L$10000,$B$2:$B$10000,$B67,$D$2:$D$10000,$D67) -> 1.05 | W67: =COUNTIFS($B$2:$B$10000,$B67,$U$2:$U$10000,1,$X$2:$X$10000,">"&$X67)+1 -> 8 | X67: =$V67-(ROW()*0.0000000001) -> 1.05
A68: 46265 | B68: AEGS | C68: ANUGERAH SPAREPARTS SEJAHTERA Tbk | D68: CV. JAMBI TRADE CENTER | E68: Commanditaire Vennootschap (CV) or Limited partnership | F68: L | H68: INDONESIA | I68: 10433000 | J68: 0 | K68: 10433000 | L68: 1.04 | M68: =IFERROR(_xlfn.XLOOKUP($B68,'Ownership Metrics'!$A:$A,'Ownership Metrics'!$B:$B),"") -> 27.54 | N68: =IFERROR(_xlfn.XLOOKUP($B68,'Ownership Metrics'!$A:$A,'Ownership Metrics'!$C:$C),"") -> 3093 | O68: =IFERROR(_xlfn.XLOOKUP($B68,'Ownership Metrics'!$A:$A,'Ownership Metrics'!$D:$D),"") -> 55.23 | P68: =IFERROR(_xlfn.XLOOKUP($B68,'Ownership Metrics'!$A:$A,'Ownership Metrics'!$E:$E),"") -> 62.13 | Q68: =IFERROR(_xlfn.XLOOKUP($B68,'Ownership Metrics'!$A:$A,'Ownership Metrics'!$F:$F),"") -> 10 | R68: =IFERROR(_xlfn.XLOOKUP($B68,'Ownership Metrics'!$A:$A,'Ownership Metrics'!$G:$G),"") -> 46 | S68: =IFERROR(_xlfn.XLOOKUP($B68,'Ownership Metrics'!$A:$A,'Ownership Metrics'!$H:$H),"") -> Mayoritas | T68: =IFERROR(_xlfn.XLOOKUP($B68,'Ownership Metrics'!$A:$A,'Ownership Metrics'!$I:$I),"") -> Sedang | U68: =IF(COUNTIFS($B$2:$B68,$B68,$D$2:$D68,$D68)=1,1,0) -> 1 | V68: =SUMIFS($L$2:$L$10000,$B$2:$B$10000,$B68,$D$2:$D$10000,$D68) -> 1.04 | W68: =COUNTIFS($B$2:$B$10000,$B68,$U$2:$U$10000,1,$X$2:$X$10000,">"&$X68)+1 -> 9 | X68: =$V68-(ROW()*0.0000000001) -> 1.04
A69: 46265 | B69: AEGS | C69: ANUGERAH SPAREPARTS SEJAHTERA Tbk | D69: ANDY TANUJAYA | E69: Individual | F69: L | G69: INDONESIAN | H69: INDONESIA | I69: 12545400 | J69: 0 | K69: 12545400 | L69: 1.25 | M69: =IFERROR(_xlfn.XLOOKUP($B69,'Ownership Metrics'!$A:$A,'Ownership Metrics'!$B:$B),"") -> 27.54 | N69: =IFERROR(_xlfn.XLOOKUP($B69,'Ownership Metrics'!$A:$A,'Ownership Metrics'!$C:$C),"") -> 3093 | O69: =IFERROR(_xlfn.XLOOKUP($B69,'Ownership Metrics'!$A:$A,'Ownership Metrics'!$D:$D),"") -> 55.23 | P69: =IFERROR(_xlfn.XLOOKUP($B69,'Ownership Metrics'!$A:$A,'Ownership Metrics'!$E:$E),"") -> 62.13 | Q69: =IFERROR(_xlfn.XLOOKUP($B69,'Ownership Metrics'!$A:$A,'Ownership Metrics'!$F:$F),"") -> 10 | R69: =IFERROR(_xlfn.XLOOKUP($B69,'Ownership Metrics'!$A:$A,'Ownership Metrics'!$G:$G),"") -> 46 | S69: =IFERROR(_xlfn.XLOOKUP($B69,'Ownership Metrics'!$A:$A,'Ownership Metrics'!$H:$H),"") -> Mayoritas | T69: =IFERROR(_xlfn.XLOOKUP($B69,'Ownership Metrics'!$A:$A,'Ownership Metrics'!$I:$I),"") -> Sedang | U69: =IF(COUNTIFS($B$2:$B69,$B69,$D$2:$D69,$D69)=1,1,0) -> 1 | V69: =SUMIFS($L$2:$L$10000,$B$2:$B$10000,$B69,$D$2:$D$10000,$D69) -> 1.25 | W69: =COUNTIFS($B$2:$B$10000,$B69,$U$2:$U$10000,1,$X$2:$X$10000,">"&$X69)+1 -> 8 | X69: =$V69-(ROW()*0.0000000001) -> 1.25
A70: 46265 | B70: AEGS | C70: ANUGERAH SPAREPARTS SEJAHTERA Tbk | D70: OEY JOHAN SINATRA SUMAWI | E70: Individual | F70: L | G70: INDONESIAN | H70: INDONESIA | I70: 25350010 | J70: 0 | K70: 25350010 | L70: 2.52 | M70: =IFERROR(_xlfn.XLOOKUP($B70,'Ownership Metrics'!$A:$A,'Ownership Metrics'!$B:$B),"") -> 27.54 | N70: =IFERROR(_xlfn.XLOOKUP($B70,'Ownership Metrics'!$A:$A,'Ownership Metrics'!$C:$C),"") -> 3093 | O70: =IFERROR(_xlfn.XLOOKUP($B70,'Ownership Metrics'!$A:$A,'Ownership Metrics'!$D:$D),"") -> 55.23 | P70: =IFERROR(_xlfn.XLOOKUP($B70,'Ownership Metrics'!$A:$A,'Ownership Metrics'!$E:$E),"") -> 62.13 | Q70: =IFERROR(_xlfn.XLOOKUP($B70,'Ownership Metrics'!$A:$A,'Ownership Metrics'!$F:$F),"") -> 10 | R70: =IFERROR(_xlfn.XLOOKUP($B70,'Ownership Metrics'!$A:$A,'Ownership Metrics'!$G:$G),"") -> 46 | S70: =IFERROR(_xlfn.XLOOKUP($B70,'Ownership Metrics'!$A:$A,'Ownership Metrics'!$H:$H),"") -> Mayoritas | T70: =IFERROR(_xlfn.XLOOKUP($B70,'Ownership Metrics'!$A:$A,'Ownership Metrics'!$I:$I),"") -> Sedang | U70: =IF(COUNTIFS($B$2:$B70,$B70,$D$2:$D70,$D70)=1,1,0) -> 1 | V70: =SUMIFS($L$2:$L$10000,$B$2:$B$10000,$B70,$D$2:$D$10000,$D70) -> 2.52 | W70: =COUNTIFS($B$2:$B$10000,$B70,$U$2:$U$10000,1,$X$2:$X$10000,">"&$X70)+1 -> 3 | X70: =$V70-(ROW()*0.0000000001) -> 2.52
A71: 46265 | B71: AEGS | C71: ANUGERAH SPAREPARTS SEJAHTERA Tbk | D71: KUSWIRA | E71: Individual | F71: L | G71: INDONESIAN | H71: INDONESIA | I71: 10232600 | J71: 0 | K71: 10232600 | L71: 1.02 | M71: =IFERROR(_xlfn.XLOOKUP($B71,'Ownership Metrics'!$A:$A,'Ownership Metrics'!$B:$B),"") -> 27.54 | N71: =IFERROR(_xlfn.XLOOKUP($B71,'Ownership Metrics'!$A:$A,'Ownership Metrics'!$C:$C),"") -> 3093 | O71: =IFERROR(_xlfn.XLOOKUP($B71,'Ownership Metrics'!$A:$A,'Ownership Metrics'!$D:$D),"") -> 55.23 | P71: =IFERROR(_xlfn.XLOOKUP($B71,'Ownership Metrics'!$A:$A,'Ownership Metrics'!$E:$E),"") -> 62.13 | Q71: =IFERROR(_xlfn.XLOOKUP($B71,'Ownership Metrics'!$A:$A,'Ownership Metrics'!$F:$F),"") -> 10 | R71: =IFERROR(_xlfn.XLOOKUP($B71,'Ownership Metrics'!$A:$A,'Ownership Metrics'!$G:$G),"") -> 46 | S71: =IFERROR(_xlfn.XLOOKUP($B71,'Ownership Metrics'!$A:$A,'Ownership Metrics'!$H:$H),"") -> Mayoritas | T71: =IFERROR(_xlfn.XLOOKUP($B71,'Ownership Metrics'!$A:$A,'Ownership Metrics'!$I:$I),"") -> Sedang | U71: =IF(COUNTIFS($B$2:$B71,$B71,$D$2:$D71,$D71)=1,1,0) -> 1 | V71: =SUMIFS($L$2:$L$10000,$B$2:$B$10000,$B71,$D$2:$D$10000,$D71) -> 1.02 | W71: =COUNTIFS($B$2:$B$10000,$B71,$U$2:$U$10000,1,$X$2:$X$10000,">"&$X71)+1 -> 10 | X71: =$V71-(ROW()*0.0000000001) -> 1.02
A72: 46265 | B72: AEGS | C72: ANUGERAH SPAREPARTS SEJAHTERA Tbk | D72: J SUWANTA SINARYA DR | E72: Individual | F72: L | G72: INDONESIAN | H72: INDONESIA | I72: 555649980 | J72: 0 | K72: 555649980 | L72: 55.23 | M72: =IFERROR(_xlfn.XLOOKUP($B72,'Ownership Metrics'!$A:$A,'Ownership Metrics'!$B:$B),"") -> 27.54 | N72: =IFERROR(_xlfn.XLOOKUP($B72,'Ownership Metrics'!$A:$A,'Ownership Metrics'!$C:$C),"") -> 3093 | O72: =IFERROR(_xlfn.XLOOKUP($B72,'Ownership Metrics'!$A:$A,'Ownership Metrics'!$D:$D),"") -> 55.23 | P72: =IFERROR(_xlfn.XLOOKUP($B72,'Ownership Metrics'!$A:$A,'Ownership Metrics'!$E:$E),"") -> 62.13 | Q72: =IFERROR(_xlfn.XLOOKUP($B72,'Ownership Metrics'!$A:$A,'Ownership Metrics'!$F:$F),"") -> 10 | R72: =IFERROR(_xlfn.XLOOKUP($B72,'Ownership Metrics'!$A:$A,'Ownership Metrics'!$G:$G),"") -> 46 | S72: =IFERROR(_xlfn.XLOOKUP($B72,'Ownership Metrics'!$A:$A,'Ownership Metrics'!$H:$H),"") -> Mayoritas | T72: =IFERROR(_xlfn.XLOOKUP($B72,'Ownership Metrics'!$A:$A,'Ownership Metrics'!$I:$I),"") -> Sedang | U72: =IF(COUNTIFS($B$2:$B72,$B72,$D$2:$D72,$D72)=1,1,0) -> 1 | V72: =SUMIFS($L$2:$L$10000,$B$2:$B$10000,$B72,$D$2:$D$10000,$D72) -> 55.23 | W72: =COUNTIFS($B$2:$B$10000,$B72,$U$2:$U$10000,1,$X$2:$X$10000,">"&$X72)+1 -> 1 | X72: =$V72-(ROW()*0.0000000001) -> 55.23
A73: 46265 | B73: AEGS | C73: ANUGERAH SPAREPARTS SEJAHTERA Tbk | D73: ANI ROLIYANI | E73: Individual | F73: L | G73: INDONESIAN | H73: INDONESIA | I73: 15130000 | J73: 0 | K73: 15130000 | L73: 1.5 | M73: =IFERROR(_xlfn.XLOOKUP($B73,'Ownership Metrics'!$A:$A,'Ownership Metrics'!$B:$B),"") -> 27.54 | N73: =IFERROR(_xlfn.XLOOKUP($B73,'Ownership Metrics'!$A:$A,'Ownership Metrics'!$C:$C),"") -> 3093 | O73: =IFERROR(_xlfn.XLOOKUP($B73,'Ownership Metrics'!$A:$A,'Ownership Metrics'!$D:$D),"") -> 55.23 | P73: =IFERROR(_xlfn.XLOOKUP($B73,'Ownership Metrics'!$A:$A,'Ownership Metrics'!$E:$E),"") -> 62.13 | Q73: =IFERROR(_xlfn.XLOOKUP($B73,'Ownership Metrics'!$A:$A,'Ownership Metrics'!$F:$F),"") -> 10 | R73: =IFERROR(_xlfn.XLOOKUP($B73,'Ownership Metrics'!$A:$A,'Ownership Metrics'!$G:$G),"") -> 46 | S73: =IFERROR(_xlfn.XLOOKUP($B73,'Ownership Metrics'!$A:$A,'Ownership Metrics'!$H:$H),"") -> Mayoritas | T73: =IFERROR(_xlfn.XLOOKUP($B73,'Ownership Metrics'!$A:$A,'Ownership Metrics'!$I:$I),"") -> Sedang | U73: =IF(COUNTIFS($B$2:$B73,$B73,$D$2:$D73,$D73)=1,1,0) -> 1 | V73: =SUMIFS($L$2:$L$10000,$B$2:$B$10000,$B73,$D$2:$D$10000,$D73) -> 1.5 | W73: =COUNTIFS($B$2:$B$10000,$B73,$U$2:$U$10000,1,$X$2:$X$10000,">"&$X73)+1 -> 6 | X73: =$V73-(ROW()*0.0000000001) -> 1.5
A74: 46265 | B74: AEGS | C74: ANUGERAH SPAREPARTS SEJAHTERA Tbk | D74: HASANUDIN | E74: Individual | F74: L | G74: INDONESIAN | H74: INDONESIA | I74: 15926800 | J74: 0 | K74: 15926800 | L74: 1.58 | M74: =IFERROR(_xlfn.XLOOKUP($B74,'Ownership Metrics'!$A:$A,'Ownership Metrics'!$B:$B),"") -> 27.54 | N74: =IFERROR(_xlfn.XLOOKUP($B74,'Ownership Metrics'!$A:$A,'Ownership Metrics'!$C:$C),"") -> 3093 | O74: =IFERROR(_xlfn.XLOOKUP($B74,'Ownership Metrics'!$A:$A,'Ownership Metrics'!$D:$D),"") -> 55.23 | P74: =IFERROR(_xlfn.XLOOKUP($B74,'Ownership Metrics'!$A:$A,'Ownership Metrics'!$E:$E),"") -> 62.13 | Q74: =IFERROR(_xlfn.XLOOKUP($B74,'Ownership Metrics'!$A:$A,'Ownership Metrics'!$F:$F),"") -> 10 | R74: =IFERROR(_xlfn.XLOOKUP($B74,'Ownership Metrics'!$A:$A,'Ownership Metrics'!$G:$G),"") -> 46 | S74: =IFERROR(_xlfn.XLOOKUP($B74,'Ownership Metrics'!$A:$A,'Ownership Metrics'!$H:$H),"") -> Mayoritas | T74: =IFERROR(_xlfn.XLOOKUP($B74,'Ownership Metrics'!$A:$A,'Ownership Metrics'!$I:$I),"") -> Sedang | U74: =IF(COUNTIFS($B$2:$B74,$B74,$D$2:$D74,$D74)=1,1,0) -> 1 | V74: =SUMIFS($L$2:$L$10000,$B$2:$B$10000,$B74,$D$2:$D$10000,$D74) -> 1.58 | W74: =COUNTIFS($B$2:$B$10000,$B74,$U$2:$U$10000,1,$X$2:$X$10000,">"&$X74)+1 -> 5 | X74: =$V74-(ROW()*0.0000000001) -> 1.58
A75: 46265 | B75: AEGS | C75: ANUGERAH SPAREPARTS SEJAHTERA Tbk | D75: JEIHAN SUMAWI PUTRA | E75: Individual | F75: L | G75: INDONESIAN | H75: INDONESIA | I75: 25000010 | J75: 0 | K75: 25000010 | L75: 2.48 | M75: =IFERROR(_xlfn.XLOOKUP($B75,'Ownership Metrics'!$A:$A,'Ownership Metrics'!$B:$B),"") -> 27.54 | N75: =IFERROR(_xlfn.XLOOKUP($B75,'Ownership Metrics'!$A:$A,'Ownership Metrics'!$C:$C),"") -> 3093 | O75: =IFERROR(_xlfn.XLOOKUP($B75,'Ownership Metrics'!$A:$A,'Ownership Metrics'!$D:$D),"") -> 55.23 | P75: =IFERROR(_xlfn.XLOOKUP($B75,'Ownership Metrics'!$A:$A,'Ownership Metrics'!$E:$E),"") -> 62.13 | Q75: =IFERROR(_xlfn.XLOOKUP($B75,'Ownership Metrics'!$A:$A,'Ownership Metrics'!$F:$F),"") -> 10 | R75: =IFERROR(_xlfn.XLOOKUP($B75,'Ownership Metrics'!$A:$A,'Ownership Metrics'!$G:$G),"") -> 46 | S75: =IFERROR(_xlfn.XLOOKUP($B75,'Ownership Metrics'!$A:$A,'Ownership Metrics'!$H:$H),"") -> Mayoritas | T75: =IFERROR(_xlfn.XLOOKUP($B75,'Ownership Metrics'!$A:$A,'Ownership Metrics'!$I:$I),"") -> Sedang | U75: =IF(COUNTIFS($B$2:$B75,$B75,$D$2:$D75,$D75)=1,1,0) -> 1 | V75: =SUMIFS($L$2:$L$10000,$B$2:$B$10000,$B75,$D$2:$D$10000,$D75) -> 2.48 | W75: =COUNTIFS($B$2:$B$10000,$B75,$U$2:$U$10000,1,$X$2:$X$10000,">"&$X75)+1 -> 4 | X75: =$V75-(ROW()*0.0000000001) -> 2.48
A76: 46265 | B76: AEGS | C76: ANUGERAH SPAREPARTS SEJAHTERA Tbk | D76: UOB KAY HIAN PTE LTD | E76: Securities Company | F76: F | H76: SINGAPORE | I76: 44095700 | J76: 0 | K76: 44095700 | L76: 4.38 | M76: =IFERROR(_xlfn.XLOOKUP($B76,'Ownership Metrics'!$A:$A,'Ownership Metrics'!$B:$B),"") -> 27.54 | N76: =IFERROR(_xlfn.XLOOKUP($B76,'Ownership Metrics'!$A:$A,'Ownership Metrics'!$C:$C),"") -> 3093 | O76: =IFERROR(_xlfn.XLOOKUP($B76,'Ownership Metrics'!$A:$A,'Ownership Metrics'!$D:$D),"") -> 55.23 | P76: =IFERROR(_xlfn.XLOOKUP($B76,'Ownership Metrics'!$A:$A,'Ownership Metrics'!$E:$E),"") -> 62.13 | Q76: =IFERROR(_xlfn.XLOOKUP($B76,'Ownership Metrics'!$A:$A,'Ownership Metrics'!$F:$F),"") -> 10 | R76: =IFERROR(_xlfn.XLOOKUP($B76,'Ownership Metrics'!$A:$A,'Ownership Metrics'!$G:$G),"") -> 46 | S76: =IFERROR(_xlfn.XLOOKUP($B76,'Ownership Metrics'!$A:$A,'Ownership Metrics'!$H:$H),"") -> Mayoritas | T76: =IFERROR(_xlfn.XLOOKUP($B76,'Ownership Metrics'!$A:$A,'Ownership Metrics'!$I:$I),"") -> Sedang | U76: =IF(COUNTIFS($B$2:$B76,$B76,$D$2:$D76,$D76)=1,1,0) -> 1 | V76: =SUMIFS($L$2:$L$10000,$B$2:$B$10000,$B76,$D$2:$D$10000,$D76) -> 4.38 | W76: =COUNTIFS($B$2:$B$10000,$B76,$U$2:$U$10000,1,$X$2:$X$10000,">"&$X76)+1 -> 2 | X76: =$V76-(ROW()*0.0000000001) -> 4.38
A77: 46265 | B77: AEGS | C77: ANUGERAH SPAREPARTS SEJAHTERA Tbk | D77: PHILLIP SECURITIES PTE LTD | E77: Investment Manager | F77: F | H77: SINGAPORE | I77: 14704300 | J77: 0 | K77: 14704300 | L77: 1.46 | M77: =IFERROR(_xlfn.XLOOKUP($B77,'Ownership Metrics'!$A:$A,'Ownership Metrics'!$B:$B),"") -> 27.54 | N77: =IFERROR(_xlfn.XLOOKUP($B77,'Ownership Metrics'!$A:$A,'Ownership Metrics'!$C:$C),"") -> 3093 | O77: =IFERROR(_xlfn.XLOOKUP($B77,'Ownership Metrics'!$A:$A,'Ownership Metrics'!$D:$D),"") -> 55.23 | P77: =IFERROR(_xlfn.XLOOKUP($B77,'Ownership Metrics'!$A:$A,'Ownership Metrics'!$E:$E),"") -> 62.13 | Q77: =IFERROR(_xlfn.XLOOKUP($B77,'Ownership Metrics'!$A:$A,'Ownership Metrics'!$F:$F),"") -> 10 | R77: =IFERROR(_xlfn.XLOOKUP($B77,'Ownership Metrics'!$A:$A,'Ownership Metrics'!$G:$G),"") -> 46 | S77: =IFERROR(_xlfn.XLOOKUP($B77,'Ownership Metrics'!$A:$A,'Ownership Metrics'!$H:$H),"") -> Mayoritas | T77: =IFERROR(_xlfn.XLOOKUP($B77,'Ownership Metrics'!$A:$A,'Ownership Metrics'!$I:$I),"") -> Sedang | U77: =IF(COUNTIFS($B$2:$B77,$B77,$D$2:$D77,$D77)=1,1,0) -> 1 | V77: =SUMIFS($L$2:$L$10000,$B$2:$B$10000,$B77,$D$2:$D$10000,$D77) -> 1.46 | W77: =COUNTIFS($B$2:$B$10000,$B77,$U$2:$U$10000,1,$X$2:$X$10000,">"&$X77)+1 -> 7 | X77: =$V77-(ROW()*0.0000000001) -> 1.46
A78: 46265 | B78: AGAR | C78: ASIA SEJAHTERA MINA Tbk | D78: PT. BENGAWAN TIMUR LAJU | E78: Corporate | F78: L | H78: INDONESIA | I78: 43000000 | J78: 0 | K78: 43000000 | L78: 4.3 | M78: =IFERROR(_xlfn.XLOOKUP($B78,'Ownership Metrics'!$A:$A,'Ownership Metrics'!$B:$B),"") -> 1.28 | N78: =IFERROR(_xlfn.XLOOKUP($B78,'Ownership Metrics'!$A:$A,'Ownership Metrics'!$C:$C),"") -> 3019 | O78: =IFERROR(_xlfn.XLOOKUP($B78,'Ownership Metrics'!$A:$A,'Ownership Metrics'!$D:$D),"") -> 45 | P78: =IFERROR(_xlfn.XLOOKUP($B78,'Ownership Metrics'!$A:$A,'Ownership Metrics'!$E:$E),"") -> 79.29 | Q78: =IFERROR(_xlfn.XLOOKUP($B78,'Ownership Metrics'!$A:$A,'Ownership Metrics'!$F:$F),"") -> 8 | R78: =IFERROR(_xlfn.XLOOKUP($B78,'Ownership Metrics'!$A:$A,'Ownership Metrics'!$G:$G),"") -> 54 | S78: =IFERROR(_xlfn.XLOOKUP($B78,'Ownership Metrics'!$A:$A,'Ownership Metrics'!$H:$H),"") -> Terkonsentrasi | T78: =IFERROR(_xlfn.XLOOKUP($B78,'Ownership Metrics'!$A:$A,'Ownership Metrics'!$I:$I),"") -> Sedang | U78: =IF(COUNTIFS($B$2:$B78,$B78,$D$2:$D78,$D78)=1,1,0) -> 1 | V78: =SUMIFS($L$2:$L$10000,$B$2:$B$10000,$B78,$D$2:$D$10000,$D78) -> 4.3 | W78: =COUNTIFS($B$2:$B$10000,$B78,$U$2:$U$10000,1,$X$2:$X$10000,">"&$X78)+1 -> 3 | X78: =$V78-(ROW()*0.0000000001) -> 4.3
A79: 46265 | B79: AGAR | C79: ASIA SEJAHTERA MINA Tbk | D79: PT. SINAR TERANG ASIA RAYA | E79: Corporate | F79: L | H79: INDONESIA | I79: 299927300 | J79: 0 | K79: 299927300 | L79: 29.99 | M79: =IFERROR(_xlfn.XLOOKUP($B79,'Ownership Metrics'!$A:$A,'Ownership Metrics'!$B:$B),"") -> 1.28 | N79: =IFERROR(_xlfn.XLOOKUP($B79,'Ownership Metrics'!$A:$A,'Ownership Metrics'!$C:$C),"") -> 3019 | O79: =IFERROR(_xlfn.XLOOKUP($B79,'Ownership Metrics'!$A:$A,'Ownership Metrics'!$D:$D),"") -> 45 | P79: =IFERROR(_xlfn.XLOOKUP($B79,'Ownership Metrics'!$A:$A,'Ownership Metrics'!$E:$E),"") -> 79.29 | Q79: =IFERROR(_xlfn.XLOOKUP($B79,'Ownership Metrics'!$A:$A,'Ownership Metrics'!$F:$F),"") -> 8 | R79: =IFERROR(_xlfn.XLOOKUP($B79,'Ownership Metrics'!$A:$A,'Ownership Metrics'!$G:$G),"") -> 54 | S79: =IFERROR(_xlfn.XLOOKUP($B79,'Ownership Metrics'!$A:$A,'Ownership Metrics'!$H:$H),"") -> Terkonsentrasi | T79: =IFERROR(_xlfn.XLOOKUP($B79,'Ownership Metrics'!$A:$A,'Ownership Metrics'!$I:$I),"") -> Sedang | U79: =IF(COUNTIFS($B$2:$B79,$B79,$D$2:$D79,$D79)=1,1,0) -> 1 | V79: =SUMIFS($L$2:$L$10000,$B$2:$B$10000,$B79,$D$2:$D$10000,$D79) -> 29.99 | W79: =COUNTIFS($B$2:$B$10000,$B79,$U$2:$U$10000,1,$X$2:$X$10000,">"&$X79)+1 -> 2 | X79: =$V79-(ROW()*0.0000000001) -> 29.99
A80: 46265 | B80: AGAR | C80: ASIA SEJAHTERA MINA Tbk | D80: PT. INDO KREASI PRATAMA | E80: Corporate | F80: L | H80: INDONESIA | I80: 450000000 | J80: 0 | K80: 450000000 | L80: 45 | M80: =IFERROR(_xlfn.XLOOKUP($B80,'Ownership Metrics'!$A:$A,'Ownership Metrics'!$B:$B),"") -> 1.28 | N80: =IFERROR(_xlfn.XLOOKUP($B80,'Ownership Metrics'!$A:$A,'Ownership Metrics'!$C:$C),"") -> 3019 | O80: =IFERROR(_xlfn.XLOOKUP($B80,'Ownership Metrics'!$A:$A,'Ownership Metrics'!$D:$D),"") -> 45 | P80: =IFERROR(_xlfn.XLOOKUP($B80,'Ownership Metrics'!$A:$A,'Ownership Metrics'!$E:$E),"") -> 79.29 | Q80: =IFERROR(_xlfn.XLOOKUP($B80,'Ownership Metrics'!$A:$A,'Ownership Metrics'!$F:$F),"") -> 8 | R80: =IFERROR(_xlfn.XLOOKUP($B80,'Ownership Metrics'!$A:$A,'Ownership Metrics'!$G:$G),"") -> 54 | S80: =IFERROR(_xlfn.XLOOKUP($B80,'Ownership Metrics'!$A:$A,'Ownership Metrics'!$H:$H),"") -> Terkonsentrasi | T80: =IFERROR(_xlfn.XLOOKUP($B80,'Ownership Metrics'!$A:$A,'Ownership Metrics'!$I:$I),"") -> Sedang | U80: =IF(COUNTIFS($B$2:$B80,$B80,$D$2:$D80,$D80)=1,1,0) -> 1 | V80: =SUMIFS($L$2:$L$10000,$B$2:$B$10000,$B80,$D$2:$D$10000,$D80) -> 45 | W80: =COUNTIFS($B$2:$B$10000,$B80,$U$2:$U$10000,1,$X$2:$X$10000,">"&$X80)+1 -> 1 | X80: =$V80-(ROW()*0.0000000001) -> 45
A81: 46265 | B81: AGAR | C81: ASIA SEJAHTERA MINA Tbk | D81: HENRY TIRTASAPUTRA JUNIOR | E81: Individual | F81: L | G81: INDONESIAN | H81: INDONESIA | I81: 40000000 | J81: 0 | K81: 40000000 | L81: 4 | M81: =IFERROR(_xlfn.XLOOKUP($B81,'Ownership Metrics'!$A:$A,'Ownership Metrics'!$B:$B),"") -> 1.28 | N81: =IFERROR(_xlfn.XLOOKUP($B81,'Ownership Metrics'!$A:$A,'Ownership Metrics'!$C:$C),"") -> 3019 | O81: =IFERROR(_xlfn.XLOOKUP($B81,'Ownership Metrics'!$A:$A,'Ownership Metrics'!$D:$D),"") -> 45 | P81: =IFERROR(_xlfn.XLOOKUP($B81,'Ownership Metrics'!$A:$A,'Ownership Metrics'!$E:$E),"") -> 79.29 | Q81: =IFERROR(_xlfn.XLOOKUP($B81,'Ownership Metrics'!$A:$A,'Ownership Metrics'!$F:$F),"") -> 8 | R81: =IFERROR(_xlfn.XLOOKUP($B81,'Ownership Metrics'!$A:$A,'Ownership Metrics'!$G:$G),"") -> 54 | S81: =IFERROR(_xlfn.XLOOKUP($B81,'Ownership Metrics'!$A:$A,'Ownership Metrics'!$H:$H),"") -> Terkonsentrasi | T81: =IFERROR(_xlfn.XLOOKUP($B81,'Ownership Metrics'!$A:$A,'Ownership Metrics'!$I:$I),"") -> Sedang | U81: =IF(COUNTIFS($B$2:$B81,$B81,$D$2:$D81,$D81)=1,1,0) -> 1 | V81: =SUMIFS($L$2:$L$10000,$B$2:$B$10000,$B81,$D$2:$D$10000,$D81) -> 4 | W81: =COUNTIFS($B$2:$B$10000,$B81,$U$2:$U$10000,1,$X$2:$X$10000,">"&$X81)+1 -> 6 | X81: =$V81-(ROW()*0.0000000001) -> 4
A82: 46265 | B82: AGAR | C82: ASIA SEJAHTERA MINA Tbk | D82: L. HAUW LIONG (LIANTO G) | E82: Individual | F82: L | G82: INDONESIAN | H82: INDONESIA | I82: 40392900 | J82: 0 | K82: 40392900 | L82: 4.04 | M82: =IFERROR(_xlfn.XLOOKUP($B82,'Ownership Metrics'!$A:$A,'Ownership Metrics'!$B:$B),"") -> 1.28 | N82: =IFERROR(_xlfn.XLOOKUP($B82,'Ownership Metrics'!$A:$A,'Ownership Metrics'!$C:$C),"") -> 3019 | O82: =IFERROR(_xlfn.XLOOKUP($B82,'Ownership Metrics'!$A:$A,'Ownership Metrics'!$D:$D),"") -> 45 | P82: =IFERROR(_xlfn.XLOOKUP($B82,'Ownership Metrics'!$A:$A,'Ownership Metrics'!$E:$E),"") -> 79.29 | Q82: =IFERROR(_xlfn.XLOOKUP($B82,'Ownership Metrics'!$A:$A,'Ownership Metrics'!$F:$F),"") -> 8 | R82: =IFERROR(_xlfn.XLOOKUP($B82,'Ownership Metrics'!$A:$A,'Ownership Metrics'!$G:$G),"") -> 54 | S82: =IFERROR(_xlfn.XLOOKUP($B82,'Ownership Metrics'!$A:$A,'Ownership Metrics'!$H:$H),"") -> Terkonsentrasi | T82: =IFERROR(_xlfn.XLOOKUP($B82,'Ownership Metrics'!$A:$A,'Ownership Metrics'!$I:$I),"") -> Sedang | U82: =IF(COUNTIFS($B$2:$B82,$B82,$D$2:$D82,$D82)=1,1,0) -> 1 | V82: =SUMIFS($L$2:$L$10000,$B$2:$B$10000,$B82,$D$2:$D$10000,$D82) -> 4.04 | W82: =COUNTIFS($B$2:$B$10000,$B82,$U$2:$U$10000,1,$X$2:$X$10000,">"&$X82)+1 -> 5 | X82: =$V82-(ROW()*0.0000000001) -> 4.04
A83: 46265 | B83: AGAR | C83: ASIA SEJAHTERA MINA Tbk | D83: ROBIN GOENADI | E83: Individual | F83: L | G83: INDONESIAN | H83: INDONESIA | I83: 39777500 | J83: 0 | K83: 39777500 | L83: 3.98 | M83: =IFERROR(_xlfn.XLOOKUP($B83,'Ownership Metrics'!$A:$A,'Ownership Metrics'!$B:$B),"") -> 1.28 | N83: =IFERROR(_xlfn.XLOOKUP($B83,'Ownership Metrics'!$A:$A,'Ownership Metrics'!$C:$C),"") -> 3019 | O83: =IFERROR(_xlfn.XLOOKUP($B83,'Ownership Metrics'!$A:$A,'Ownership Metrics'!$D:$D),"") -> 45 | P83: =IFERROR(_xlfn.XLOOKUP($B83,'Ownership Metrics'!$A:$A,'Ownership Metrics'!$E:$E),"") -> 79.29 | Q83: =IFERROR(_xlfn.XLOOKUP($B83,'Ownership Metrics'!$A:$A,'Ownership Metrics'!$F:$F),"") -> 8 | R83: =IFERROR(_xlfn.XLOOKUP($B83,'Ownership Metrics'!$A:$A,'Ownership Metrics'!$G:$G),"") -> 54 | S83: =IFERROR(_xlfn.XLOOKUP($B83,'Ownership Metrics'!$A:$A,'Ownership Metrics'!$H:$H),"") -> Terkonsentrasi | T83: =IFERROR(_xlfn.XLOOKUP($B83,'Ownership Metrics'!$A:$A,'Ownership Metrics'!$I:$I),"") -> Sedang | U83: =IF(COUNTIFS($B$2:$B83,$B83,$D$2:$D83,$D83)=1,1,0) -> 1 | V83: =SUMIFS($L$2:$L$10000,$B$2:$B$10000,$B83,$D$2:$D$10000,$D83) -> 3.98 | W83: =COUNTIFS($B$2:$B$10000,$B83,$U$2:$U$10000,1,$X$2:$X$10000,">"&$X83)+1 -> 7 | X83: =$V83-(ROW()*0.0000000001) -> 3.98
A84: 46265 | B84: AGAR | C84: ASIA SEJAHTERA MINA Tbk | D84: INTAN POLANARIA SANTOSA | E84: Individual | F84: L | G84: INDONESIAN | H84: INDONESIA | I84: 33113600 | J84: 0 | K84: 33113600 | L84: 3.31 | M84: =IFERROR(_xlfn.XLOOKUP($B84,'Ownership Metrics'!$A:$A,'Ownership Metrics'!$B:$B),"") -> 1.28 | N84: =IFERROR(_xlfn.XLOOKUP($B84,'Ownership Metrics'!$A:$A,'Ownership Metrics'!$C:$C),"") -> 3019 | O84: =IFERROR(_xlfn.XLOOKUP($B84,'Ownership Metrics'!$A:$A,'Ownership Metrics'!$D:$D),"") -> 45 | P84: =IFERROR(_xlfn.XLOOKUP($B84,'Ownership Metrics'!$A:$A,'Ownership Metrics'!$E:$E),"") -> 79.29 | Q84: =IFERROR(_xlfn.XLOOKUP($B84,'Ownership Metrics'!$A:$A,'Ownership Metrics'!$F:$F),"") -> 8 | R84: =IFERROR(_xlfn.XLOOKUP($B84,'Ownership Metrics'!$A:$A,'Ownership Metrics'!$G:$G),"") -> 54 | S84: =IFERROR(_xlfn.XLOOKUP($B84,'Ownership Metrics'!$A:$A,'Ownership Metrics'!$H:$H),"") -> Terkonsentrasi | T84: =IFERROR(_xlfn.XLOOKUP($B84,'Ownership Metrics'!$A:$A,'Ownership Metrics'!$I:$I),"") -> Sedang | U84: =IF(COUNTIFS($B$2:$B84,$B84,$D$2:$D84,$D84)=1,1,0) -> 1 | V84: =SUMIFS($L$2:$L$10000,$B$2:$B$10000,$B84,$D$2:$D$10000,$D84) -> 3.31 | W84: =COUNTIFS($B$2:$B$10000,$B84,$U$2:$U$10000,1,$X$2:$X$10000,">"&$X84)+1 -> 8 | X84: =$V84-(ROW()*0.0000000001) -> 3.31
A85: 46265 | B85: AGAR | C85: ASIA SEJAHTERA MINA Tbk | D85: WILDA TETY ARYDESIA | E85: Individual | F85: L | G85: INDONESIAN | H85: INDONESIA | I85: 41000000 | J85: 0 | K85: 41000000 | L85: 4.1 | M85: =IFERROR(_xlfn.XLOOKUP($B85,'Ownership Metrics'!$A:$A,'Ownership Metrics'!$B:$B),"") -> 1.28 | N85: =IFERROR(_xlfn.XLOOKUP($B85,'Ownership Metrics'!$A:$A,'Ownership Metrics'!$C:$C),"") -> 3019 | O85: =IFERROR(_xlfn.XLOOKUP($B85,'Ownership Metrics'!$A:$A,'Ownership Metrics'!$D:$D),"") -> 45 | P85: =IFERROR(_xlfn.XLOOKUP($B85,'Ownership Metrics'!$A:$A,'Ownership Metrics'!$E:$E),"") -> 79.29 | Q85: =IFERROR(_xlfn.XLOOKUP($B85,'Ownership Metrics'!$A:$A,'Ownership Metrics'!$F:$F),"") -> 8 | R85: =IFERROR(_xlfn.XLOOKUP($B85,'Ownership Metrics'!$A:$A,'Ownership Metrics'!$G:$G),"") -> 54 | S85: =IFERROR(_xlfn.XLOOKUP($B85,'Ownership Metrics'!$A:$A,'Ownership Metrics'!$H:$H),"") -> Terkonsentrasi | T85: =IFERROR(_xlfn.XLOOKUP($B85,'Ownership Metrics'!$A:$A,'Ownership Metrics'!$I:$I),"") -> Sedang | U85: =IF(COUNTIFS($B$2:$B85,$B85,$D$2:$D85,$D85)=1,1,0) -> 1 | V85: =SUMIFS($L$2:$L$10000,$B$2:$B$10000,$B85,$D$2:$D$10000,$D85) -> 4.1 | W85: =COUNTIFS($B$2:$B$10000,$B85,$U$2:$U$10000,1,$X$2:$X$10000,">"&$X85)+1 -> 4 | X85: =$V85-(ROW()*0.0000000001) -> 4.1
A86: 46265 | B86: AGII | C86: SAMATOR INDO GAS Tbk | D86: PT. ANEKA MEGA ENERGI | E86: Corporate | F86: L | H86: INDONESIA | I86: 459999000 | J86: 0 | K86: 459999000 | L86: 15 | M86: =IFERROR(_xlfn.XLOOKUP($B86,'Ownership Metrics'!$A:$A,'Ownership Metrics'!$B:$B),"") -> 4.59 | N86: =IFERROR(_xlfn.XLOOKUP($B86,'Ownership Metrics'!$A:$A,'Ownership Metrics'!$C:$C),"") -> 2611 | O86: =IFERROR(_xlfn.XLOOKUP($B86,'Ownership Metrics'!$A:$A,'Ownership Metrics'!$D:$D),"") -> 35.24 | P86: =IFERROR(_xlfn.XLOOKUP($B86,'Ownership Metrics'!$A:$A,'Ownership Metrics'!$E:$E),"") -> 82.42 | Q86: =IFERROR(_xlfn.XLOOKUP($B86,'Ownership Metrics'!$A:$A,'Ownership Metrics'!$F:$F),"") -> 5 | R86: =IFERROR(_xlfn.XLOOKUP($B86,'Ownership Metrics'!$A:$A,'Ownership Metrics'!$G:$G),"") -> 56 | S86: =IFERROR(_xlfn.XLOOKUP($B86,'Ownership Metrics'!$A:$A,'Ownership Metrics'!$H:$H),"") -> Terkonsentrasi | T86: =IFERROR(_xlfn.XLOOKUP($B86,'Ownership Metrics'!$A:$A,'Ownership Metrics'!$I:$I),"") -> Tinggi | U86: =IF(COUNTIFS($B$2:$B86,$B86,$D$2:$D86,$D86)=1,1,0) -> 1 | V86: =SUMIFS($L$2:$L$10000,$B$2:$B$10000,$B86,$D$2:$D$10000,$D86) -> 15 | W86: =COUNTIFS($B$2:$B$10000,$B86,$U$2:$U$10000,1,$X$2:$X$10000,">"&$X86)+1 -> 3 | X86: =$V86-(ROW()*0.0000000001) -> 15
A87: 46265 | B87: AGII | C87: SAMATOR INDO GAS Tbk | D87: SARATOGA INVESTAMA SEDAYA TBK | E87: Private Bank | F87: L | H87: INDONESIA | I87: 306666000 | J87: 0 | K87: 306666000 | L87: 10 | M87: =IFERROR(_xlfn.XLOOKUP($B87,'Ownership Metrics'!$A:$A,'Ownership Metrics'!$B:$B),"") -> 4.59 | N87: =IFERROR(_xlfn.XLOOKUP($B87,'Ownership Metrics'!$A:$A,'Ownership Metrics'!$C:$C),"") -> 2611 | O87: =IFERROR(_xlfn.XLOOKUP($B87,'Ownership Metrics'!$A:$A,'Ownership Metrics'!$D:$D),"") -> 35.24 | P87: =IFERROR(_xlfn.XLOOKUP($B87,'Ownership Metrics'!$A:$A,'Ownership Metrics'!$E:$E),"") -> 82.42 | Q87: =IFERROR(_xlfn.XLOOKUP($B87,'Ownership Metrics'!$A:$A,'Ownership Metrics'!$F:$F),"") -> 5 | R87: =IFERROR(_xlfn.XLOOKUP($B87,'Ownership Metrics'!$A:$A,'Ownership Metrics'!$G:$G),"") -> 56 | S87: =IFERROR(_xlfn.XLOOKUP($B87,'Ownership Metrics'!$A:$A,'Ownership Metrics'!$H:$H),"") -> Terkonsentrasi | T87: =IFERROR(_xlfn.XLOOKUP($B87,'Ownership Metrics'!$A:$A,'Ownership Metrics'!$I:$I),"") -> Tinggi | U87: =IF(COUNTIFS($B$2:$B87,$B87,$D$2:$D87,$D87)=1,1,0) -> 1 | V87: =SUMIFS($L$2:$L$10000,$B$2:$B$10000,$B87,$D$2:$D$10000,$D87) -> 10 | W87: =COUNTIFS($B$2:$B$10000,$B87,$U$2:$U$10000,1,$X$2:$X$10000,">"&$X87)+1 -> 4 | X87: =$V87-(ROW()*0.0000000001) -> 10
A88: 46265 | B88: AGII | C88: SAMATOR INDO GAS Tbk | D88: PT SAMATOR | E88: Corporate | F88: L | H88: INDONESIA | I88: 709549020 | J88: 371144000 | K88: 1080693020 | L88: 35.24 | M88: =IFERROR(_xlfn.XLOOKUP($B88,'Ownership Metrics'!$A:$A,'Ownership Metrics'!$B:$B),"") -> 4.59 | N88: =IFERROR(_xlfn.XLOOKUP($B88,'Ownership Metrics'!$A:$A,'Ownership Metrics'!$C:$C),"") -> 2611 | O88: =IFERROR(_xlfn.XLOOKUP($B88,'Ownership Metrics'!$A:$A,'Ownership Metrics'!$D:$D),"") -> 35.24 | P88: =IFERROR(_xlfn.XLOOKUP($B88,'Ownership Metrics'!$A:$A,'Ownership Metrics'!$E:$E),"") -> 82.42 | Q88: =IFERROR(_xlfn.XLOOKUP($B88,'Ownership Metrics'!$A:$A,'Ownership Metrics'!$F:$F),"") -> 5 | R88: =IFERROR(_xlfn.XLOOKUP($B88,'Ownership Metrics'!$A:$A,'Ownership Metrics'!$G:$G),"") -> 56 | S88: =IFERROR(_xlfn.XLOOKUP($B88,'Ownership Metrics'!$A:$A,'Ownership Metrics'!$H:$H),"") -> Terkonsentrasi | T88: =IFERROR(_xlfn.XLOOKUP($B88,'Ownership Metrics'!$A:$A,'Ownership Metrics'!$I:$I),"") -> Tinggi | U88: =IF(COUNTIFS($B$2:$B88,$B88,$D$2:$D88,$D88)=1,1,0) -> 1 | V88: =SUMIFS($L$2:$L$10000,$B$2:$B$10000,$B88,$D$2:$D$10000,$D88) -> 35.24 | W88: =COUNTIFS($B$2:$B$10000,$B88,$U$2:$U$10000,1,$X$2:$X$10000,">"&$X88)+1 -> 1 | X88: =$V88-(ROW()*0.0000000001) -> 35.24
A89: 46265 | B89: AGII | C89: SAMATOR INDO GAS Tbk | D89: MATRIX COMPANY LIMITED | E89: Private Equity | F89: F | H89: JERSEY | I89: 986967780 | J89: 0 | K89: 986967780 | L89: 32.18 | M89: =IFERROR(_xlfn.XLOOKUP($B89,'Ownership Metrics'!$A:$A,'Ownership Metrics'!$B:$B),"") -> 4.59 | N89: =IFERROR(_xlfn.XLOOKUP($B89,'Ownership Metrics'!$A:$A,'Ownership Metrics'!$C:$C),"") -> 2611 | O89: =IFERROR(_xlfn.XLOOKUP($B89,'Ownership Metrics'!$A:$A,'Ownership Metrics'!$D:$D),"") -> 35.24 | P89: =IFERROR(_xlfn.XLOOKUP($B89,'Ownership Metrics'!$A:$A,'Ownership Metrics'!$E:$E),"") -> 82.42 | Q89: =IFERROR(_xlfn.XLOOKUP($B89,'Ownership Metrics'!$A:$A,'Ownership Metrics'!$F:$F),"") -> 5 | R89: =IFERROR(_xlfn.XLOOKUP($B89,'Ownership Metrics'!$A:$A,'Ownership Metrics'!$G:$G),"") -> 56 | S89: =IFERROR(_xlfn.XLOOKUP($B89,'Ownership Metrics'!$A:$A,'Ownership Metrics'!$H:$H),"") -> Terkonsentrasi | T89: =IFERROR(_xlfn.XLOOKUP($B89,'Ownership Metrics'!$A:$A,'Ownership Metrics'!$I:$I),"") -> Tinggi | U89: =IF(COUNTIFS($B$2:$B89,$B89,$D$2:$D89,$D89)=1,1,0) -> 1 | V89: =SUMIFS($L$2:$L$10000,$B$2:$B$10000,$B89,$D$2:$D$10000,$D89) -> 32.18 | W89: =COUNTIFS($B$2:$B$10000,$B89,$U$2:$U$10000,1,$X$2:$X$10000,">"&$X89)+1 -> 2 | X89: =$V89-(ROW()*0.0000000001) -> 32.18
A90: 46265 | B90: AGII | C90: SAMATOR INDO GAS Tbk | D90: ZICO TRUST (S) LTD. | E90: Trustee Bank | F90: F | H90: SINGAPORE | I90: 91633900 | J90: 0 | K90: 91633900 | L90: 2.99 | M90: =IFERROR(_xlfn.XLOOKUP($B90,'Ownership Metrics'!$A:$A,'Ownership Metrics'!$B:$B),"") -> 4.59 | N90: =IFERROR(_xlfn.XLOOKUP($B90,'Ownership Metrics'!$A:$A,'Ownership Metrics'!$C:$C),"") -> 2611 | O90: =IFERROR(_xlfn.XLOOKUP($B90,'Ownership Metrics'!$A:$A,'Ownership Metrics'!$D:$D),"") -> 35.24 | P90: =IFERROR(_xlfn.XLOOKUP($B90,'Ownership Metrics'!$A:$A,'Ownership Metrics'!$E:$E),"") -> 82.42 | Q90: =IFERROR(_xlfn.XLOOKUP($B90,'Ownership Metrics'!$A:$A,'Ownership Metrics'!$F:$F),"") -> 5 | R90: =IFERROR(_xlfn.XLOOKUP($B90,'Ownership Metrics'!$A:$A,'Ownership Metrics'!$G:$G),"") -> 56 | S90: =IFERROR(_xlfn.XLOOKUP($B90,'Ownership Metrics'!$A:$A,'Ownership Metrics'!$H:$H),"") -> Terkonsentrasi | T90: =IFERROR(_xlfn.XLOOKUP($B90,'Ownership Metrics'!$A:$A,'Ownership Metrics'!$I:$I),"") -> Tinggi | U90: =IF(COUNTIFS($B$2:$B90,$B90,$D$2:$D90,$D90)=1,1,0) -> 1 | V90: =SUMIFS($L$2:$L$10000,$B$2:$B$10000,$B90,$D$2:$D$10000,$D90) -> 2.99 | W90: =COUNTIFS($B$2:$B$10000,$B90,$U$2:$U$10000,1,$X$2:$X$10000,">"&$X90)+1 -> 5 | X90: =$V90-(ROW()*0.0000000001) -> 2.99
A91: 46265 | B91: AGRO | C91: BANK RAYA INDONESIA Tbk | D91: BANK RAKYAT INDONESIA (PERSERO), PT | E91: Bank | F91: L | H91: INDONESIA | I91: 21239760958 | J91: 0 | K91: 21239760958 | L91: 85.85 | M91: =IFERROR(_xlfn.XLOOKUP($B91,'Ownership Metrics'!$A:$A,'Ownership Metrics'!$B:$B),"") -> 11.72 | N91: =IFERROR(_xlfn.XLOOKUP($B91,'Ownership Metrics'!$A:$A,'Ownership Metrics'!$C:$C),"") -> 7376 | O91: =IFERROR(_xlfn.XLOOKUP($B91,'Ownership Metrics'!$A:$A,'Ownership Metrics'!$D:$D),"") -> 85.85 | P91: =IFERROR(_xlfn.XLOOKUP($B91,'Ownership Metrics'!$A:$A,'Ownership Metrics'!$E:$E),"") -> 88.28 | Q91: =IFERROR(_xlfn.XLOOKUP($B91,'Ownership Metrics'!$A:$A,'Ownership Metrics'!$F:$F),"") -> 2 | R91: =IFERROR(_xlfn.XLOOKUP($B91,'Ownership Metrics'!$A:$A,'Ownership Metrics'!$G:$G),"") -> 83 | S91: =IFERROR(_xlfn.XLOOKUP($B91,'Ownership Metrics'!$A:$A,'Ownership Metrics'!$H:$H),"") -> Mayoritas | T91: =IFERROR(_xlfn.XLOOKUP($B91,'Ownership Metrics'!$A:$A,'Ownership Metrics'!$I:$I),"") -> Tinggi | U91: =IF(COUNTIFS($B$2:$B91,$B91,$D$2:$D91,$D91)=1,1,0) -> 1 | V91: =SUMIFS($L$2:$L$10000,$B$2:$B$10000,$B91,$D$2:$D$10000,$D91) -> 85.85 | W91: =COUNTIFS($B$2:$B$10000,$B91,$U$2:$U$10000,1,$X$2:$X$10000,">"&$X91)+1 -> 1 | X91: =$V91-(ROW()*0.0000000001) -> 85.85
A92: 46265 | B92: AGRO | C92: BANK RAYA INDONESIA Tbk | D92: DANA PENSIUN PERKEBUNAN | E92: Pension Funds | F92: L | H92: INDONESIA | I92: 600703375 | J92: 0 | K92: 600703375 | L92: 2.43 | M92: =IFERROR(_xlfn.XLOOKUP($B92,'Ownership Metrics'!$A:$A,'Ownership Metrics'!$B:$B),"") -> 11.72 | N92: =IFERROR(_xlfn.XLOOKUP($B92,'Ownership Metrics'!$A:$A,'Ownership Metrics'!$C:$C),"") -> 7376 | O92: =IFERROR(_xlfn.XLOOKUP($B92,'Ownership Metrics'!$A:$A,'Ownership Metrics'!$D:$D),"") -> 85.85 | P92: =IFERROR(_xlfn.XLOOKUP($B92,'Ownership Metrics'!$A:$A,'Ownership Metrics'!$E:$E),"") -> 88.28 | Q92: =IFERROR(_xlfn.XLOOKUP($B92,'Ownership Metrics'!$A:$A,'Ownership Metrics'!$F:$F),"") -> 2 | R92: =IFERROR(_xlfn.XLOOKUP($B92,'Ownership Metrics'!$A:$A,'Ownership Metrics'!$G:$G),"") -> 83 | S92: =IFERROR(_xlfn.XLOOKUP($B92,'Ownership Metrics'!$A:$A,'Ownership Metrics'!$H:$H),"") -> Mayoritas | T92: =IFERROR(_xlfn.XLOOKUP($B92,'Ownership Metrics'!$A:$A,'Ownership Metrics'!$I:$I),"") -> Tinggi | U92: =IF(COUNTIFS($B$2:$B92,$B92,$D$2:$D92,$D92)=1,1,0) -> 1 | V92: =SUMIFS($L$2:$L$10000,$B$2:$B$10000,$B92,$D$2:$D$10000,$D92) -> 2.43 | W92: =COUNTIFS($B$2:$B$10000,$B92,$U$2:$U$10000,1,$X$2:$X$10000,">"&$X92)+1 -> 2 | X92: =$V92-(ROW()*0.0000000001) -> 2.43
A93: 46265 | B93: AGRS | C93: BANK IBK INDONESIA Tbk | D93: INDUSTRIAL BANK OF KOREA | E93: Private Bank | F93: F | H93: KOREA, REPUBLIC OF | I93: 4701453340 | J93: 39090909045 | K93: 43792362385 | L93: 91.49 | M93: =IFERROR(_xlfn.XLOOKUP($B93,'Ownership Metrics'!$A:$A,'Ownership Metrics'!$B:$B),"") -> 5.55 | N93: =IFERROR(_xlfn.XLOOKUP($B93,'Ownership Metrics'!$A:$A,'Ownership Metrics'!$C:$C),"") -> 8379 | O93: =IFERROR(_xlfn.XLOOKUP($B93,'Ownership Metrics'!$A:$A,'Ownership Metrics'!$D:$D),"") -> 91.49 | P93: =IFERROR(_xlfn.XLOOKUP($B93,'Ownership Metrics'!$A:$A,'Ownership Metrics'!$E:$E),"") -> 94.45 | Q93: =IFERROR(_xlfn.XLOOKUP($B93,'Ownership Metrics'!$A:$A,'Ownership Metrics'!$F:$F),"") -> 2 | R93: =IFERROR(_xlfn.XLOOKUP($B93,'Ownership Metrics'!$A:$A,'Ownership Metrics'!$G:$G),"") -> 90 | S93: =IFERROR(_xlfn.XLOOKUP($B93,'Ownership Metrics'!$A:$A,'Ownership Metrics'!$H:$H),"") -> Mayoritas | T93: =IFERROR(_xlfn.XLOOKUP($B93,'Ownership Metrics'!$A:$A,'Ownership Metrics'!$I:$I),"") -> Tinggi | U93: =IF(COUNTIFS($B$2:$B93,$B93,$D$2:$D93,$D93)=1,1,0) -> 1 | V93: =SUMIFS($L$2:$L$10000,$B$2:$B$10000,$B93,$D$2:$D$10000,$D93) -> 91.49 | W93: =COUNTIFS($B$2:$B$10000,$B93,$U$2:$U$10000,1,$X$2:$X$10000,">"&$X93)+1 -> 1 | X93: =$V93-(ROW()*0.0000000001) -> 91.49
A94: 46265 | B94: AGRS | C94: BANK IBK INDONESIA Tbk | D94: PT KOREA INVESTMENT AND SEKURITAS INDONESIA | E94: Securities Company | F94: L | H94: INDONESIA | I94: 1414728100 | J94: 0 | K94: 1414728100 | L94: 2.96 | M94: =IFERROR(_xlfn.XLOOKUP($B94,'Ownership Metrics'!$A:$A,'Ownership Metrics'!$B:$B),"") -> 5.55 | N94: =IFERROR(_xlfn.XLOOKUP($B94,'Ownership Metrics'!$A:$A,'Ownership Metrics'!$C:$C),"") -> 8379 | O94: =IFERROR(_xlfn.XLOOKUP($B94,'Ownership Metrics'!$A:$A,'Ownership Metrics'!$D:$D),"") -> 91.49 | P94: =IFERROR(_xlfn.XLOOKUP($B94,'Ownership Metrics'!$A:$A,'Ownership Metrics'!$E:$E),"") -> 94.45 | Q94: =IFERROR(_xlfn.XLOOKUP($B94,'Ownership Metrics'!$A:$A,'Ownership Metrics'!$F:$F),"") -> 2 | R94: =IFERROR(_xlfn.XLOOKUP($B94,'Ownership Metrics'!$A:$A,'Ownership Metrics'!$G:$G),"") -> 90 | S94: =IFERROR(_xlfn.XLOOKUP($B94,'Ownership Metrics'!$A:$A,'Ownership Metrics'!$H:$H),"") -> Mayoritas | T94: =IFERROR(_xlfn.XLOOKUP($B94,'Ownership Metrics'!$A:$A,'Ownership Metrics'!$I:$I),"") -> Tinggi | U94: =IF(COUNTIFS($B$2:$B94,$B94,$D$2:$D94,$D94)=1,1,0) -> 1 | V94: =SUMIFS($L$2:$L$10000,$B$2:$B$10000,$B94,$D$2:$D$10000,$D94) -> 2.96 | W94: =COUNTIFS($B$2:$B$10000,$B94,$U$2:$U$10000,1,$X$2:$X$10000,">"&$X94)+1 -> 2 | X94: =$V94-(ROW()*0.0000000001) -> 2.96
A95: 46265 | B95: AHAP | C95: ASURANSI HARTA AMAN PRATAMA Tbk | D95: PT ASIAN INTERNATIONAL INVESTINDO | E95: Corporate | F95: L | H95: INDONESIA | I95: 52829854 | J95: 0 | K95: 52829854 | L95: 1.08 | M95: =IFERROR(_xlfn.XLOOKUP($B95,'Ownership Metrics'!$A:$A,'Ownership Metrics'!$B:$B),"") -> 20.54 | N95: =IFERROR(_xlfn.XLOOKUP($B95,'Ownership Metrics'!$A:$A,'Ownership Metrics'!$C:$C),"") -> 4072 | O95: =IFERROR(_xlfn.XLOOKUP($B95,'Ownership Metrics'!$A:$A,'Ownership Metrics'!$D:$D),"") -> 62.58 | P95: =IFERROR(_xlfn.XLOOKUP($B95,'Ownership Metrics'!$A:$A,'Ownership Metrics'!$E:$E),"") -> 77.07 | Q95: =IFERROR(_xlfn.XLOOKUP($B95,'Ownership Metrics'!$A:$A,'Ownership Metrics'!$F:$F),"") -> 5 | R95: =IFERROR(_xlfn.XLOOKUP($B95,'Ownership Metrics'!$A:$A,'Ownership Metrics'!$G:$G),"") -> 61 | S95: =IFERROR(_xlfn.XLOOKUP($B95,'Ownership Metrics'!$A:$A,'Ownership Metrics'!$H:$H),"") -> Mayoritas | T95: =IFERROR(_xlfn.XLOOKUP($B95,'Ownership Metrics'!$A:$A,'Ownership Metrics'!$I:$I),"") -> Tinggi | U95: =IF(COUNTIFS($B$2:$B95,$B95,$D$2:$D95,$D95)=1,1,0) -> 1 | V95: =SUMIFS($L$2:$L$10000,$B$2:$B$10000,$B95,$D$2:$D$10000,$D95) -> 1.08 | W95: =COUNTIFS($B$2:$B$10000,$B95,$U$2:$U$10000,1,$X$2:$X$10000,">"&$X95)+1 -> 5 | X95: =$V95-(ROW()*0.0000000001) -> 1.08
A96: 46265 | B96: AHAP | C96: ASURANSI HARTA AMAN PRATAMA Tbk | D96: SENDRA GUNAWAN | E96: Individual | F96: L | G96: INDONESIAN | H96: INDONESIA | I96: 594981066 | J96: 0 | K96: 594981066 | L96: 12.14 | M96: =IFERROR(_xlfn.XLOOKUP($B96,'Ownership Metrics'!$A:$A,'Ownership Metrics'!$B:$B),"") -> 20.54 | N96: =IFERROR(_xlfn.XLOOKUP($B96,'Ownership Metrics'!$A:$A,'Ownership Metrics'!$C:$C),"") -> 4072 | O96: =IFERROR(_xlfn.XLOOKUP($B96,'Ownership Metrics'!$A:$A,'Ownership Metrics'!$D:$D),"") -> 62.58 | P96: =IFERROR(_xlfn.XLOOKUP($B96,'Ownership Metrics'!$A:$A,'Ownership Metrics'!$E:$E),"") -> 77.07 | Q96: =IFERROR(_xlfn.XLOOKUP($B96,'Ownership Metrics'!$A:$A,'Ownership Metrics'!$F:$F),"") -> 5 | R96: =IFERROR(_xlfn.XLOOKUP($B96,'Ownership Metrics'!$A:$A,'Ownership Metrics'!$G:$G),"") -> 61 | S96: =IFERROR(_xlfn.XLOOKUP($B96,'Ownership Metrics'!$A:$A,'Ownership Metrics'!$H:$H),"") -> Mayoritas | T96: =IFERROR(_xlfn.XLOOKUP($B96,'Ownership Metrics'!$A:$A,'Ownership Metrics'!$I:$I),"") -> Tinggi | U96: =IF(COUNTIFS($B$2:$B96,$B96,$D$2:$D96,$D96)=1,1,0) -> 1 | V96: =SUMIFS($L$2:$L$10000,$B$2:$B$10000,$B96,$D$2:$D$10000,$D96) -> 12.14 | W96: =COUNTIFS($B$2:$B$10000,$B96,$U$2:$U$10000,1,$X$2:$X$10000,">"&$X96)+1 -> 2 | X96: =$V96-(ROW()*0.0000000001) -> 12.14
A97: 46265 | B97: AHAP | C97: ASURANSI HARTA AMAN PRATAMA Tbk | D97: TAN KAH HO | E97: Individual | F97: F | G97: SINGAPOREAN | H97: SINGAPORE | I97: 115237763 | J97: 0 | K97: 115237763 | L97: 2.35 | M97: =IFERROR(_xlfn.XLOOKUP($B97,'Ownership Metrics'!$A:$A,'Ownership Metrics'!$B:$B),"") -> 20.54 | N97: =IFERROR(_xlfn.XLOOKUP($B97,'Ownership Metrics'!$A:$A,'Ownership Metrics'!$C:$C),"") -> 4072 | O97: =IFERROR(_xlfn.XLOOKUP($B97,'Ownership Metrics'!$A:$A,'Ownership Metrics'!$D:$D),"") -> 62.58 | P97: =IFERROR(_xlfn.XLOOKUP($B97,'Ownership Metrics'!$A:$A,'Ownership Metrics'!$E:$E),"") -> 77.07 | Q97: =IFERROR(_xlfn.XLOOKUP($B97,'Ownership Metrics'!$A:$A,'Ownership Metrics'!$F:$F),"") -> 5 | R97: =IFERROR(_xlfn.XLOOKUP($B97,'Ownership Metrics'!$A:$A,'Ownership Metrics'!$G:$G),"") -> 61 | S97: =IFERROR(_xlfn.XLOOKUP($B97,'Ownership Metrics'!$A:$A,'Ownership Metrics'!$H:$H),"") -> Mayoritas | T97: =IFERROR(_xlfn.XLOOKUP($B97,'Ownership Metrics'!$A:$A,'Ownership Metrics'!$I:$I),"") -> Tinggi | U97: =IF(COUNTIFS($B$2:$B97,$B97,$D$2:$D97,$D97)=1,1,0) -> 1 | V97: =SUMIFS($L$2:$L$10000,$B$2:$B$10000,$B97,$D$2:$D$10000,$D97) -> 2.35 | W97: =COUNTIFS($B$2:$B$10000,$B97,$U$2:$U$10000,1,$X$2:$X$10000,">"&$X97)+1 -> 3 | X97: =$V97-(ROW()*0.0000000001) -> 2.35
A98: 46265 | B98: AHAP | C98: ASURANSI HARTA AMAN PRATAMA Tbk | D98: PT ASURANSI CENTRAL ASIA | E98: Insurance | F98: L | H98: INDONESIA | I98: 3066343009 | J98: 0 | K98: 3066343009 | L98: 62.58 | M98: =IFERROR(_xlfn.XLOOKUP($B98,'Ownership Metrics'!$A:$A,'Ownership Metrics'!$B:$B),"") -> 20.54 | N98: =IFERROR(_xlfn.XLOOKUP($B98,'Ownership Metrics'!$A:$A,'Ownership Metrics'!$C:$C),"") -> 4072 | O98: =IFERROR(_xlfn.XLOOKUP($B98,'Ownership Metrics'!$A:$A,'Ownership Metrics'!$D:$D),"") -> 62.58 | P98: =IFERROR(_xlfn.XLOOKUP($B98,'Ownership Metrics'!$A:$A,'Ownership Metrics'!$E:$E),"") -> 77.07 | Q98: =IFERROR(_xlfn.XLOOKUP($B98,'Ownership Metrics'!$A:$A,'Ownership Metrics'!$F:$F),"") -> 5 | R98: =IFERROR(_xlfn.XLOOKUP($B98,'Ownership Metrics'!$A:$A,'Ownership Metrics'!$G:$G),"") -> 61 | S98: =IFERROR(_xlfn.XLOOKUP($B98,'Ownership Metrics'!$A:$A,'Ownership Metrics'!$H:$H),"") -> Mayoritas | T98: =IFERROR(_xlfn.XLOOKUP($B98,'Ownership Metrics'!$A:$A,'Ownership Metrics'!$I:$I),"") -> Tinggi | U98: =IF(COUNTIFS($B$2:$B98,$B98,$D$2:$D98,$D98)=1,1,0) -> 1 | V98: =SUMIFS($L$2:$L$10000,$B$2:$B$10000,$B98,$D$2:$D$10000,$D98) -> 62.58 | W98: =COUNTIFS($B$2:$B$10000,$B98,$U$2:$U$10000,1,$X$2:$X$10000,">"&$X98)+1 -> 1 | X98: =$V98-(ROW()*0.0000000001) -> 62.58
A99: 46265 | B99: AHAP | C99: ASURANSI HARTA AMAN PRATAMA Tbk | D99: BANGKOK INSURANCE PUBLIC COMPANY LIMITED | E99: Insurance | F99: F | H99: THAILAND | I99: 64086000 | J99: 0 | K99: 64086000 | L99: 1.31 | M99: =IFERROR(_xlfn.XLOOKUP($B99,'Ownership Metrics'!$A:$A,'Ownership Metrics'!$B:$B),"") -> 20.54 | N99: =IFERROR(_xlfn.XLOOKUP($B99,'Ownership Metrics'!$A:$A,'Ownership Metrics'!$C:$C),"") -> 4072 | O99: =IFERROR(_xlfn.XLOOKUP($B99,'Ownership Metrics'!$A:$A,'Ownership Metrics'!$D:$D),"") -> 62.58 | P99: =IFERROR(_xlfn.XLOOKUP($B99,'Ownership Metrics'!$A:$A,'Ownership Metrics'!$E:$E),"") -> 77.07 | Q99: =IFERROR(_xlfn.XLOOKUP($B99,'Ownership Metrics'!$A:$A,'Ownership Metrics'!$F:$F),"") -> 5 | R99: =IFERROR(_xlfn.XLOOKUP($B99,'Ownership Metrics'!$A:$A,'Ownership Metrics'!$G:$G),"") -> 61 | S99: =IFERROR(_xlfn.XLOOKUP($B99,'Ownership Metrics'!$A:$A,'Ownership Metrics'!$H:$H),"") -> Mayoritas | T99: =IFERROR(_xlfn.XLOOKUP($B99,'Ownership Metrics'!$A:$A,'Ownership Metrics'!$I:$I),"") -> Tinggi | U99: =IF(COUNTIFS($B$2:$B99,$B99,$D$2:$D99,$D99)=1,1,0) -> 1 | V99: =SUMIFS($L$2:$L$10000,$B$2:$B$10000,$B99,$D$2:$D$10000,$D99) -> 1.31 | W99: =COUNTIFS($B$2:$B$10000,$B99,$U$2:$U$10000,1,$X$2:$X$10000,">"&$X99)+1 -> 4 | X99: =$V99-(ROW()*0.0000000001) -> 1.31
A100: 46265 | B100: AIMS | C100: ARTHA MAHIYA INVESTAMA Tbk | D100: PT DELTA WIBAWA BERSAMA | E100: Corporate | F100: L | H100: INDONESIA | I100: 68493151 | J100: 0 | K100: 68493151 | L100: 31.13 | M100: =IFERROR(_xlfn.XLOOKUP($B100,'Ownership Metrics'!$A:$A,'Ownership Metrics'!$B:$B),"") -> 16.6 | N100: =IFERROR(_xlfn.XLOOKUP($B100,'Ownership Metrics'!$A:$A,'Ownership Metrics'!$C:$C),"") -> 2185 | O100: =IFERROR(_xlfn.XLOOKUP($B100,'Ownership Metrics'!$A:$A,'Ownership Metrics'!$D:$D),"") -> 34.01 | P100: =IFERROR(_xlfn.XLOOKUP($B100,'Ownership Metrics'!$A:$A,'Ownership Metrics'!$E:$E),"") -> 70.21 | Q100: =IFERROR(_xlfn.XLOOKUP($B100,'Ownership Metrics'!$A:$A,'Ownership Metrics'!$F:$F),"") -> 10 | R100: =IFERROR(_xlfn.XLOOKUP($B100,'Ownership Metrics'!$A:$A,'Ownership Metrics'!$G:$G),"") -> 45 | S100: =IFERROR(_xlfn.XLOOKUP($B100,'Ownership Metrics'!$A:$A,'Ownership Metrics'!$H:$H),"") -> Terkonsentrasi | T100: =IFERROR(_xlfn.XLOOKUP($B100,'Ownership Metrics'!$A:$A,'Ownership Metrics'!$I:$I),"") -> Sedang | U100: =IF(COUNTIFS($B$2:$B100,$B100,$D$2:$D100,$D100)=1,1,0) -> 1 | V100: =SUMIFS($L$2:$L$10000,$B$2:$B$10000,$B100,$D$2:$D$10000,$D100) -> 31.13 | W100: =COUNTIFS($B$2:$B$10000,$B100,$U$2:$U$10000,1,$X$2:$X$10000,">"&$X100)+1 -> 2 | X100: =$V100-(ROW()*0.0000000001) -> 31.13
...

Sheet OWNERSHIP CLASSIFICATION
A1: Date | B1: Ticker | C1: Company Name | D1: Bank | E1: Government | F1: Private Equity | G1: Trustee Bank | H1: Venture Capital | I1: Private Bank | J1: Exchange Traded Funds | K1: Investment Manager | L1: Investment Advisors | M1: Brokerage Firms | N1: Hedge Fund | O1: Sovereign Wealth Fund | P1: Capital Market Supporting Institutions and Professions | Q1: Commanditaire Vennootschap (CV) or Limited Partnership | R1: Firm | S1: Investment Fund Selling Agent | T1: Peer to Peer Lending | U1: Permanent Establishment | V1: Sole Proprietorship | W1: Corporate | X1: Association/Social Organizations | Y1: State Owned Enterprises | Z1: Central Bank | AA1: State Owned Company | AB1: Diocese | AC1: Conference | AD1: Congregation | AE1: Cooperatives | AF1: International Organization | AG1: Political Parties | AH1: Partnership | AI1: Educational Institution | AJ1: Mutual Funds (MF) | AK1: Securities Company (SC) | AL1: Pension Funds (PF) | AM1: Financial Institutional (IB) | AN1: Insurance (IS) | AO1: Foundation (FD) | AP1: Individual (ID) | AQ1: Total Scripless
A2: 46265 | B2: AADI | C2: ADARO ANDALAN INDONESIA Tbk | D2: 22689622 | E2: 2445800 | F2: 15534069 | G2: 14091457 | H2: 279109 | I2: 407745164 | J2: 74101165 | K2: 902068 | L2: 43202412 | M2: 1001874 | N2: 1511900 | O2: 5548173 | P2: 3431914 | Q2: 7896556 | R2: 9310345 | S2: 0 | T2: 0 | U2: 0 | V2: 2600 | W2: 4767324914 | X2: 117700 | Y2: 0 | Z2: 6906800 | AA2: 238400 | AB2: 0 | AC2: 0 | AD2: 0 | AE2: 75 | AF2: 0 | AG2: 0 | AH2: 1361600 | AI2: 112506 | AJ2: 375253695 | AK2: 25532845 | AL2: 50398966 | AM2: 112444141 | AN2: 129761778 | AO2: 2732997 | AP2: 1705011115 | AQ2: 7786891760
A3: 46265 | B3: AALI | C3: ASTRA AGRO LESTARI Tbk | D3: 17637913 | E3: 1706710 | F3: 665700 | G3: 444300 | H3: 0 | I3: 7986754 | J3: 3191010 | K3: 1092664 | L3: 20600401 | M3: 2442862 | N3: 461000 | O3: 1938458 | P3: 867079 | Q3: 2469300 | R3: 923700 | S3: 0 | T3: 0 | U3: 0 | V3: 0 | W3: 28382779 | X3: 0 | Y3: 13683700 | Z3: 103500 | AA3: 0 | AB3: 0 | AC3: 0 | AD3: 0 | AE3: 7800 | AF3: 0 | AG3: 0 | AH3: 4747227 | AI3: 0 | AJ3: 51282467 | AK3: 3963986 | AL3: 25024332 | AM3: 246036 | AN3: 59061116 | AO3: 4213312 | AP3: 137652987 | AQ3: 390797093
A4: 46265 | B4: ABBA | C4: MAHAKA MEDIA Tbk | D4: 629886 | E4: 0 | F4: 1593331618 | G4: 0 | H4: 0 | I4: 1690100 | J4: 0 | K4: 0 | L4: 77100 | M4: 0 | N4: 0 | O4: 0 | P4: 0 | Q4: 0 | R4: 46247699 | S4: 0 | T4: 0 | U4: 0 | V4: 0 | W4: 728542388 | X4: 0 | Y4: 0 | Z4: 0 | AA4: 0 | AB4: 0 | AC4: 0 | AD4: 0 | AE4: 0 | AF4: 0 | AG4: 0 | AH4: 0 | AI4: 0 | AJ4: 0 | AK4: 1754780 | AL4: 0 | AM4: 39999999 | AN4: 0 | AO4: 71 | AP4: 1065382715 | AQ4: 3477656356
A5: 46265 | B5: ABDA | C5: ASURANSI BINA DANA ARTA Tbk | D5: 3598 | E5: 20 | F5: 21750171 | G5: 0 | H5: 0 | I5: 28002100 | J5: 0 | K5: 0 | L5: 516 | M5: 0 | N5: 0 | O5: 0 | P5: 0 | Q5: 0 | R5: 0 | S5: 0 | T5: 0 | U5: 0 | V5: 0 | W5: 32120 | X5: 0 | Y5: 0 | Z5: 0 | AA5: 0 | AB5: 0 | AC5: 0 | AD5: 0 | AE5: 0 | AF5: 0 | AG5: 0 | AH5: 0 | AI5: 0 | AJ5: 0 | AK5: 30511250 | AL5: 0 | AM5: 0 | AN5: 538604204 | AO5: 422334 | AP5: 442757 | AQ5: 619769070
A6: 46265 | B6: ABMM | C6: ABM INVESTAMA Tbk | D6: 19432 | E6: 42100 | F6: 43000 | G6: 131000 | H6: 127000 | I6: 1000100 | J6: 2594000 | K6: 705520 | L6: 4615100 | M6: 373120 | N6: 0 | O6: 93400 | P6: 20000 | Q6: 486800 | R6: 702464167 | S6: 0 | T6: 0 | U6: 0 | V6: 0 | W6: 1502322871 | X6: 0 | Y6: 0 | Z6: 0 | AA6: 0 | AB6: 0 | AC6: 0 | AD6: 0 | AE6: 0 | AF6: 0 | AG6: 0 | AH6: 30637 | AI6: 0 | AJ6: 109379735 | AK6: 3973324 | AL6: 4376994 | AM6: 460000 | AN6: 1453200 | AO6: 0 | AP6: 418453500 | AQ6: 2753165000
A7: 46265 | B7: ACES | C7: ASPIRASI HIDUP INDONESIA Tbk | D7: 187720069 | E7: 23427500 | F7: 28559900 | G7: 20888800 | H7: 28612200 | I7: 21264500 | J7: 193513238 | K7: 34626947 | L7: 373436954 | M7: 174827 | N7: 0 | O7: 116448000 | P7: 1263274 | Q7: 426200 | R7: 2154800 | S7: 0 | T7: 0 | U7: 0 | V7: 605500 | W7: 10907882112 | X7: 3800 | Y7: 0 | Z7: 4665812 | AA7: 0 | AB7: 0 | AC7: 0 | AD7: 300000 | AE7: 28637687 | AF7: 1700000 | AG7: 0 | AH7: 40000 | AI7: 100 | AJ7: 1641078609 | AK7: 153091663 | AL7: 391273703 | AM7: 9285900 | AN7: 229630300 | AO7: 16623414 | AP7: 2702953891 | AQ7: 17120289700
A8: 46265 | B8: ACRO | C8: SAMCRO HYOSUNG ADILESTARI Tbk | D8: 0 | E8: 0 | F8: 0 | G8: 0 | H8: 0 | I8: 0 | J8: 0 | K8: 0 | L8: 3602900 | M8: 0 | N8: 0 | O8: 0 | P8: 0 | Q8: 4700 | R8: 0 | S8: 0 | T8: 0 | U8: 0 | V8: 0 | W8: 0 | X8: 0 | Y8: 0 | Z8: 0 | AA8: 0 | AB8: 0 | AC8: 0 | AD8: 0 | AE8: 0 | AF8: 0 | AG8: 0 | AH8: 0 | AI8: 0 | AJ8: 0 | AK8: 109303 | AL8: 0 | AM8: 0 | AN8: 0 | AO8: 0 | AP8: 3465628634 | AQ8: 3469345537
A9: 46265 | B9: ACST | C9: ACSET INDONUSA Tbk | D9: 1888020 | E9: 80 | F9: 0 | G9: 0 | H9: 0 | I9: 1433224 | J9: 0 | K9: 1430035 | L9: 5081800 | M9: 20 | N9: 0 | O9: 0 | P9: 0 | Q9: 228400 | R9: 20029600 | S9: 0 | T9: 0 | U9: 67 | V9: 0 | W9: 16201140388 | X9: 0 | Y9: 0 | Z9: 0 | AA9: 0 | AB9: 0 | AC9: 0 | AD9: 0 | AE9: 0 | AF9: 0 | AG9: 0 | AH9: 0 | AI9: 100 | AJ9: 0 | AK9: 391040 | AL9: 0 | AM9: 0 | AN9: 0 | AO9: 0 | AP9: 1443537226 | AQ9: 17675160000
A10: 46265 | B10: ADCP | C10: ADHI COMMUTER PROPERTI Tbk | D10: 1526600 | E10: 0 | F10: 0 | G10: 0 | H10: 0 | I10: 100 | J10: 0 | K10: 0 | L10: 2815200 | M10: 0 | N10: 0 | O10: 0 | P10: 0 | Q10: 0 | R10: 0 | S10: 0 | T10: 0 | U10: 0 | V10: 0 | W10: 452547000 | X10: 0 | Y10: 0 | Z10: 0 | AA10: 0 | AB10: 0 | AC10: 0 | AD10: 0 | AE10: 147078400 | AF10: 0 | AG10: 0 | AH10: 0 | AI10: 700 | AJ10: 0 | AK10: 1772700 | AL10: 1200000 | AM10: 0 | AN10: 0 | AO10: 400 | AP10: 1615281100 | AQ10: 2222222200
A11: 46265 | B11: ADES | C11: AKASHA WIRA INTERNATIONAL Tbk | D11: 3925450 | E11: 0 | F11: 16900 | G11: 61400 | H11: 0 | I11: 126400 | J11: 0 | K11: 193600 | L11: 5300 | M11: 97 | N11: 0 | O11: 0 | P11: 2000 | Q11: 200 | R11: 0 | S11: 0 | T11: 0 | U11: 0 | V11: 0 | W11: 542487377 | X11: 0 | Y11: 0 | Z11: 0 | AA11: 0 | AB11: 0 | AC11: 0 | AD11: 0 | AE11: 0 | AF11: 0 | AG11: 0 | AH11: 0 | AI11: 0 | AJ11: 453300 | AK11: 243171 | AL11: 60300 | AM11: 10000 | AN11: 0 | AO11: 0 | AP11: 41622877 | AQ11: 589208372
A12: 46265 | B12: ADHI | C12: ADHI KARYA (PERSERO) Tbk | D12: 4370003 | E12: 8140487 | F12: 814100 | G12: 0 | H12: 0 | I12: 10354029 | J12: 5778269 | K12: 377423 | L12: 7373914 | M12: 78 | N12: 0 | O12: 226107 | P12: 2874334 | Q12: 1400084 | R12: 105979900 | S12: 0 | T12: 0 | U12: 0 | V12: 0 | W12: 139799261 | X12: 0 | Y12: 260820 | Z12: 2359600 | AA12: 0 | AB12: 0 | AC12: 0 | AD12: 20000 | AE12: 964900 | AF12: 0 | AG12: 0 | AH12: 0 | AI12: 300 | AJ12: 3004602 | AK12: 261691553 | AL12: 50630880 | AM12: 3000000 | AN12: 15478759 | AO12: 1150438 | AP12: 2372775346 | AQ12: 2998825187
A13: 46265 | B13: ADMF | C13: ADIRA DINAMIKA MULTI FINANCE Tbk | D13: 920905338 | E13: 0 | F13: 50000 | G13: 0 | H13: 0 | I13: 233807670 | J13: 0 | K13: 29631 | L13: 58606 | M13: 17247 | N13: 168500 | O13: 0 | P13: 0 | Q13: 200 | R13: 16000 | S13: 0 | T13: 0 | U13: 0 | V13: 400 | W13: 681088 | X13: 0 | Y13: 0 | Z13: 0 | AA13: 0 | AB13: 0 | AC13: 0 | AD13: 0 | AE13: 0 | AF13: 0 | AG13: 0 | AH13: 0 | AI13: 0 | AJ13: 8857000 | AK13: 8509766 | AL13: 274274 | AM13: 9836454 | AN13: 5082393 | AO13: 98 | AP13: 47408444 | AQ13: 1235703109
... A963: 46265 | B963: ZYRX | C963: ZYREXINDO MANDIRI BUANA Tbk | D963: 0 | E963: 0 | F963: 68682000 | G963: 0 | H963: 0 | I963: 100 | J963: 0 | K963: 0 | L963: 0 | M963: 0 | N963: 0 | O963: 0 | P963: 0 | Q963: 0 | R963: 0 | S963: 0 | T963: 0 | U963: 0 | V963: 0 | W963: 142839400 | X963: 0 | Y963: 0 | Z963: 0 | AA963: 0 | AB963: 0 | AC963: 0 | AD963: 0 | AE963: 0 | AF963: 0 | AG963: 0 | AH963: 0 | AI963: 0 | AJ963: 0 | AK963: 1150 | AL963: 0 | AM963: 0 | AN963: 0 | AO963: 0 | AP963: 121811906 | AQ963: 333334556

Sheet IHSG INDEX
A1: Sector Index | B1: Ticker | C1: Free Float Ratio | D1: Shares for Index (Units) | G1: Index Weight
D2: Pre-Evaluation | E2: Post-Evaluation (9% Cap) | F2: Status (Fixed/Up/Down/New) | G2: Pre-Evaluation | H2: Post-Evaluation | I2: Status (Fixed/Up/Down/New)
A3: IHSG | B3: AADI | C3: 0.1909 | D3: 1464714340 | E3: 1486517637 | F3: Naik | G3: 0.0048558699 | H3: 0.004909016 | I3: Tetap
A4: IHSG | B4: AALI | C4: 0.203 | D4: 390711732 | E4: 390711732 | F4: Tetap | G4: 0.00090420742 | H4: 0.0009006962 | I4: Tetap
A5: IHSG | B5: ABBA | C5: 0.33 | D5: 1298844643 | E5: 1298844643 | F5: Tetap | G5: 1.6225406e-05 | H5: 1.61624e-05 | I5: Tetap
A6: IHSG | B6: ABDA | C6: 0.131 | D6: 81325675 | E6: 81325675 | F6: Tetap | G6: 7.0333982e-05 | H6: 7.0060861e-05 | I6: Tetap
A7: IHSG | B7: ABMM | C7: 0.1503 | D7: 414626649 | E7: 413800700 | F7: Turun | G7: 0.00037452437 | H7: 0.00037232685 | I7: Tetap
A8: IHSG | B8: ACES | C8: 0.3999 | D8: 6846443841 | E8: 6846443841 | F8: Tetap | G8: 0.00083334035 | H8: 0.00083010432 | I8: Tetap
A9: IHSG | B9: ACRO | C9: 0.2104 | D9: 720207460 | E9: 729950301 | F9: Naik | G9: 1.499494e-05 | H9: 1.5138773e-05 | I9: Tetap
A10: IHSG | B10: ACST | C10: 0.0883 | D10: 1560716628 | E10: 1560716628 | F10: Tetap | G10: 5.2991192e-05 | H10: 5.2785416e-05 | I10: Tetap
A11: IHSG | B11: ADCP | C11: 0.1 | D11: 2222222220 | E11: 2222222220 | F11: Tetap | G11: 3.5590268e-05 | H11: 3.5452063e-05 | I11: Tetap
A12: IHSG | B12: ADES | C12: 0.0853 | D12: 50318197 | E12: 50318197 | F12: Tetap | G12: 0.00024216608 | H12: 0.0002412257 | I12: Tetap
A13: IHSG | B13: ADHI | C13: 0.3563 | D13: 2993949557 | E13: 2995631079 | F13: Naik | G13: 0.00019371784 | H13: 0.00019307397 | I13: Tetap
A14: IHSG | B14: ADMF | C14: 0.0544 | D14: 67104109 | E14: 67227689 | F14: Naik | G14: 0.0001773278 | H14: 0.0001769645 | I14: Tetap
... A914: IHSG | B914: ZYRX | C914: 0.2011 | D914: 269200247 | E914: 268133579 | F914: Turun | G914: 1.233063e-05 | H914: 1.2234079e-05 | I914: Tetap

Sheet SECTORAL INDEX
A1: Sector Index | B1: Ticker | C1: Free Float Ratio | D1: Shares for Index (Units) | G1: Index Weight
D2: Pre-Evaluation | E2: Post-Evaluation (9% Cap) | F2: Status (Fixed/Up/Down/New) | G2: Pre-Evaluation | H2: Post-Evaluation | I2: Status (Fixed/Up/Down/New)
A3: IDXENERGY | B3: AADI | C3: 0.1909 | D3: 1464714340 | E3: 1486517637 | F3: Naik | G3: 0.050663109 | H3: 0.046729188 | I3: Turun
A4: IDXENERGY | B4: ABMM | C4: 0.1503 | D4: 414626649 | E4: 413800700 | F4: Turun | G4: 0.0039075529 | H4: 0.0035441994 | I4: Turun
A5: IDXENERGY | B5: ADMR | C5: 0.1156 | D5: 4893615081 | E5: 4725997521 | F5: Turun | G5: 0.030664058 | H5: 0.026913649 | I5: Turun
A6: IDXENERGY | B6: ADRO | C6: 0.2867 | D6: 8426023951 | E6: 8426023951 | F6: Tetap | G6: 0.068708595 | H6: 0.062443945 | I6: Turun
A7: IDXENERGY | B7: AIMS | C7: 0.3263 | D7: 71786000 | E7: 71786000 | F7: Tetap | G7: 9.4042545e-05 | H7: 8.546802e-05 | I7: Tetap
A8: IDXENERGY | B8: AKRA | C8: 0.3265 | D8: 6551982109 | E8: 6553989457 | F8: Naik | G8: 0.028136779 | H8: 0.025579184 | I8: Turun
A9: IDXENERGY | B9: ALII | C9: 0.194 | D9: 3163577420 | E9: 3070205200 | F9: Turun | G9: 0.0072421512 | H9: 0.0063875718 | I9: Turun
A10: IDXENERGY | B10: APEX | C10: 0.3282 | D10: 1163950358 | E10: 1163950358 | F10: Tetap | G10: 0.00066905444 | H10: 0.00060805201 | I10: Turun
A11: IDXENERGY | B11: ARII | C11: 0.4122 | D11: 1412542700 | E11: 1545750000 | F11: Naik | G11: 0.0012745706 | H11: 0.0012675959 | I11: Tetap
A12: IDXENERGY | B12: ARTI | C12: 0.5207 | D12: 4082288000 | E12: 4082288000 | F12: Tetap | G12: 2.7285517e-05 | H12: 2.4797703e-05 | I12: Tetap
A13: IDXENERGY | B13: ATLA | C13: 0.3735 | D13: 2128315022 | E13: 2315542268 | F13: Naik | G13: 0.00035563497 | H13: 0.00035164183 | I13: Tetap
A14: IDXENERGY | B14: BBRM | C14: 0.0894 | D14: 758066435 | E14: 758066435 | F14: Tetap | G14: 0.00031920991 | H14: 0.00029010528 | I14: Tetap
... A914: IDXTRANS | B914: WEHA | C914: 0.2997 | D914: 407640850 | E914: 437728279 | F914: Naik | G914: 0.0050608713 | H914: 0.0050734492 | I914: Tetap

Sheet KONGLO INDEX
A1: Conglomerate Group | B1: Ticker
A2: Agung Sedayu Group | B2: PANI
A3: Agung Sedayu Group | B3: CBDK
A4: Agung Sedayu Group | B4: ERAA
A5: Agung Sedayu Group | B5: ERAL
A6: Agung Sedayu Group | B6: PDPP
A7: Agung Sedayu Group | B7: INPC
A8: Agung Sedayu Group | B8: JIHD
A9: Alfa Corp | B9: AMRT
A10: Alfa Corp | B10: MIDI
A11: Alfa Corp | B11: BLOG
A12: Alfa Corp | B12: BANK
... A240: Wings Group | B240: MASB

Sheet Ownership Metrics
A1: Ticker | B1: Free Float (%) | C1: Classic HHI | D1: Concentration Ratio Top 1 (CR1) | E1: Concentration Ratio Top 3 (CR3) | F1: Holder | G1: CCS | H1: Ownership Type | I1: CCS Category
A2: =" "&'TICKER LIST'!B2 -> MGLV | B2: =IFERROR(ROUND(MAX(0,MIN(100,100-SUMIFS('OWNERSHIP 1%'!$V$2:$V$10000,'OWNERSHIP 1%'!$B$2:$B$10000,$A2,'OWNERSHIP 1%'!$U$2:$U$10000,1))),2),"") -> 13.36 | C2: {=IFERROR(ROUND(SUMPRODUCT(('OWNERSHIP 1%'!$B$2:$B$10000=$A2)*('OWNERSHIP 1%'!$U$2:$U$10000=1)*('OWNERSHIP 1%'!$V$2:$V$10000)^2),0),"")} -> 4552 | D2: =IFERROR(ROUND(_xlfn.SINGLE(_xlfn.MAXIFS('OWNERSHIP 1%'!$V$2:$V$10000,'OWNERSHIP 1%'!$B$2:$B$10000,$A2,'OWNERSHIP 1%'!$U$2:$U$10000,1)),2),"") -> 67.08 | E2: =IFERROR(ROUND(SUMIFS('OWNERSHIP 1%'!$V$2:$V$7159,'OWNERSHIP 1%'!$B$2:$B$7159,$A2,'OWNERSHIP 1%'!$U$2:$U$7159,1,'OWNERSHIP 1%'!$W$2:$W$7159,"<=3"),2),"") -> 74.46 | F2: {=IFERROR(SUMPRODUCT(('OWNERSHIP 1%'!$B$2:$B$10000=$A2)*('OWNERSHIP 1%'!$U$2:$U$10000=1)*('OWNERSHIP 1%'!$V$2:$V$10000>=1)),0)} -> 10 | G2: =IFERROR(ROUND(((C2/10000)*0.45+(E2/100)*0.35+IF(F2=0,0,MAX(0,MIN(1,(20-F2)/19)))*0.2)*100,0),"") -> 57 | H2: =IF(B2="","",IF(D2>=50,"Mayoritas",IF(E2>=70,"Terkonsentrasi",IF(E2>=60,"Oligopoli",IF(E2<=40,"Tersebar","Moderat"))))) -> Mayoritas | I2: =IF(G2="","",IF(G2<=25,"Rendah",IF(G2<=55,"Sedang","Tinggi"))) -> Tinggi
A3: =" "&'TICKER LIST'!B3 -> TRUE | B3: =IFERROR(ROUND(MAX(0,MIN(100,100-SUMIFS('OWNERSHIP 1%'!$V$2:$V$10000,'OWNERSHIP 1%'!$B$2:$B$10000,$A3,'OWNERSHIP 1%'!$U$2:$U$10000,1))),2),"") -> 24.96 | C3: {=IFERROR(ROUND(SUMPRODUCT(('OWNERSHIP 1%'!$B$2:$B$10000=$A3)*('OWNERSHIP 1%'!$U$2:$U$10000=1)*('OWNERSHIP 1%'!$V$2:$V$10000)^2),0),"")} -> 3023 | D3: =IFERROR(ROUND(_xlfn.SINGLE(_xlfn.MAXIFS('OWNERSHIP 1%'!$V$2:$V$10000,'OWNERSHIP 1%'!$B$2:$B$10000,$A3,'OWNERSHIP 1%'!$U$2:$U$10000,1)),2),"") -> 52.83 | E3: =IFERROR(ROUND(SUMIFS('OWNERSHIP 1%'!$V$2:$V$7159,'OWNERSHIP 1%'!$B$2:$B$7159,$A3,'OWNERSHIP 1%'!$U$2:$U$7159,1,'OWNERSHIP 1%'!$W$2:$W$7159,"<=3"),2),"") -> 70.9 | F3: {=IFERROR(SUMPRODUCT(('OWNERSHIP 1%'!$B$2:$B$10000=$A3)*('OWNERSHIP 1%'!$U$2:$U$10000=1)*('OWNERSHIP 1%'!$V$2:$V$10000>=1)),0)} -> 5 | G3: =IFERROR(ROUND(((C3/10000)*0.45+(E3/100)*0.35+IF(F3=0,0,MAX(0,MIN(1,(20-F3)/19)))*0.2)*100,0),"") -> 54 | H3: =IF(B3="","",IF(D3>=50,"Mayoritas",IF(E3>=70,"Terkonsentrasi",IF(E3>=60,"Oligopoli",IF(E3<=40,"Tersebar","Moderat"))))) -> Mayoritas | I3: =IF(G3="","",IF(G3<=25,"Rendah",IF(G3<=55,"Sedang","Tinggi"))) -> Sedang
A4: =" "&'TICKER LIST'!B4 -> LABA | B4: =IFERROR(ROUND(MAX(0,MIN(100,100-SUMIFS('OWNERSHIP 1%'!$V$2:$V$10000,'OWNERSHIP 1%'!$B$2:$B$10000,$A4,'OWNERSHIP 1%'!$U$2:$U$10000,1))),2),"") -> 61.53 | C4: {=IFERROR(ROUND(SUMPRODUCT(('OWNERSHIP 1%'!$B$2:$B$10000=$A4)*('OWNERSHIP 1%'!$U$2:$U$10000=1)*('OWNERSHIP 1%'!$V$2:$V$10000)^2),0),"")} -> 793 | D4: =IFERROR(ROUND(_xlfn.SINGLE(_xlfn.MAXIFS('OWNERSHIP 1%'!$V$2:$V$10000,'OWNERSHIP 1%'!$B$2:$B$10000,$A4,'OWNERSHIP 1%'!$U$2:$U$10000,1)),2),"") -> 25.54 | E4: =IFERROR(ROUND(SUMIFS('OWNERSHIP 1%'!$V$2:$V$7159,'OWNERSHIP 1%'!$B$2:$B$7159,$A4,'OWNERSHIP 1%'!$U$2:$U$7159,1,'OWNERSHIP 1%'!$W$2:$W$7159,"<=3"),2),"") -> 38.47 | F4: {=IFERROR(SUMPRODUCT(('OWNERSHIP 1%'!$B$2:$B$10000=$A4)*('OWNERSHIP 1%'!$U$2:$U$10000=1)*('OWNERSHIP 1%'!$V$2:$V$10000>=1)),0)} -> 3 | G4: =IFERROR(ROUND(((C4/10000)*0.45+(E4/100)*0.35+IF(F4=0,0,MAX(0,MIN(1,(20-F4)/19)))*0.2)*100,0),"") -> 35 | H4: =IF(B4="","",IF(D4>=50,"Mayoritas",IF(E4>=70,"Terkonsentrasi",IF(E4>=60,"Oligopoli",IF(E4<=40,"Tersebar","Moderat"))))) -> Tersebar | I4: =IF(G4="","",IF(G4<=25,"Rendah",IF(G4<=55,"Sedang","Tinggi"))) -> Sedang
A5: =" "&'TICKER LIST'!B5 -> ARCI | B5: =IFERROR(ROUND(MAX(0,MIN(100,100-SUMIFS('OWNERSHIP 1%'!$V$2:$V$10000,'OWNERSHIP 1%'!$B$2:$B$10000,$A5,'OWNERSHIP 1%'!$U$2:$U$10000,1))),2),"") -> 12.46 | C5: {=IFERROR(ROUND(SUMPRODUCT(('OWNERSHIP 1%'!$B$2:$B$10000=$A5)*('OWNERSHIP 1%'!$U$2:$U$10000=1)*('OWNERSHIP 1%'!$V$2:$V$10000)^2),0),"")} -> 7005 | D5: =IFERROR(ROUND(_xlfn.SINGLE(_xlfn.MAXIFS('OWNERSHIP 1%'!$V$2:$V$10000,'OWNERSHIP 1%'!$B$2:$B$10000,$A5,'OWNERSHIP 1%'!$U$2:$U$10000,1)),2),"") -> 83.65 | E5: =IFERROR(ROUND(SUMIFS('OWNERSHIP 1%'!$V$2:$V$7159,'OWNERSHIP 1%'!$B$2:$B$7159,$A5,'OWNERSHIP 1%'!$U$2:$U$7159,1,'OWNERSHIP 1%'!$W$2:$W$7159,"<=3"),2),"") -> 87.54 | F5: {=IFERROR(SUMPRODUCT(('OWNERSHIP 1%'!$B$2:$B$10000=$A5)*('OWNERSHIP 1%'!$U$2:$U$10000=1)*('OWNERSHIP 1%'!$V$2:$V$10000>=1)),0)} -> 3 | G5: =IFERROR(ROUND(((C5/10000)*0.45+(E5/100)*0.35+IF(F5=0,0,MAX(0,MIN(1,(20-F5)/19)))*0.2)*100,0),"") -> 80 | H5: =IF(B5="","",IF(D5>=50,"Mayoritas",IF(E5>=70,"Terkonsentrasi",IF(E5>=60,"Oligopoli",IF(E5<=40,"Tersebar","Moderat"))))) -> Mayoritas | I5: =IF(G5="","",IF(G5<=25,"Rendah",IF(G5<=55,"Sedang","Tinggi"))) -> Tinggi
A6: =" "&'TICKER LIST'!B6 -> IPAC | B6: =IFERROR(ROUND(MAX(0,MIN(100,100-SUMIFS('OWNERSHIP 1%'!$V$2:$V$10000,'OWNERSHIP 1%'!$B$2:$B$10000,$A6,'OWNERSHIP 1%'!$U$2:$U$10000,1))),2),"") -> 1.88 | C6: {=IFERROR(ROUND(SUMPRODUCT(('OWNERSHIP 1%'!$B$2:$B$10000=$A6)*('OWNERSHIP 1%'!$U$2:$U$10000=1)*('OWNERSHIP 1%'!$V$2:$V$10000)^2),0),"")} -> 8239 | D6: =IFERROR(ROUND(_xlfn.SINGLE(_xlfn.MAXIFS('OWNERSHIP 1%'!$V$2:$V$10000,'OWNERSHIP 1%'!$B$2:$B$10000,$A6,'OWNERSHIP 1%'!$U$2:$U$10000,1)),2),"") -> 90.6 | E6: =IFERROR(ROUND(SUMIFS('OWNERSHIP 1%'!$V$2:$V$7159,'OWNERSHIP 1%'!$B$2:$B$7159,$A6,'OWNERSHIP 1%'!$U$2:$U$7159,1,'OWNERSHIP 1%'!$W$2:$W$7159,"<=3"),2),"") -> 98.12 | F6: {=IFERROR(SUMPRODUCT(('OWNERSHIP 1%'!$B$2:$B$10000=$A6)*('OWNERSHIP 1%'!$U$2:$U$10000=1)*('OWNERSHIP 1%'!$V$2:$V$10000>=1)),0)} -> 3 | G6: =IFERROR(ROUND(((C6/10000)*0.45+(E6/100)*0.35+IF(F6=0,0,MAX(0,MIN(1,(20-F6)/19)))*0.2)*100,0),"") -> 89 | H6: =IF(B6="","",IF(D6>=50,"Mayoritas",IF(E6>=70,"Terkonsentrasi",IF(E6>=60,"Oligopoli",IF(E6<=40,"Tersebar","Moderat"))))) -> Mayoritas | I6: =IF(G6="","",IF(G6<=25,"Rendah",IF(G6<=55,"Sedang","Tinggi"))) -> Tinggi
A7: =" "&'TICKER LIST'!B7 -> MASB | B7: =IFERROR(ROUND(MAX(0,MIN(100,100-SUMIFS('OWNERSHIP 1%'!$V$2:$V$10000,'OWNERSHIP 1%'!$B$2:$B$10000,$A7,'OWNERSHIP 1%'!$U$2:$U$10000,1))),2),"") -> 5.1 | C7: {=IFERROR(ROUND(SUMPRODUCT(('OWNERSHIP 1%'!$B$2:$B$10000=$A7)*('OWNERSHIP 1%'!$U$2:$U$10000=1)*('OWNERSHIP 1%'!$V$2:$V$10000)^2),0),"")} -> 3206 | D7: =IFERROR(ROUND(_xlfn.SINGLE(_xlfn.MAXIFS('OWNERSHIP 1%'!$V$2:$V$10000,'OWNERSHIP 1%'!$B$2:$B$10000,$A7,'OWNERSHIP 1%'!$U$2:$U$10000,1)),2),"") -> 52.67 | E7: =IFERROR(ROUND(SUMIFS('OWNERSHIP 1%'!$V$2:$V$7159,'OWNERSHIP 1%'!$B$2:$B$7159,$A7,'OWNERSHIP 1%'!$U$2:$U$7159,1,'OWNERSHIP 1%'!$W$2:$W$7159,"<=3"),2),"") -> 75.99 | F7: {=IFERROR(SUMPRODUCT(('OWNERSHIP 1%'!$B$2:$B$10000=$A7)*('OWNERSHIP 1%'!$U$2:$U$10000=1)*('OWNERSHIP 1%'!$V$2:$V$10000>=1)),0)} -> 10 | G7: =IFERROR(ROUND(((C7/10000)*0.45+(E7/100)*0.35+IF(F7=0,0,MAX(0,MIN(1,(20-F7)/19)))*0.2)*100,0),"") -> 52 | H7: =IF(B7="","",IF(D7>=50,"Mayoritas",IF(E7>=70,"Terkonsentrasi",IF(E7>=60,"Oligopoli",IF(E7<=40,"Tersebar","Moderat"))))) -> Mayoritas | I7: =IF(G7="","",IF(G7<=25,"Rendah",IF(G7<=55,"Sedang","Tinggi"))) -> Sedang
A8: =" "&'TICKER LIST'!B8 -> BMHS | B8: =IFERROR(ROUND(MAX(0,MIN(100,100-SUMIFS('OWNERSHIP 1%'!$V$2:$V$10000,'OWNERSHIP 1%'!$B$2:$B$10000,$A8,'OWNERSHIP 1%'!$U$2:$U$10000,1))),2),"") -> 12.58 | C8: {=IFERROR(ROUND(SUMPRODUCT(('OWNERSHIP 1%'!$B$2:$B$10000=$A8)*('OWNERSHIP 1%'!$U$2:$U$10000=1)*('OWNERSHIP 1%'!$V$2:$V$10000)^2),0),"")} -> 3387 | D8: =IFERROR(ROUND(_xlfn.SINGLE(_xlfn.MAXIFS('OWNERSHIP 1%'!$V$2:$V$10000,'OWNERSHIP 1%'!$B$2:$B$10000,$A8,'OWNERSHIP 1%'!$U$2:$U$10000,1)),2),"") -> 57.37 | E8: =IFERROR(ROUND(SUMIFS('OWNERSHIP 1%'!$V$2:$V$7159,'OWNERSHIP 1%'!$B$2:$B$7159,$A8,'OWNERSHIP 1%'!$U$2:$U$7159,1,'OWNERSHIP 1%'!$W$2:$W$7159,"<=3"),2),"") -> 65.97 | F8: {=IFERROR(SUMPRODUCT(('OWNERSHIP 1%'!$B$2:$B$10000=$A8)*('OWNERSHIP 1%'!$U$2:$U$10000=1)*('OWNERSHIP 1%'!$V$2:$V$10000>=1)),0)} -> 12 | G8: =IFERROR(ROUND(((C8/10000)*0.45+(E8/100)*0.35+IF(F8=0,0,MAX(0,MIN(1,(20-F8)/19)))*0.2)*100,0),"") -> 47 | H8: =IF(B8="","",IF(D8>=50,"Mayoritas",IF(E8>=70,"Terkonsentrasi",IF(E8>=60,"Oligopoli",IF(E8<=40,"Tersebar","Moderat"))))) -> Mayoritas | I8: =IF(G8="","",IF(G8<=25,"Rendah",IF(G8<=55,"Sedang","Tinggi"))) -> Sedang
A9: =" "&'TICKER LIST'!B9 -> FLMC | B9: =IFERROR(ROUND(MAX(0,MIN(100,100-SUMIFS('OWNERSHIP 1%'!$V$2:$V$10000,'OWNERSHIP 1%'!$B$2:$B$10000,$A9,'OWNERSHIP 1%'!$U$2:$U$10000,1))),2),"") -> 12.93 | C9: {=IFERROR(ROUND(SUMPRODUCT(('OWNERSHIP 1%'!$B$2:$B$10000=$A9)*('OWNERSHIP 1%'!$U$2:$U$10000=1)*('OWNERSHIP 1%'!$V$2:$V$10000)^2),0),"")} -> 1769 | D9: =IFERROR(ROUND(_xlfn.SINGLE(_xlfn.MAXIFS('OWNERSHIP 1%'!$V$2:$V$10000,'OWNERSHIP 1%'!$B$2:$B$10000,$A9,'OWNERSHIP 1%'!$U$2:$U$10000,1)),2),"") -> 39.49 | E9: =IFERROR(ROUND(SUMIFS('OWNERSHIP 1%'!$V$2:$V$7159,'OWNERSHIP 1%'!$B$2:$B$7159,$A9,'OWNERSHIP 1%'!$U$2:$U$7159,1,'OWNERSHIP 1%'!$W$2:$W$7159,"<=3"),2),"") -> 50.37 | F9: {=IFERROR(SUMPRODUCT(('OWNERSHIP 1%'!$B$2:$B$10000=$A9)*('OWNERSHIP 1%'!$U$2:$U$10000=1)*('OWNERSHIP 1%'!$V$2:$V$10000>=1)),0)} -> 13 | G9: =IFERROR(ROUND(((C9/10000)*0.45+(E9/100)*0.35+IF(F9=0,0,MAX(0,MIN(1,(20-F9)/19)))*0.2)*100,0),"") -> 33 | H9: =IF(B9="","",IF(D9>=50,"Mayoritas",IF(E9>=70,"Terkonsentrasi",IF(E9>=60,"Oligopoli",IF(E9<=40,"Tersebar","Moderat"))))) -> Moderat | I9: =IF(G9="","",IF(G9<=25,"Rendah",IF(G9<=55,"Sedang","Tinggi"))) -> Sedang
A10: =" "&'TICKER LIST'!B10 -> NICL | B10: =IFERROR(ROUND(MAX(0,MIN(100,100-SUMIFS('OWNERSHIP 1%'!$V$2:$V$10000,'OWNERSHIP 1%'!$B$2:$B$10000,$A10,'OWNERSHIP 1%'!$U$2:$U$10000,1))),2),"") -> 14.43 | C10: {=IFERROR(ROUND(SUMPRODUCT(('OWNERSHIP 1%'!$B$2:$B$10000=$A10)*('OWNERSHIP 1%'!$U$2:$U$10000=1)*('OWNERSHIP 1%'!$V$2:$V$10000)^2),0),"")} -> 2740 | D10: =IFERROR(ROUND(_xlfn.SINGLE(_xlfn.MAXIFS('OWNERSHIP 1%'!$V$2:$V$10000,'OWNERSHIP 1%'!$B$2:$B$10000,$A10,'OWNERSHIP 1%'!$U$2:$U$10000,1)),2),"") -> 43.23 | E10: =IFERROR(ROUND(SUMIFS('OWNERSHIP 1%'!$V$2:$V$7159,'OWNERSHIP 1%'!$B$2:$B$7159,$A10,'OWNERSHIP 1%'!$U$2:$U$7159,1,'OWNERSHIP 1%'!$W$2:$W$7159,"<=3"),2),"") -> 75.67 | F10: {=IFERROR(SUMPRODUCT(('OWNERSHIP 1%'!$B$2:$B$10000=$A10)*('OWNERSHIP 1%'!$U$2:$U$10000=1)*('OWNERSHIP 1%'!$V$2:$V$10000>=1)),0)} -> 7 | G10: =IFERROR(ROUND(((C10/10000)*0.45+(E10/100)*0.35+IF(F10=0,0,MAX(0,MIN(1,(20-F10)/19)))*0.2)*100,0),"") -> 52 | H10: =IF(B10="","",IF(D10>=50,"Mayoritas",IF(E10>=70,"Terkonsentrasi",IF(E10>=60,"Oligopoli",IF(E10<=40,"Tersebar","Moderat"))))) -> Terkonsentrasi | I10: =IF(G10="","",IF(G10<=25,"Rendah",IF(G10<=55,"Sedang","Tinggi"))) -> Sedang
A11: =" "&'TICKER LIST'!B11 -> UVCR | B11: =IFERROR(ROUND(MAX(0,MIN(100,100-SUMIFS('OWNERSHIP 1%'!$V$2:$V$10000,'OWNERSHIP 1%'!$B$2:$B$10000,$A11,'OWNERSHIP 1%'!$U$2:$U$10000,1))),2),"") -> 33.48 | C11: {=IFERROR(ROUND(SUMPRODUCT(('OWNERSHIP 1%'!$B$2:$B$10000=$A11)*('OWNERSHIP 1%'!$U$2:$U$10000=1)*('OWNERSHIP 1%'!$V$2:$V$10000)^2),0),"")} -> 1079 | D11: =IFERROR(ROUND(_xlfn.SINGLE(_xlfn.MAXIFS('OWNERSHIP 1%'!$V$2:$V$10000,'OWNERSHIP 1%'!$B$2:$B$10000,$A11,'OWNERSHIP 1%'!$U$2:$U$10000,1)),2),"") -> 31.18 | E11: =IFERROR(ROUND(SUMIFS('OWNERSHIP 1%'!$V$2:$V$7159,'OWNERSHIP 1%'!$B$2:$B$7159,$A11,'OWNERSHIP 1%'!$U$2:$U$7159,1,'OWNERSHIP 1%'!$W$2:$W$7159,"<=3"),2),"") -> 40.01 | F11: {=IFERROR(SUMPRODUCT(('OWNERSHIP 1%'!$B$2:$B$10000=$A11)*('OWNERSHIP 1%'!$U$2:$U$10000=1)*('OWNERSHIP 1%'!$V$2:$V$10000>=1)),0)} -> 15 | G11: =IFERROR(ROUND(((C11/10000)*0.45+(E11/100)*0.35+IF(F11=0,0,MAX(0,MIN(1,(20-F11)/19)))*0.2)*100,0),"") -> 24 | H11: =IF(B11="","",IF(D11>=50,"Mayoritas",IF(E11>=70,"Terkonsentrasi",IF(E11>=60,"Oligopoli",IF(E11<=40,"Tersebar","Moderat"))))) -> Moderat | I11: =IF(G11="","",IF(G11<=25,"Rendah",IF(G11<=55,"Sedang","Tinggi"))) -> Rendah
A12: =" "&'TICKER LIST'!B12 -> BUKA | B12: =IFERROR(ROUND(MAX(0,MIN(100,100-SUMIFS('OWNERSHIP 1%'!$V$2:$V$10000,'OWNERSHIP 1%'!$B$2:$B$10000,$A12,'OWNERSHIP 1%'!$U$2:$U$10000,1))),2),"") -> 28.09 | C12: {=IFERROR(ROUND(SUMPRODUCT(('OWNERSHIP 1%'!$B$2:$B$10000=$A12)*('OWNERSHIP 1%'!$U$2:$U$10000=1)*('OWNERSHIP 1%'!$V$2:$V$10000)^2),0),"")} -> 2255 | D12: =IFERROR(ROUND(_xlfn.SINGLE(_xlfn.MAXIFS('OWNERSHIP 1%'!$V$2:$V$10000,'OWNERSHIP 1%'!$B$2:$B$10000,$A12,'OWNERSHIP 1%'!$U$2:$U$10000,1)),2),"") -> 44.9 | E12: =IFERROR(ROUND(SUMIFS('OWNERSHIP 1%'!$V$2:$V$7159,'OWNERSHIP 1%'!$B$2:$B$7159,$A12,'OWNERSHIP 1%'!$U$2:$U$7159,1,'OWNERSHIP 1%'!$W$2:$W$7159,"<=3"),2),"") -> 66.38 | F12: {=IFERROR(SUMPRODUCT(('OWNERSHIP 1%'!$B$2:$B$10000=$A12)*('OWNERSHIP 1%'!$U$2:$U$10000=1)*('OWNERSHIP 1%'!$V$2:$V$10000>=1)),0)} -> 7 | G12: =IFERROR(ROUND(((C12/10000)*0.45+(E12/100)*0.35+IF(F12=0,0,MAX(0,MIN(1,(20-F12)/19)))*0.2)*100,0),"") -> 47 | H12: =IF(B12="","",IF(D12>=50,"Mayoritas",IF(E12>=70,"Terkonsentrasi",IF(E12>=60,"Oligopoli",IF(E12<=40,"Tersebar","Moderat"))))) -> Oligopoli | I12: =IF(G12="","",IF(G12<=25,"Rendah",IF(G12<=55,"Sedang","Tinggi"))) -> Sedang
A13: =" "&'TICKER LIST'!B13 -> HAIS | B13: =IFERROR(ROUND(MAX(0,MIN(100,100-SUMIFS('OWNERSHIP 1%'!$V$2:$V$10000,'OWNERSHIP 1%'!$B$2:$B$10000,$A13,'OWNERSHIP 1%'!$U$2:$U$10000,1))),2),"") -> 10.21 | C13: {=IFERROR(ROUND(SUMPRODUCT(('OWNERSHIP 1%'!$B$2:$B$10000=$A13)*('OWNERSHIP 1%'!$U$2:$U$10000=1)*('OWNERSHIP 1%'!$V$2:$V$10000)^2),0),"")} -> 1906 | D13: =IFERROR(ROUND(_xlfn.SINGLE(_xlfn.MAXIFS('OWNERSHIP 1%'!$V$2:$V$10000,'OWNERSHIP 1%'!$B$2:$B$10000,$A13,'OWNERSHIP 1%'!$U$2:$U$10000,1)),2),"") -> 40.8 | E13: =IFERROR(ROUND(SUMIFS('OWNERSHIP 1%'!$V$2:$V$7159,'OWNERSHIP 1%'!$B$2:$B$7159,$A13,'OWNERSHIP 1%'!$U$2:$U$7159,1,'OWNERSHIP 1%'!$W$2:$W$7159,"<=3"),2),"") -> 52 | F13: {=IFERROR(SUMPRODUCT(('OWNERSHIP 1%'!$B$2:$B$10000=$A13)*('OWNERSHIP 1%'!$U$2:$U$10000=1)*('OWNERSHIP 1%'!$V$2:$V$10000>=1)),0)} -> 13 | G13: =IFERROR(ROUND(((C13/10000)*0.45+(E13/100)*0.35+IF(F13=0,0,MAX(0,MIN(1,(20-F13)/19)))*0.2)*100,0),"") -> 34 | H13: =IF(B13="","",IF(D13>=50,"Mayoritas",IF(E13>=70,"Terkonsentrasi",IF(E13>=60,"Oligopoli",IF(E13<=40,"Tersebar","Moderat"))))) -> Moderat | I13: =IF(G13="","",IF(G13<=25,"Rendah",IF(G13<=55,"Sedang","Tinggi"))) -> Sedang
... A963: =" "&'TICKER LIST'!B963 -> HOPE | B963: =IFERROR(ROUND(MAX(0,MIN(100,100-SUMIFS('OWNERSHIP 1%'!$V$2:$V$10000,'OWNERSHIP 1%'!$B$2:$B$10000,$A963,'OWNERSHIP 1%'!$U$2:$U$10000,1))),2),"") -> 22.98 | C963: {=IFERROR(ROUND(SUMPRODUCT(('OWNERSHIP 1%'!$B$2:$B$10000=$A963)*('OWNERSHIP 1%'!$U$2:$U$10000=1)*('OWNERSHIP 1%'!$V$2:$V$10000)^2),0),"")} -> 1223 | D963: =IFERROR(ROUND(_xlfn.SINGLE(_xlfn.MAXIFS('OWNERSHIP 1%'!$V$2:$V$10000,'OWNERSHIP 1%'!$B$2:$B$10000,$A963,'OWNERSHIP 1%'!$U$2:$U$10000,1)),2),"") -> 32.27 | E963: =IFERROR(ROUND(SUMIFS('OWNERSHIP 1%'!$V$2:$V$7159,'OWNERSHIP 1%'!$B$2:$B$7159,$A963,'OWNERSHIP 1%'!$U$2:$U$7159,1,'OWNERSHIP 1%'!$W$2:$W$7159,"<=3"),2),"") -> 43.52 | F963: {=IFERROR(SUMPRODUCT(('OWNERSHIP 1%'!$B$2:$B$10000=$A963)*('OWNERSHIP 1%'!$U$2:$U$10000=1)*('OWNERSHIP 1%'!$V$2:$V$10000>=1)),0)} -> 14 | G963: =IFERROR(ROUND(((C963/10000)*0.45+(E963/100)*0.35+IF(F963=0,0,MAX(0,MIN(1,(20-F963)/19)))*0.2)*100,0),"") -> 27 | H963: =IF(B963="","",IF(D963>=50,"Mayoritas",IF(E963>=70,"Terkonsentrasi",IF(E963>=60,"Oligopoli",IF(E963<=40,"Tersebar","Moderat"))))) -> Moderat | I963: =IF(G963="","",IF(G963<=25,"Rendah",IF(G963<=55,"Sedang","Tinggi"))) -> Sedang
